Workbook

Sheet SAXS
F1: DETALLE PEDIDOS CHINA (PROGRAMACION GENERAL 9-10)
A2: SALIDA | F2: 46253 | G2: 46293 | H2: 46293
A3: ENTRADA | F3: 46294 | G3: 46332 | H3: 46332 | AC3: ¿Columna N (pedidos ARNO) suma al disponible? | AD3: SI
A4: FACTURA | F4: 17035 | G4: 17106 | H4: 17107 | I4: PEDIDO | J4: PEDIDO | K4: PEDIDO | L4: PEDIDO | M4: PEDIDO | N4: PEDIDO | AC4: Meses hasta arribo G/H:
A5: ORIGEN | F5: CHINA | G5: CHINA | H5: CHINA | I5: CHINA | J5: CHINA | K5: CHINA | L5: CHINA | M5: CHINA | N5: CHINA | AC5: (se recalcula con la fecha de hoy) | AD5: =MAX(0,ROUND(($G$3-TODAY())/30.4,2)) -> 0.53
X6: Cálculo automático — Disponible (TOTAL) = STOCK + 17035 (F) + pedidos China G:M + N (si AD3=SI). Revisado 12/10.
A7: SKU | B7: CATEGORIA | C7: ARTICULO | D7: COLOR | E7: STOCK | F7: CANTIDAD | G7: CANTIDAD | H7: CANTIDAD | I7: CANTIDAD | J7: CANTIDAD | K7: CANTIDAD | L7: CANTIDAD | M7: CANTIDAD | N7: CANTIDAD | O7: ANALISIS COMPRA (vs 4 meses, automático) | P7: TOTAL | X7: VENTA PROM. m/mes (Jun-Sep) | Y7: NECESIDAD 4 MESES (m) | Z7: COBERTURA (meses) | AA7: FALTANTE (+) / SOBRANTE (−) m | AB7: SKU DUPLICADO | AC7: VENTA CONCENTRADA (1 mes >50% del período) | AD7: RIESGO QUIEBRE antes del 06/11 (stock+F17035 < venta hasta esa fecha) | AE7: VENTA SUBESTIMADA (stock 0 y Sep < 50% del prom. Feb-Ago) | AF7: VENTA PROM. AJUSTADA m/mes (si hubo quiebre: mayor entre Jun-Sep y Feb-Ago) | AG7: FALTANTE (+)/SOBRANTE (−) AJUSTADO m | AH7: SEÑAL AJUSTADA
A8: 4931098-9999 | B8: CAPELLADA | C8: CALI | D8: NEGRO | E8: 10430 | K8: 9000 | L8: 5000 | O8: =IF(A8="","SIN SKU — cargar código para calcular",IF(X8="","SIN HISTORIAL DE VENTAS — artículo nuevo o código distinto en Ventas",IF(X8=0,IF(P8>0,"SIN VENTAS Jun-Sep — no comprar ("&TEXT(P8,"#,##0")&" m disponibles)","SIN VENTAS Jun-Sep — no comprar"),IF(AA8>0.1*Y8,"COMPRAR — faltan "&TEXT(AA8,"#,##0")&" m para 4 meses"&IF(P8-E8>0," (ya contando pedidos)",""),IF(AND(-AA8>0.1*Y8,SUM(I8:M8)+IF($AD$3="SI",SUM(N8),0)>0),"PEDIR MENOS — sobran "&TEXT(-AA8,"#,##0")&" m; revisar pedidos sin facturar ("&TEXT(SUM(I8:M8)+IF($AD$3="SI",SUM(N8),0),"#,##0")&" m)",IF(Z8>8,"SOBRESTOCK — "&TEXT(Z8,"0.0")&" meses de cobertura","OK — cubierto ("&TEXT(Z8,"0.0")&" meses)")))))) -> PEDIR MENOS — sobran 3,623 m; revisar pedidos sin facturar (14,000 m) | P8: =E8+N(F8)+SUM(G8:M8)+IF($AD$3="SI",SUM(N8),0) -> 24430 | Q8: 10000 | X8: =IFERROR(VLOOKUP($A8,Ventas!$A$2:$L$5000,12,FALSE()),"") -> 5201.75 | Y8: =IF(X8="","",ROUND(X8*4,0)) -> 20807 | Z8: =IF(OR(X8="",X8=0),"",ROUND(P8/X8,1)) -> 4.7 | AA8: =IF(Y8="","",Y8-P8) -> -3623 | AB8: =IF(A8="","",IF(COUNTIF($A$8:$A$670,A8)>1,"DUPLICADO","")) | AC8: {=IF(AH8<>"COMPRAR","",IF(MAX(INDEX(Ventas!$G$2:$G$5000,MATCH($A8,Ventas!$A$2:$A$5000,0)),INDEX(Ventas!$H$2:$H$5000,MATCH($A8,Ventas!$A$2:$A$5000,0)),INDEX(Ventas!$I$2:$I$5000,MATCH($A8,Ventas!$A$2:$A$5000,0)),INDEX(Ventas!$J$2:$J$5000,MATCH($A8,Ventas!$A$2:$A$5000,0)))>0.5*AF8*4,"1 mes = "&TEXT(MAX(INDEX(Ventas!$G$2:$G$5000,MATCH($A8,Ventas!$A$2:$A$5000,0)),INDEX(Ventas!$H$2:$H$5000,MATCH($A8,Ventas!$A$2:$A$5000,0)),INDEX(Ventas!$I$2:$I$5000,MATCH($A8,Ventas!$A$2:$A$5000,0)),INDEX(Ventas!$J$2:$J$5000,MATCH($A8,Ventas!$A$2:$A$5000,0)))/(AF8*4),"0%")&" de 4 meses",""))} | AD8: =IF(OR(X8="",X8=0),"",IF(E8+N(F8)<X8*$AD$5,"SÍ — "&TEXT(E8+N(F8),"#,##0")&" m vs "&TEXT(X8*$AD$5,"#,##0")&" m","")) | AE8: {=IF(X8="","",IF(AND(E8=0,AVERAGE(INDEX(Ventas!$C$2:$I$5000,MATCH($A8,Ventas!$A$2:$A$5000,0),0))>0,INDEX(Ventas!$J$2:$J$5000,MATCH($A8,Ventas!$A$2:$A$5000,0))<0.5*AVERAGE(INDEX(Ventas!$C$2:$I$5000,MATCH($A8,Ventas!$A$2:$A$5000,0),0))),"SÍ — stock 0 y Sep cayó (prom Feb-Ago "&TEXT(AVERAGE(INDEX(Ventas!$C$2:$I$5000,MATCH($A8,Ventas!$A$2:$A$5000,0),0)),"#,##0")&")",""))} | AF8: {=IF(X8="","",IF(AE8<>"",MAX(X8,AVERAGE(INDEX(Ventas!$C$2:$I$5000,MATCH($A8,Ventas!$A$2:$A$5000,0),0))),X8))} -> 5201.75 | AG8: =IF(AF8="","",ROUND(AF8*4,0)-P8) -> -3623 | AH8: =IF(A8="","",IF(AF8="","SIN HISTORIAL",IF(AF8=0,"SIN VENTAS",IF(AG8>0.1*ROUND(AF8*4,0),"COMPRAR",IF(AND(-AG8>0.1*ROUND(AF8*4,0),SUM(I8:M8)+IF($AD$3="SI",SUM(N8),0)>0),"PEDIR MENOS",IF(P8/AF8>8,"SOBRESTOCK","OK")))))) -> PEDIR MENOS
A9: 4931098-0000 | B9: CAPELLADA | C9: CALI | D9: BLANCO | E9: 200 | H9: 2033 | K9: 2000 | O9: =IF(A9="","SIN SKU — cargar código para calcular",IF(X9="","SIN HISTORIAL DE VENTAS — artículo nuevo o código distinto en Ventas",IF(X9=0,IF(P9>0,"SIN VENTAS Jun-Sep — no comprar ("&TEXT(P9,"#,##0")&" m disponibles)","SIN VENTAS Jun-Sep — no comprar"),IF(AA9>0.1*Y9,"COMPRAR — faltan "&TEXT(AA9,"#,##0")&" m para 4 meses"&IF(P9-E9>0," (ya contando pedidos)",""),IF(AND(-AA9>0.1*Y9,SUM(I9:M9)+IF($AD$3="SI",SUM(N9),0)>0),"PEDIR MENOS — sobran "&TEXT(-AA9,"#,##0")&" m; revisar pedidos sin facturar ("&TEXT(SUM(I9:M9)+IF($AD$3="SI",SUM(N9),0),"#,##0")&" m)",IF(Z9>8,"SOBRESTOCK — "&TEXT(Z9,"0.0")&" meses de cobertura","OK — cubierto ("&TEXT(Z9,"0.0")&" meses)")))))) -> PEDIR MENOS — sobran 522 m; revisar pedidos sin facturar (2,000 m) | P9: =E9+N(F9)+SUM(G9:M9)+IF($AD$3="SI",SUM(N9),0) -> 4233 | X9: =IFERROR(VLOOKUP($A9,Ventas!$A$2:$L$5000,12,FALSE()),"") -> 927.75 | Y9: =IF(X9="","",ROUND(X9*4,0)) -> 3711 | Z9: =IF(OR(X9="",X9=0),"",ROUND(P9/X9,1)) -> 4.6 | AA9: =IF(Y9="","",Y9-P9) -> -522 | AB9: =IF(A9="","",IF(COUNTIF($A$8:$A$670,A9)>1,"DUPLICADO","")) | AC9: {=IF(AH9<>"COMPRAR","",IF(MAX(INDEX(Ventas!$G$2:$G$5000,MATCH($A9,Ventas!$A$2:$A$5000,0)),INDEX(Ventas!$H$2:$H$5000,MATCH($A9,Ventas!$A$2:$A$5000,0)),INDEX(Ventas!$I$2:$I$5000,MATCH($A9,Ventas!$A$2:$A$5000,0)),INDEX(Ventas!$J$2:$J$5000,MATCH($A9,Ventas!$A$2:$A$5000,0)))>0.5*AF9*4,"1 mes = "&TEXT(MAX(INDEX(Ventas!$G$2:$G$5000,MATCH($A9,Ventas!$A$2:$A$5000,0)),INDEX(Ventas!$H$2:$H$5000,MATCH($A9,Ventas!$A$2:$A$5000,0)),INDEX(Ventas!$I$2:$I$5000,MATCH($A9,Ventas!$A$2:$A$5000,0)),INDEX(Ventas!$J$2:$J$5000,MATCH($A9,Ventas!$A$2:$A$5000,0)))/(AF9*4),"0%")&" de 4 meses",""))} | AD9: =IF(OR(X9="",X9=0),"",IF(E9+N(F9)<X9*$AD$5,"SÍ — "&TEXT(E9+N(F9),"#,##0")&" m vs "&TEXT(X9*$AD$5,"#,##0")&" m","")) -> SÍ — 200 m vs 492 m | AE9: {=IF(X9="","",IF(AND(E9=0,AVERAGE(INDEX(Ventas!$C$2:$I$5000,MATCH($A9,Ventas!$A$2:$A$5000,0),0))>0,INDEX(Ventas!$J$2:$J$5000,MATCH($A9,Ventas!$A$2:$A$5000,0))<0.5*AVERAGE(INDEX(Ventas!$C$2:$I$5000,MATCH($A9,Ventas!$A$2:$A$5000,0),0))),"SÍ — stock 0 y Sep cayó (prom Feb-Ago "&TEXT(AVERAGE(INDEX(Ventas!$C$2:$I$5000,MATCH($A9,Ventas!$A$2:$A$5000,0),0)),"#,##0")&")",""))} | AF9: {=IF(X9="","",IF(AE9<>"",MAX(X9,AVERAGE(INDEX(Ventas!$C$2:$I$5000,MATCH($A9,Ventas!$A$2:$A$5000,0),0))),X9))} -> 927.75 | AG9: =IF(AF9="","",ROUND(AF9*4,0)-P9) -> -522 | AH9: =IF(A9="","",IF(AF9="","SIN HISTORIAL",IF(AF9=0,"SIN VENTAS",IF(AG9>0.1*ROUND(AF9*4,0),"COMPRAR",IF(AND(-AG9>0.1*ROUND(AF9*4,0),SUM(I9:M9)+IF($AD$3="SI",SUM(N9),0)>0),"PEDIR MENOS",IF(P9/AF9>8,"SOBRESTOCK","OK")))))) -> PEDIR MENOS
A10: 4931098-0697 | B10: CAPELLADA | C10: CALI | D10: SUELA OSCURO D/T | E10: 1120 | O10: =IF(A10="","SIN SKU — cargar código para calcular",IF(X10="","SIN HISTORIAL DE VENTAS — artículo nuevo o código distinto en Ventas",IF(X10=0,IF(P10>0,"SIN VENTAS Jun-Sep — no comprar ("&TEXT(P10,"#,##0")&" m disponibles)","SIN VENTAS Jun-Sep — no comprar"),IF(AA10>0.1*Y10,"COMPRAR — faltan "&TEXT(AA10,"#,##0")&" m para 4 meses"&IF(P10-E10>0," (ya contando pedidos)",""),IF(AND(-AA10>0.1*Y10,SUM(I10:M10)+IF($AD$3="SI",SUM(N10),0)>0),"PEDIR MENOS — sobran "&TEXT(-AA10,"#,##0")&" m; revisar pedidos sin facturar ("&TEXT(SUM(I10:M10)+IF($AD$3="SI",SUM(N10),0),"#,##0")&" m)",IF(Z10>8,"SOBRESTOCK — "&TEXT(Z10,"0.0")&" meses de cobertura","OK — cubierto ("&TEXT(Z10,"0.0")&" meses)")))))) -> OK — cubierto (7.0 meses) | P10: =E10+N(F10)+SUM(G10:M10)+IF($AD$3="SI",SUM(N10),0) -> 1120 | X10: =IFERROR(VLOOKUP($A10,Ventas!$A$2:$L$5000,12,FALSE()),"") -> 160.75 | Y10: =IF(X10="","",ROUND(X10*4,0)) -> 643 | Z10: =IF(OR(X10="",X10=0),"",ROUND(P10/X10,1)) -> 7 | AA10: =IF(Y10="","",Y10-P10) -> -477 | AB10: =IF(A10="","",IF(COUNTIF($A$8:$A$670,A10)>1,"DUPLICADO","")) | AC10: {=IF(AH10<>"COMPRAR","",IF(MAX(INDEX(Ventas!$G$2:$G$5000,MATCH($A10,Ventas!$A$2:$A$5000,0)),INDEX(Ventas!$H$2:$H$5000,MATCH($A10,Ventas!$A$2:$A$5000,0)),INDEX(Ventas!$I$2:$I$5000,MATCH($A10,Ventas!$A$2:$A$5000,0)),INDEX(Ventas!$J$2:$J$5000,MATCH($A10,Ventas!$A$2:$A$5000,0)))>0.5*AF10*4,"1 mes = "&TEXT(MAX(INDEX(Ventas!$G$2:$G$5000,MATCH($A10,Ventas!$A$2:$A$5000,0)),INDEX(Ventas!$H$2:$H$5000,MATCH($A10,Ventas!$A$2:$A$5000,0)),INDEX(Ventas!$I$2:$I$5000,MATCH($A10,Ventas!$A$2:$A$5000,0)),INDEX(Ventas!$J$2:$J$5000,MATCH($A10,Ventas!$A$2:$A$5000,0)))/(AF10*4),"0%")&" de 4 meses",""))} | AD10: =IF(OR(X10="",X10=0),"",IF(E10+N(F10)<X10*$AD$5,"SÍ — "&TEXT(E10+N(F10),"#,##0")&" m vs "&TEXT(X10*$AD$5,"#,##0")&" m","")) | AE10: {=IF(X10="","",IF(AND(E10=0,AVERAGE(INDEX(Ventas!$C$2:$I$5000,MATCH($A10,Ventas!$A$2:$A$5000,0),0))>0,INDEX(Ventas!$J$2:$J$5000,MATCH($A10,Ventas!$A$2:$A$5000,0))<0.5*AVERAGE(INDEX(Ventas!$C$2:$I$5000,MATCH($A10,Ventas!$A$2:$A$5000,0),0))),"SÍ — stock 0 y Sep cayó (prom Feb-Ago "&TEXT(AVERAGE(INDEX(Ventas!$C$2:$I$5000,MATCH($A10,Ventas!$A$2:$A$5000,0),0)),"#,##0")&")",""))} | AF10: {=IF(X10="","",IF(AE10<>"",MAX(X10,AVERAGE(INDEX(Ventas!$C$2:$I$5000,MATCH($A10,Ventas!$A$2:$A$5000,0),0))),X10))} -> 160.75 | AG10: =IF(AF10="","",ROUND(AF10*4,0)-P10) -> -477 | AH10: =IF(A10="","",IF(AF10="","SIN HISTORIAL",IF(AF10=0,"SIN VENTAS",IF(AG10>0.1*ROUND(AF10*4,0),"COMPRAR",IF(AND(-AG10>0.1*ROUND(AF10*4,0),SUM(I10:M10)+IF($AD$3="SI",SUM(N10),0)>0),"PEDIR MENOS",IF(P10/AF10>8,"SOBRESTOCK","OK")))))) -> OK
A11: 4931098-0597 | B11: CAPELLADA | C11: CALI | D11: SUELA D/T | E11: 0 | L11: 1000 | O11: =IF(A11="","SIN SKU — cargar código para calcular",IF(X11="","SIN HISTORIAL DE VENTAS — artículo nuevo o código distinto en Ventas",IF(X11=0,IF(P11>0,"SIN VENTAS Jun-Sep — no comprar ("&TEXT(P11,"#,##0")&" m disponibles)","SIN VENTAS Jun-Sep — no comprar"),IF(AA11>0.1*Y11,"COMPRAR — faltan "&TEXT(AA11,"#,##0")&" m para 4 meses"&IF(P11-E11>0," (ya contando pedidos)",""),IF(AND(-AA11>0.1*Y11,SUM(I11:M11)+IF($AD$3="SI",SUM(N11),0)>0),"PEDIR MENOS — sobran "&TEXT(-AA11,"#,##0")&" m; revisar pedidos sin facturar ("&TEXT(SUM(I11:M11)+IF($AD$3="SI",SUM(N11),0),"#,##0")&" m)",IF(Z11>8,"SOBRESTOCK — "&TEXT(Z11,"0.0")&" meses de cobertura","OK — cubierto ("&TEXT(Z11,"0.0")&" meses)")))))) -> OK — cubierto (3.8 meses) | P11: =E11+N(F11)+SUM(G11:M11)+IF($AD$3="SI",SUM(N11),0) -> 1000 | X11: =IFERROR(VLOOKUP($A11,Ventas!$A$2:$L$5000,12,FALSE()),"") -> 261.25 | Y11: =IF(X11="","",ROUND(X11*4,0)) -> 1045 | Z11: =IF(OR(X11="",X11=0),"",ROUND(P11/X11,1)) -> 3.8 | AA11: =IF(Y11="","",Y11-P11) -> 45 | AB11: =IF(A11="","",IF(COUNTIF($A$8:$A$670,A11)>1,"DUPLICADO","")) | AC11: {=IF(AH11<>"COMPRAR","",IF(MAX(INDEX(Ventas!$G$2:$G$5000,MATCH($A11,Ventas!$A$2:$A$5000,0)),INDEX(Ventas!$H$2:$H$5000,MATCH($A11,Ventas!$A$2:$A$5000,0)),INDEX(Ventas!$I$2:$I$5000,MATCH($A11,Ventas!$A$2:$A$5000,0)),INDEX(Ventas!$J$2:$J$5000,MATCH($A11,Ventas!$A$2:$A$5000,0)))>0.5*AF11*4,"1 mes = "&TEXT(MAX(INDEX(Ventas!$G$2:$G$5000,MATCH($A11,Ventas!$A$2:$A$5000,0)),INDEX(Ventas!$H$2:$H$5000,MATCH($A11,Ventas!$A$2:$A$5000,0)),INDEX(Ventas!$I$2:$I$5000,MATCH($A11,Ventas!$A$2:$A$5000,0)),INDEX(Ventas!$J$2:$J$5000,MATCH($A11,Ventas!$A$2:$A$5000,0)))/(AF11*4),"0%")&" de 4 meses",""))} | AD11: =IF(OR(X11="",X11=0),"",IF(E11+N(F11)<X11*$AD$5,"SÍ — "&TEXT(E11+N(F11),"#,##0")&" m vs "&TEXT(X11*$AD$5,"#,##0")&" m","")) -> SÍ — 0 m vs 138 m | AE11: {=IF(X11="","",IF(AND(E11=0,AVERAGE(INDEX(Ventas!$C$2:$I$5000,MATCH($A11,Ventas!$A$2:$A$5000,0),0))>0,INDEX(Ventas!$J$2:$J$5000,MATCH($A11,Ventas!$A$2:$A$5000,0))<0.5*AVERAGE(INDEX(Ventas!$C$2:$I$5000,MATCH($A11,Ventas!$A$2:$A$5000,0),0))),"SÍ — stock 0 y Sep cayó (prom Feb-Ago "&TEXT(AVERAGE(INDEX(Ventas!$C$2:$I$5000,MATCH($A11,Ventas!$A$2:$A$5000,0),0)),"#,##0")&")",""))} -> SÍ — stock 0 y Sep cayó (prom Feb-Ago 344) | AF11: {=IF(X11="","",IF(AE11<>"",MAX(X11,AVERAGE(INDEX(Ventas!$C$2:$I$5000,MATCH($A11,Ventas!$A$2:$A$5000,0),0))),X11))} -> 343.57143 | AG11: =IF(AF11="","",ROUND(AF11*4,0)-P11) -> 374 | AH11: =IF(A11="","",IF(AF11="","SIN HISTORIAL",IF(AF11=0,"SIN VENTAS",IF(AG11>0.1*ROUND(AF11*4,0),"COMPRAR",IF(AND(-AG11>0.1*ROUND(AF11*4,0),SUM(I11:M11)+IF($AD$3="SI",SUM(N11),0)>0),"PEDIR MENOS",IF(P11/AF11>8,"SOBRESTOCK","OK")))))) -> COMPRAR
A12: 4931098-0047 | B12: CAPELLADA | C12: CALI | D12: VISON | E12: 40 | L12: 800 | O12: =IF(A12="","SIN SKU — cargar código para calcular",IF(X12="","SIN HISTORIAL DE VENTAS — artículo nuevo o código distinto en Ventas",IF(X12=0,IF(P12>0,"SIN VENTAS Jun-Sep — no comprar ("&TEXT(P12,"#,##0")&" m disponibles)","SIN VENTAS Jun-Sep — no comprar"),IF(AA12>0.1*Y12,"COMPRAR — faltan "&TEXT(AA12,"#,##0")&" m para 4 meses"&IF(P12-E12>0," (ya contando pedidos)",""),IF(AND(-AA12>0.1*Y12,SUM(I12:M12)+IF($AD$3="SI",SUM(N12),0)>0),"PEDIR MENOS — sobran "&TEXT(-AA12,"#,##0")&" m; revisar pedidos sin facturar ("&TEXT(SUM(I12:M12)+IF($AD$3="SI",SUM(N12),0),"#,##0")&" m)",IF(Z12>8,"SOBRESTOCK — "&TEXT(Z12,"0.0")&" meses de cobertura","OK — cubierto ("&TEXT(Z12,"0.0")&" meses)")))))) -> PEDIR MENOS — sobran 560 m; revisar pedidos sin facturar (800 m) | P12: =E12+N(F12)+SUM(G12:M12)+IF($AD$3="SI",SUM(N12),0) -> 840 | X12: =IFERROR(VLOOKUP($A12,Ventas!$A$2:$L$5000,12,FALSE()),"") -> 70 | Y12: =IF(X12="","",ROUND(X12*4,0)) -> 280 | Z12: =IF(OR(X12="",X12=0),"",ROUND(P12/X12,1)) -> 12 | AA12: =IF(Y12="","",Y12-P12) -> -560 | AB12: =IF(A12="","",IF(COUNTIF($A$8:$A$670,A12)>1,"DUPLICADO","")) | AC12: {=IF(AH12<>"COMPRAR","",IF(MAX(INDEX(Ventas!$G$2:$G$5000,MATCH($A12,Ventas!$A$2:$A$5000,0)),INDEX(Ventas!$H$2:$H$5000,MATCH($A12,Ventas!$A$2:$A$5000,0)),INDEX(Ventas!$I$2:$I$5000,MATCH($A12,Ventas!$A$2:$A$5000,0)),INDEX(Ventas!$J$2:$J$5000,MATCH($A12,Ventas!$A$2:$A$5000,0)))>0.5*AF12*4,"1 mes = "&TEXT(MAX(INDEX(Ventas!$G$2:$G$5000,MATCH($A12,Ventas!$A$2:$A$5000,0)),INDEX(Ventas!$H$2:$H$5000,MATCH($A12,Ventas!$A$2:$A$5000,0)),INDEX(Ventas!$I$2:$I$5000,MATCH($A12,Ventas!$A$2:$A$5000,0)),INDEX(Ventas!$J$2:$J$5000,MATCH($A12,Ventas!$A$2:$A$5000,0)))/(AF12*4),"0%")&" de 4 meses",""))} | AD12: =IF(OR(X12="",X12=0),"",IF(E12+N(F12)<X12*$AD$5,"SÍ — "&TEXT(E12+N(F12),"#,##0")&" m vs "&TEXT(X12*$AD$5,"#,##0")&" m","")) | AE12: {=IF(X12="","",IF(AND(E12=0,AVERAGE(INDEX(Ventas!$C$2:$I$5000,MATCH($A12,Ventas!$A$2:$A$5000,0),0))>0,INDEX(Ventas!$J$2:$J$5000,MATCH($A12,Ventas!$A$2:$A$5000,0))<0.5*AVERAGE(INDEX(Ventas!$C$2:$I$5000,MATCH($A12,Ventas!$A$2:$A$5000,0),0))),"SÍ — stock 0 y Sep cayó (prom Feb-Ago "&TEXT(AVERAGE(INDEX(Ventas!$C$2:$I$5000,MATCH($A12,Ventas!$A$2:$A$5000,0),0)),"#,##0")&")",""))} | AF12: {=IF(X12="","",IF(AE12<>"",MAX(X12,AVERAGE(INDEX(Ventas!$C$2:$I$5000,MATCH($A12,Ventas!$A$2:$A$5000,0),0))),X12))} -> 70 | AG12: =IF(AF12="","",ROUND(AF12*4,0)-P12) -> -560 | AH12: =IF(A12="","",IF(AF12="","SIN HISTORIAL",IF(AF12=0,"SIN VENTAS",IF(AG12>0.1*ROUND(AF12*4,0),"COMPRAR",IF(AND(-AG12>0.1*ROUND(AF12*4,0),SUM(I12:M12)+IF($AD$3="SI",SUM(N12),0)>0),"PEDIR MENOS",IF(P12/AF12>8,"SOBRESTOCK","OK")))))) -> PEDIR MENOS
B13: CAPELLADA | C13: CALI | D13: BORDO | L13: 800 | O13: =IF(A13="","SIN SKU — cargar código para calcular",IF(X13="","SIN HISTORIAL DE VENTAS — artículo nuevo o código distinto en Ventas",IF(X13=0,IF(P13>0,"SIN VENTAS Jun-Sep — no comprar ("&TEXT(P13,"#,##0")&" m disponibles)","SIN VENTAS Jun-Sep — no comprar"),IF(AA13>0.1*Y13,"COMPRAR — faltan "&TEXT(AA13,"#,##0")&" m para 4 meses"&IF(P13-E13>0," (ya contando pedidos)",""),IF(AND(-AA13>0.1*Y13,SUM(I13:M13)+IF($AD$3="SI",SUM(N13),0)>0),"PEDIR MENOS — sobran "&TEXT(-AA13,"#,##0")&" m; revisar pedidos sin facturar ("&TEXT(SUM(I13:M13)+IF($AD$3="SI",SUM(N13),0),"#,##0")&" m)",IF(Z13>8,"SOBRESTOCK — "&TEXT(Z13,"0.0")&" meses de cobertura","OK — cubierto ("&TEXT(Z13,"0.0")&" meses)")))))) -> SIN SKU — cargar código para calcular | P13: =E13+N(F13)+SUM(G13:M13)+IF($AD$3="SI",SUM(N13),0) -> 800 | X13: =IFERROR(VLOOKUP($A13,Ventas!$A$2:$L$5000,12,FALSE()),"") | Y13: =IF(X13="","",ROUND(X13*4,0)) | Z13: =IF(OR(X13="",X13=0),"",ROUND(P13/X13,1)) | AA13: =IF(Y13="","",Y13-P13) | AB13: =IF(A13="","",IF(COUNTIF($A$8:$A$670,A13)>1,"DUPLICADO","")) | AC13: {=IF(AH13<>"COMPRAR","",IF(MAX(INDEX(Ventas!$G$2:$G$5000,MATCH($A13,Ventas!$A$2:$A$5000,0)),INDEX(Ventas!$H$2:$H$5000,MATCH($A13,Ventas!$A$2:$A$5000,0)),INDEX(Ventas!$I$2:$I$5000,MATCH($A13,Ventas!$A$2:$A$5000,0)),INDEX(Ventas!$J$2:$J$5000,MATCH($A13,Ventas!$A$2:$A$5000,0)))>0.5*AF13*4,"1 mes = "&TEXT(MAX(INDEX(Ventas!$G$2:$G$5000,MATCH($A13,Ventas!$A$2:$A$5000,0)),INDEX(Ventas!$H$2:$H$5000,MATCH($A13,Ventas!$A$2:$A$5000,0)),INDEX(Ventas!$I$2:$I$5000,MATCH($A13,Ventas!$A$2:$A$5000,0)),INDEX(Ventas!$J$2:$J$5000,MATCH($A13,Ventas!$A$2:$A$5000,0)))/(AF13*4),"0%")&" de 4 meses",""))} | AD13: =IF(OR(X13="",X13=0),"",IF(E13+N(F13)<X13*$AD$5,"SÍ — "&TEXT(E13+N(F13),"#,##0")&" m vs "&TEXT(X13*$AD$5,"#,##0")&" m","")) | AE13: {=IF(X13="","",IF(AND(E13=0,AVERAGE(INDEX(Ventas!$C$2:$I$5000,MATCH($A13,Ventas!$A$2:$A$5000,0),0))>0,INDEX(Ventas!$J$2:$J$5000,MATCH($A13,Ventas!$A$2:$A$5000,0))<0.5*AVERAGE(INDEX(Ventas!$C$2:$I$5000,MATCH($A13,Ventas!$A$2:$A$5000,0),0))),"SÍ — stock 0 y Sep cayó (prom Feb-Ago "&TEXT(AVERAGE(INDEX(Ventas!$C$2:$I$5000,MATCH($A13,Ventas!$A$2:$A$5000,0),0)),"#,##0")&")",""))} | AF13: {=IF(X13="","",IF(AE13<>"",MAX(X13,AVERAGE(INDEX(Ventas!$C$2:$I$5000,MATCH($A13,Ventas!$A$2:$A$5000,0),0))),X13))} | AG13: =IF(AF13="","",ROUND(AF13*4,0)-P13) | AH13: =IF(A13="","",IF(AF13="","SIN HISTORIAL",IF(AF13=0,"SIN VENTAS",IF(AG13>0.1*ROUND(AF13*4,0),"COMPRAR",IF(AND(-AG13>0.1*ROUND(AF13*4,0),SUM(I13:M13)+IF($AD$3="SI",SUM(N13),0)>0),"PEDIR MENOS",IF(P13/AF13>8,"SOBRESTOCK","OK"))))))
A14: 4931098-0159 | B14: CAPELLADA | C14: CALI | D14: NUDE | E14: 1084 | O14: =IF(A14="","SIN SKU — cargar código para calcular",IF(X14="","SIN HISTORIAL DE VENTAS — artículo nuevo o código distinto en Ventas",IF(X14=0,IF(P14>0,"SIN VENTAS Jun-Sep — no comprar ("&TEXT(P14,"#,##0")&" m disponibles)","SIN VENTAS Jun-Sep — no comprar"),IF(AA14>0.1*Y14,"COMPRAR — faltan "&TEXT(AA14,"#,##0")&" m para 4 meses"&IF(P14-E14>0," (ya contando pedidos)",""),IF(AND(-AA14>0.1*Y14,SUM(I14:M14)+IF($AD$3="SI",SUM(N14),0)>0),"PEDIR MENOS — sobran "&TEXT(-AA14,"#,##0")&" m; revisar pedidos sin facturar ("&TEXT(SUM(I14:M14)+IF($AD$3="SI",SUM(N14),0),"#,##0")&" m)",IF(Z14>8,"SOBRESTOCK — "&TEXT(Z14,"0.0")&" meses de cobertura","OK — cubierto ("&TEXT(Z14,"0.0")&" meses)")))))) -> SOBRESTOCK — 15.5 meses de cobertura | P14: =E14+N(F14)+SUM(G14:M14)+IF($AD$3="SI",SUM(N14),0) -> 1084 | X14: =IFERROR(VLOOKUP($A14,Ventas!$A$2:$L$5000,12,FALSE()),"") -> 70 | Y14: =IF(X14="","",ROUND(X14*4,0)) -> 280 | Z14: =IF(OR(X14="",X14=0),"",ROUND(P14/X14,1)) -> 15.5 | AA14: =IF(Y14="","",Y14-P14) -> -804 | AB14: =IF(A14="","",IF(COUNTIF($A$8:$A$670,A14)>1,"DUPLICADO","")) | AC14: {=IF(AH14<>"COMPRAR","",IF(MAX(INDEX(Ventas!$G$2:$G$5000,MATCH($A14,Ventas!$A$2:$A$5000,0)),INDEX(Ventas!$H$2:$H$5000,MATCH($A14,Ventas!$A$2:$A$5000,0)),INDEX(Ventas!$I$2:$I$5000,MATCH($A14,Ventas!$A$2:$A$5000,0)),INDEX(Ventas!$J$2:$J$5000,MATCH($A14,Ventas!$A$2:$A$5000,0)))>0.5*AF14*4,"1 mes = "&TEXT(MAX(INDEX(Ventas!$G$2:$G$5000,MATCH($A14,Ventas!$A$2:$A$5000,0)),INDEX(Ventas!$H$2:$H$5000,MATCH($A14,Ventas!$A$2:$A$5000,0)),INDEX(Ventas!$I$2:$I$5000,MATCH($A14,Ventas!$A$2:$A$5000,0)),INDEX(Ventas!$J$2:$J$5000,MATCH($A14,Ventas!$A$2:$A$5000,0)))/(AF14*4),"0%")&" de 4 meses",""))} | AD14: =IF(OR(X14="",X14=0),"",IF(E14+N(F14)<X14*$AD$5,"SÍ — "&TEXT(E14+N(F14),"#,##0")&" m vs "&TEXT(X14*$AD$5,"#,##0")&" m","")) | AE14: {=IF(X14="","",IF(AND(E14=0,AVERAGE(INDEX(Ventas!$C$2:$I$5000,MATCH($A14,Ventas!$A$2:$A$5000,0),0))>0,INDEX(Ventas!$J$2:$J$5000,MATCH($A14,Ventas!$A$2:$A$5000,0))<0.5*AVERAGE(INDEX(Ventas!$C$2:$I$5000,MATCH($A14,Ventas!$A$2:$A$5000,0),0))),"SÍ — stock 0 y Sep cayó (prom Feb-Ago "&TEXT(AVERAGE(INDEX(Ventas!$C$2:$I$5000,MATCH($A14,Ventas!$A$2:$A$5000,0),0)),"#,##0")&")",""))} | AF14: {=IF(X14="","",IF(AE14<>"",MAX(X14,AVERAGE(INDEX(Ventas!$C$2:$I$5000,MATCH($A14,Ventas!$A$2:$A$5000,0),0))),X14))} -> 70 | AG14: =IF(AF14="","",ROUND(AF14*4,0)-P14) -> -804 | AH14: =IF(A14="","",IF(AF14="","SIN HISTORIAL",IF(AF14=0,"SIN VENTAS",IF(AG14>0.1*ROUND(AF14*4,0),"COMPRAR",IF(AND(-AG14>0.1*ROUND(AF14*4,0),SUM(I14:M14)+IF($AD$3="SI",SUM(N14),0)>0),"PEDIR MENOS",IF(P14/AF14>8,"SOBRESTOCK","OK")))))) -> SOBRESTOCK
A15: 4931098-0198 | B15: CAPELLADA | C15: CALI | D15: MANTECA | E15: 1960 | O15: =IF(A15="","SIN SKU — cargar código para calcular",IF(X15="","SIN HISTORIAL DE VENTAS — artículo nuevo o código distinto en Ventas",IF(X15=0,IF(P15>0,"SIN VENTAS Jun-Sep — no comprar ("&TEXT(P15,"#,##0")&" m disponibles)","SIN VENTAS Jun-Sep — no comprar"),IF(AA15>0.1*Y15,"COMPRAR — faltan "&TEXT(AA15,"#,##0")&" m para 4 meses"&IF(P15-E15>0," (ya contando pedidos)",""),IF(AND(-AA15>0.1*Y15,SUM(I15:M15)+IF($AD$3="SI",SUM(N15),0)>0),"PEDIR MENOS — sobran "&TEXT(-AA15,"#,##0")&" m; revisar pedidos sin facturar ("&TEXT(SUM(I15:M15)+IF($AD$3="SI",SUM(N15),0),"#,##0")&" m)",IF(Z15>8,"SOBRESTOCK — "&TEXT(Z15,"0.0")&" meses de cobertura","OK — cubierto ("&TEXT(Z15,"0.0")&" meses)")))))) -> SOBRESTOCK — 11.5 meses de cobertura | P15: =E15+N(F15)+SUM(G15:M15)+IF($AD$3="SI",SUM(N15),0) -> 1960 | X15: =IFERROR(VLOOKUP($A15,Ventas!$A$2:$L$5000,12,FALSE()),"") -> 170 | Y15: =IF(X15="","",ROUND(X15*4,0)) -> 680 | Z15: =IF(OR(X15="",X15=0),"",ROUND(P15/X15,1)) -> 11.5 | AA15: =IF(Y15="","",Y15-P15) -> -1280 | AB15: =IF(A15="","",IF(COUNTIF($A$8:$A$670,A15)>1,"DUPLICADO","")) | AC15: {=IF(AH15<>"COMPRAR","",IF(MAX(INDEX(Ventas!$G$2:$G$5000,MATCH($A15,Ventas!$A$2:$A$5000,0)),INDEX(Ventas!$H$2:$H$5000,MATCH($A15,Ventas!$A$2:$A$5000,0)),INDEX(Ventas!$I$2:$I$5000,MATCH($A15,Ventas!$A$2:$A$5000,0)),INDEX(Ventas!$J$2:$J$5000,MATCH($A15,Ventas!$A$2:$A$5000,0)))>0.5*AF15*4,"1 mes = "&TEXT(MAX(INDEX(Ventas!$G$2:$G$5000,MATCH($A15,Ventas!$A$2:$A$5000,0)),INDEX(Ventas!$H$2:$H$5000,MATCH($A15,Ventas!$A$2:$A$5000,0)),INDEX(Ventas!$I$2:$I$5000,MATCH($A15,Ventas!$A$2:$A$5000,0)),INDEX(Ventas!$J$2:$J$5000,MATCH($A15,Ventas!$A$2:$A$5000,0)))/(AF15*4),"0%")&" de 4 meses",""))} | AD15: =IF(OR(X15="",X15=0),"",IF(E15+N(F15)<X15*$AD$5,"SÍ — "&TEXT(E15+N(F15),"#,##0")&" m vs "&TEXT(X15*$AD$5,"#,##0")&" m","")) | AE15: {=IF(X15="","",IF(AND(E15=0,AVERAGE(INDEX(Ventas!$C$2:$I$5000,MATCH($A15,Ventas!$A$2:$A$5000,0),0))>0,INDEX(Ventas!$J$2:$J$5000,MATCH($A15,Ventas!$A$2:$A$5000,0))<0.5*AVERAGE(INDEX(Ventas!$C$2:$I$5000,MATCH($A15,Ventas!$A$2:$A$5000,0),0))),"SÍ — stock 0 y Sep cayó (prom Feb-Ago "&TEXT(AVERAGE(INDEX(Ventas!$C$2:$I$5000,MATCH($A15,Ventas!$A$2:$A$5000,0),0)),"#,##0")&")",""))} | AF15: {=IF(X15="","",IF(AE15<>"",MAX(X15,AVERAGE(INDEX(Ventas!$C$2:$I$5000,MATCH($A15,Ventas!$A$2:$A$5000,0),0))),X15))} -> 170 | AG15: =IF(AF15="","",ROUND(AF15*4,0)-P15) -> -1280 | AH15: =IF(A15="","",IF(AF15="","SIN HISTORIAL",IF(AF15=0,"SIN VENTAS",IF(AG15>0.1*ROUND(AF15*4,0),"COMPRAR",IF(AND(-AG15>0.1*ROUND(AF15*4,0),SUM(I15:M15)+IF($AD$3="SI",SUM(N15),0)>0),"PEDIR MENOS",IF(P15/AF15>8,"SOBRESTOCK","OK")))))) -> SOBRESTOCK
A16: 4931098-0156 | B16: CAPELLADA | C16: CALI | D16: OLIVA | E16: 520 | O16: =IF(A16="","SIN SKU — cargar código para calcular",IF(X16="","SIN HISTORIAL DE VENTAS — artículo nuevo o código distinto en Ventas",IF(X16=0,IF(P16>0,"SIN VENTAS Jun-Sep — no comprar ("&TEXT(P16,"#,##0")&" m disponibles)","SIN VENTAS Jun-Sep — no comprar"),IF(AA16>0.1*Y16,"COMPRAR — faltan "&TEXT(AA16,"#,##0")&" m para 4 meses"&IF(P16-E16>0," (ya contando pedidos)",""),IF(AND(-AA16>0.1*Y16,SUM(I16:M16)+IF($AD$3="SI",SUM(N16),0)>0),"PEDIR MENOS — sobran "&TEXT(-AA16,"#,##0")&" m; revisar pedidos sin facturar ("&TEXT(SUM(I16:M16)+IF($AD$3="SI",SUM(N16),0),"#,##0")&" m)",IF(Z16>8,"SOBRESTOCK — "&TEXT(Z16,"0.0")&" meses de cobertura","OK — cubierto ("&TEXT(Z16,"0.0")&" meses)")))))) -> OK — cubierto (7.4 meses) | P16: =E16+N(F16)+SUM(G16:M16)+IF($AD$3="SI",SUM(N16),0) -> 520 | X16: =IFERROR(VLOOKUP($A16,Ventas!$A$2:$L$5000,12,FALSE()),"") -> 70 | Y16: =IF(X16="","",ROUND(X16*4,0)) -> 280 | Z16: =IF(OR(X16="",X16=0),"",ROUND(P16/X16,1)) -> 7.4 | AA16: =IF(Y16="","",Y16-P16) -> -240 | AB16: =IF(A16="","",IF(COUNTIF($A$8:$A$670,A16)>1,"DUPLICADO","")) | AC16: {=IF(AH16<>"COMPRAR","",IF(MAX(INDEX(Ventas!$G$2:$G$5000,MATCH($A16,Ventas!$A$2:$A$5000,0)),INDEX(Ventas!$H$2:$H$5000,MATCH($A16,Ventas!$A$2:$A$5000,0)),INDEX(Ventas!$I$2:$I$5000,MATCH($A16,Ventas!$A$2:$A$5000,0)),INDEX(Ventas!$J$2:$J$5000,MATCH($A16,Ventas!$A$2:$A$5000,0)))>0.5*AF16*4,"1 mes = "&TEXT(MAX(INDEX(Ventas!$G$2:$G$5000,MATCH($A16,Ventas!$A$2:$A$5000,0)),INDEX(Ventas!$H$2:$H$5000,MATCH($A16,Ventas!$A$2:$A$5000,0)),INDEX(Ventas!$I$2:$I$5000,MATCH($A16,Ventas!$A$2:$A$5000,0)),INDEX(Ventas!$J$2:$J$5000,MATCH($A16,Ventas!$A$2:$A$5000,0)))/(AF16*4),"0%")&" de 4 meses",""))} | AD16: =IF(OR(X16="",X16=0),"",IF(E16+N(F16)<X16*$AD$5,"SÍ — "&TEXT(E16+N(F16),"#,##0")&" m vs "&TEXT(X16*$AD$5,"#,##0")&" m","")) | AE16: {=IF(X16="","",IF(AND(E16=0,AVERAGE(INDEX(Ventas!$C$2:$I$5000,MATCH($A16,Ventas!$A$2:$A$5000,0),0))>0,INDEX(Ventas!$J$2:$J$5000,MATCH($A16,Ventas!$A$2:$A$5000,0))<0.5*AVERAGE(INDEX(Ventas!$C$2:$I$5000,MATCH($A16,Ventas!$A$2:$A$5000,0),0))),"SÍ — stock 0 y Sep cayó (prom Feb-Ago "&TEXT(AVERAGE(INDEX(Ventas!$C$2:$I$5000,MATCH($A16,Ventas!$A$2:$A$5000,0),0)),"#,##0")&")",""))} | AF16: {=IF(X16="","",IF(AE16<>"",MAX(X16,AVERAGE(INDEX(Ventas!$C$2:$I$5000,MATCH($A16,Ventas!$A$2:$A$5000,0),0))),X16))} -> 70 | AG16: =IF(AF16="","",ROUND(AF16*4,0)-P16) -> -240 | AH16: =IF(A16="","",IF(AF16="","SIN HISTORIAL",IF(AF16=0,"SIN VENTAS",IF(AG16>0.1*ROUND(AF16*4,0),"COMPRAR",IF(AND(-AG16>0.1*ROUND(AF16*4,0),SUM(I16:M16)+IF($AD$3="SI",SUM(N16),0)>0),"PEDIR MENOS",IF(P16/AF16>8,"SOBRESTOCK","OK")))))) -> OK
A17: 4931098-0069 | B17: CAPELLADA | C17: CALI | D17: MIEL | E17: 1893 | O17: =IF(A17="","SIN SKU — cargar código para calcular",IF(X17="","SIN HISTORIAL DE VENTAS — artículo nuevo o código distinto en Ventas",IF(X17=0,IF(P17>0,"SIN VENTAS Jun-Sep — no comprar ("&TEXT(P17,"#,##0")&" m disponibles)","SIN VENTAS Jun-Sep — no comprar"),IF(AA17>0.1*Y17,"COMPRAR — faltan "&TEXT(AA17,"#,##0")&" m para 4 meses"&IF(P17-E17>0," (ya contando pedidos)",""),IF(AND(-AA17>0.1*Y17,SUM(I17:M17)+IF($AD$3="SI",SUM(N17),0)>0),"PEDIR MENOS — sobran "&TEXT(-AA17,"#,##0")&" m; revisar pedidos sin facturar ("&TEXT(SUM(I17:M17)+IF($AD$3="SI",SUM(N17),0),"#,##0")&" m)",IF(Z17>8,"SOBRESTOCK — "&TEXT(Z17,"0.0")&" meses de cobertura","OK — cubierto ("&TEXT(Z17,"0.0")&" meses)")))))) -> SOBRESTOCK — 9.5 meses de cobertura | P17: =E17+N(F17)+SUM(G17:M17)+IF($AD$3="SI",SUM(N17),0) -> 1893 | X17: =IFERROR(VLOOKUP($A17,Ventas!$A$2:$L$5000,12,FALSE()),"") -> 200 | Y17: =IF(X17="","",ROUND(X17*4,0)) -> 800 | Z17: =IF(OR(X17="",X17=0),"",ROUND(P17/X17,1)) -> 9.5 | AA17: =IF(Y17="","",Y17-P17) -> -1093 | AB17: =IF(A17="","",IF(COUNTIF($A$8:$A$670,A17)>1,"DUPLICADO","")) | AC17: {=IF(AH17<>"COMPRAR","",IF(MAX(INDEX(Ventas!$G$2:$G$5000,MATCH($A17,Ventas!$A$2:$A$5000,0)),INDEX(Ventas!$H$2:$H$5000,MATCH($A17,Ventas!$A$2:$A$5000,0)),INDEX(Ventas!$I$2:$I$5000,MATCH($A17,Ventas!$A$2:$A$5000,0)),INDEX(Ventas!$J$2:$J$5000,MATCH($A17,Ventas!$A$2:$A$5000,0)))>0.5*AF17*4,"1 mes = "&TEXT(MAX(INDEX(Ventas!$G$2:$G$5000,MATCH($A17,Ventas!$A$2:$A$5000,0)),INDEX(Ventas!$H$2:$H$5000,MATCH($A17,Ventas!$A$2:$A$5000,0)),INDEX(Ventas!$I$2:$I$5000,MATCH($A17,Ventas!$A$2:$A$5000,0)),INDEX(Ventas!$J$2:$J$5000,MATCH($A17,Ventas!$A$2:$A$5000,0)))/(AF17*4),"0%")&" de 4 meses",""))} | AD17: =IF(OR(X17="",X17=0),"",IF(E17+N(F17)<X17*$AD$5,"SÍ — "&TEXT(E17+N(F17),"#,##0")&" m vs "&TEXT(X17*$AD$5,"#,##0")&" m","")) | AE17: {=IF(X17="","",IF(AND(E17=0,AVERAGE(INDEX(Ventas!$C$2:$I$5000,MATCH($A17,Ventas!$A$2:$A$5000,0),0))>0,INDEX(Ventas!$J$2:$J$5000,MATCH($A17,Ventas!$A$2:$A$5000,0))<0.5*AVERAGE(INDEX(Ventas!$C$2:$I$5000,MATCH($A17,Ventas!$A$2:$A$5000,0),0))),"SÍ — stock 0 y Sep cayó (prom Feb-Ago "&TEXT(AVERAGE(INDEX(Ventas!$C$2:$I$5000,MATCH($A17,Ventas!$A$2:$A$5000,0),0)),"#,##0")&")",""))} | AF17: {=IF(X17="","",IF(AE17<>"",MAX(X17,AVERAGE(INDEX(Ventas!$C$2:$I$5000,MATCH($A17,Ventas!$A$2:$A$5000,0),0))),X17))} -> 200 | AG17: =IF(AF17="","",ROUND(AF17*4,0)-P17) -> -1093 | AH17: =IF(A17="","",IF(AF17="","SIN HISTORIAL",IF(AF17=0,"SIN VENTAS",IF(AG17>0.1*ROUND(AF17*4,0),"COMPRAR",IF(AND(-AG17>0.1*ROUND(AF17*4,0),SUM(I17:M17)+IF($AD$3="SI",SUM(N17),0)>0),"PEDIR MENOS",IF(P17/AF17>8,"SOBRESTOCK","OK")))))) -> SOBRESTOCK
A18: 4931098-0019 | B18: CAPELLADA | C18: CALI | D18: NARANJA | E18: 512 | O18: =IF(A18="","SIN SKU — cargar código para calcular",IF(X18="","SIN HISTORIAL DE VENTAS — artículo nuevo o código distinto en Ventas",IF(X18=0,IF(P18>0,"SIN VENTAS Jun-Sep — no comprar ("&TEXT(P18,"#,##0")&" m disponibles)","SIN VENTAS Jun-Sep — no comprar"),IF(AA18>0.1*Y18,"COMPRAR — faltan "&TEXT(AA18,"#,##0")&" m para 4 meses"&IF(P18-E18>0," (ya contando pedidos)",""),IF(AND(-AA18>0.1*Y18,SUM(I18:M18)+IF($AD$3="SI",SUM(N18),0)>0),"PEDIR MENOS — sobran "&TEXT(-AA18,"#,##0")&" m; revisar pedidos sin facturar ("&TEXT(SUM(I18:M18)+IF($AD$3="SI",SUM(N18),0),"#,##0")&" m)",IF(Z18>8,"SOBRESTOCK — "&TEXT(Z18,"0.0")&" meses de cobertura","OK — cubierto ("&TEXT(Z18,"0.0")&" meses)")))))) -> SIN VENTAS Jun-Sep — no comprar (512 m disponibles) | P18: =E18+N(F18)+SUM(G18:M18)+IF($AD$3="SI",SUM(N18),0) -> 512 | X18: =IFERROR(VLOOKUP($A18,Ventas!$A$2:$L$5000,12,FALSE()),"") -> 0 | Y18: =IF(X18="","",ROUND(X18*4,0)) -> 0 | Z18: =IF(OR(X18="",X18=0),"",ROUND(P18/X18,1)) | AA18: =IF(Y18="","",Y18-P18) -> -512 | AB18: =IF(A18="","",IF(COUNTIF($A$8:$A$670,A18)>1,"DUPLICADO","")) | AC18: {=IF(AH18<>"COMPRAR","",IF(MAX(INDEX(Ventas!$G$2:$G$5000,MATCH($A18,Ventas!$A$2:$A$5000,0)),INDEX(Ventas!$H$2:$H$5000,MATCH($A18,Ventas!$A$2:$A$5000,0)),INDEX(Ventas!$I$2:$I$5000,MATCH($A18,Ventas!$A$2:$A$5000,0)),INDEX(Ventas!$J$2:$J$5000,MATCH($A18,Ventas!$A$2:$A$5000,0)))>0.5*AF18*4,"1 mes = "&TEXT(MAX(INDEX(Ventas!$G$2:$G$5000,MATCH($A18,Ventas!$A$2:$A$5000,0)),INDEX(Ventas!$H$2:$H$5000,MATCH($A18,Ventas!$A$2:$A$5000,0)),INDEX(Ventas!$I$2:$I$5000,MATCH($A18,Ventas!$A$2:$A$5000,0)),INDEX(Ventas!$J$2:$J$5000,MATCH($A18,Ventas!$A$2:$A$5000,0)))/(AF18*4),"0%")&" de 4 meses",""))} | AD18: =IF(OR(X18="",X18=0),"",IF(E18+N(F18)<X18*$AD$5,"SÍ — "&TEXT(E18+N(F18),"#,##0")&" m vs "&TEXT(X18*$AD$5,"#,##0")&" m","")) | AE18: {=IF(X18="","",IF(AND(E18=0,AVERAGE(INDEX(Ventas!$C$2:$I$5000,MATCH($A18,Ventas!$A$2:$A$5000,0),0))>0,INDEX(Ventas!$J$2:$J$5000,MATCH($A18,Ventas!$A$2:$A$5000,0))<0.5*AVERAGE(INDEX(Ventas!$C$2:$I$5000,MATCH($A18,Ventas!$A$2:$A$5000,0),0))),"SÍ — stock 0 y Sep cayó (prom Feb-Ago "&TEXT(AVERAGE(INDEX(Ventas!$C$2:$I$5000,MATCH($A18,Ventas!$A$2:$A$5000,0),0)),"#,##0")&")",""))} | AF18: {=IF(X18="","",IF(AE18<>"",MAX(X18,AVERAGE(INDEX(Ventas!$C$2:$I$5000,MATCH($A18,Ventas!$A$2:$A$5000,0),0))),X18))} -> 0 | AG18: =IF(AF18="","",ROUND(AF18*4,0)-P18) -> -512 | AH18: =IF(A18="","",IF(AF18="","SIN HISTORIAL",IF(AF18=0,"SIN VENTAS",IF(AG18>0.1*ROUND(AF18*4,0),"COMPRAR",IF(AND(-AG18>0.1*ROUND(AF18*4,0),SUM(I18:M18)+IF($AD$3="SI",SUM(N18),0)>0),"PEDIR MENOS",IF(P18/AF18>8,"SOBRESTOCK","OK")))))) -> SIN VENTAS
A19: 4931098-0193 | B19: CAPELLADA | C19: CALI | D19: VERDE BENETTON | E19: 440 | O19: =IF(A19="","SIN SKU — cargar código para calcular",IF(X19="","SIN HISTORIAL DE VENTAS — artículo nuevo o código distinto en Ventas",IF(X19=0,IF(P19>0,"SIN VENTAS Jun-Sep — no comprar ("&TEXT(P19,"#,##0")&" m disponibles)","SIN VENTAS Jun-Sep — no comprar"),IF(AA19>0.1*Y19,"COMPRAR — faltan "&TEXT(AA19,"#,##0")&" m para 4 meses"&IF(P19-E19>0," (ya contando pedidos)",""),IF(AND(-AA19>0.1*Y19,SUM(I19:M19)+IF($AD$3="SI",SUM(N19),0)>0),"PEDIR MENOS — sobran "&TEXT(-AA19,"#,##0")&" m; revisar pedidos sin facturar ("&TEXT(SUM(I19:M19)+IF($AD$3="SI",SUM(N19),0),"#,##0")&" m)",IF(Z19>8,"SOBRESTOCK — "&TEXT(Z19,"0.0")&" meses de cobertura","OK — cubierto ("&TEXT(Z19,"0.0")&" meses)")))))) -> SIN VENTAS Jun-Sep — no comprar (440 m disponibles) | P19: =E19+N(F19)+SUM(G19:M19)+IF($AD$3="SI",SUM(N19),0) -> 440 | X19: =IFERROR(VLOOKUP($A19,Ventas!$A$2:$L$5000,12,FALSE()),"") -> 0 | Y19: =IF(X19="","",ROUND(X19*4,0)) -> 0 | Z19: =IF(OR(X19="",X19=0),"",ROUND(P19/X19,1)) | AA19: =IF(Y19="","",Y19-P19) -> -440 | AB19: =IF(A19="","",IF(COUNTIF($A$8:$A$670,A19)>1,"DUPLICADO","")) | AC19: {=IF(AH19<>"COMPRAR","",IF(MAX(INDEX(Ventas!$G$2:$G$5000,MATCH($A19,Ventas!$A$2:$A$5000,0)),INDEX(Ventas!$H$2:$H$5000,MATCH($A19,Ventas!$A$2:$A$5000,0)),INDEX(Ventas!$I$2:$I$5000,MATCH($A19,Ventas!$A$2:$A$5000,0)),INDEX(Ventas!$J$2:$J$5000,MATCH($A19,Ventas!$A$2:$A$5000,0)))>0.5*AF19*4,"1 mes = "&TEXT(MAX(INDEX(Ventas!$G$2:$G$5000,MATCH($A19,Ventas!$A$2:$A$5000,0)),INDEX(Ventas!$H$2:$H$5000,MATCH($A19,Ventas!$A$2:$A$5000,0)),INDEX(Ventas!$I$2:$I$5000,MATCH($A19,Ventas!$A$2:$A$5000,0)),INDEX(Ventas!$J$2:$J$5000,MATCH($A19,Ventas!$A$2:$A$5000,0)))/(AF19*4),"0%")&" de 4 meses",""))} | AD19: =IF(OR(X19="",X19=0),"",IF(E19+N(F19)<X19*$AD$5,"SÍ — "&TEXT(E19+N(F19),"#,##0")&" m vs "&TEXT(X19*$AD$5,"#,##0")&" m","")) | AE19: {=IF(X19="","",IF(AND(E19=0,AVERAGE(INDEX(Ventas!$C$2:$I$5000,MATCH($A19,Ventas!$A$2:$A$5000,0),0))>0,INDEX(Ventas!$J$2:$J$5000,MATCH($A19,Ventas!$A$2:$A$5000,0))<0.5*AVERAGE(INDEX(Ventas!$C$2:$I$5000,MATCH($A19,Ventas!$A$2:$A$5000,0),0))),"SÍ — stock 0 y Sep cayó (prom Feb-Ago "&TEXT(AVERAGE(INDEX(Ventas!$C$2:$I$5000,MATCH($A19,Ventas!$A$2:$A$5000,0),0)),"#,##0")&")",""))} | AF19: {=IF(X19="","",IF(AE19<>"",MAX(X19,AVERAGE(INDEX(Ventas!$C$2:$I$5000,MATCH($A19,Ventas!$A$2:$A$5000,0),0))),X19))} -> 0 | AG19: =IF(AF19="","",ROUND(AF19*4,0)-P19) -> -440 | AH19: =IF(A19="","",IF(AF19="","SIN HISTORIAL",IF(AF19=0,"SIN VENTAS",IF(AG19>0.1*ROUND(AF19*4,0),"COMPRAR",IF(AND(-AG19>0.1*ROUND(AF19*4,0),SUM(I19:M19)+IF($AD$3="SI",SUM(N19),0)>0),"PEDIR MENOS",IF(P19/AF19>8,"SOBRESTOCK","OK")))))) -> SIN VENTAS
A20: 4931098-0008 | B20: CAPELLADA | C20: CALI | D20: CORAL | E20: 502 | O20: =IF(A20="","SIN SKU — cargar código para calcular",IF(X20="","SIN HISTORIAL DE VENTAS — artículo nuevo o código distinto en Ventas",IF(X20=0,IF(P20>0,"SIN VENTAS Jun-Sep — no comprar ("&TEXT(P20,"#,##0")&" m disponibles)","SIN VENTAS Jun-Sep — no comprar"),IF(AA20>0.1*Y20,"COMPRAR — faltan "&TEXT(AA20,"#,##0")&" m para 4 meses"&IF(P20-E20>0," (ya contando pedidos)",""),IF(AND(-AA20>0.1*Y20,SUM(I20:M20)+IF($AD$3="SI",SUM(N20),0)>0),"PEDIR MENOS — sobran "&TEXT(-AA20,"#,##0")&" m; revisar pedidos sin facturar ("&TEXT(SUM(I20:M20)+IF($AD$3="SI",SUM(N20),0),"#,##0")&" m)",IF(Z20>8,"SOBRESTOCK — "&TEXT(Z20,"0.0")&" meses de cobertura","OK — cubierto ("&TEXT(Z20,"0.0")&" meses)")))))) -> SIN VENTAS Jun-Sep — no comprar (502 m disponibles) | P20: =E20+N(F20)+SUM(G20:M20)+IF($AD$3="SI",SUM(N20),0) -> 502 | X20: =IFERROR(VLOOKUP($A20,Ventas!$A$2:$L$5000,12,FALSE()),"") -> 0 | Y20: =IF(X20="","",ROUND(X20*4,0)) -> 0 | Z20: =IF(OR(X20="",X20=0),"",ROUND(P20/X20,1)) | AA20: =IF(Y20="","",Y20-P20) -> -502 | AB20: =IF(A20="","",IF(COUNTIF($A$8:$A$670,A20)>1,"DUPLICADO","")) | AC20: {=IF(AH20<>"COMPRAR","",IF(MAX(INDEX(Ventas!$G$2:$G$5000,MATCH($A20,Ventas!$A$2:$A$5000,0)),INDEX(Ventas!$H$2:$H$5000,MATCH($A20,Ventas!$A$2:$A$5000,0)),INDEX(Ventas!$I$2:$I$5000,MATCH($A20,Ventas!$A$2:$A$5000,0)),INDEX(Ventas!$J$2:$J$5000,MATCH($A20,Ventas!$A$2:$A$5000,0)))>0.5*AF20*4,"1 mes = "&TEXT(MAX(INDEX(Ventas!$G$2:$G$5000,MATCH($A20,Ventas!$A$2:$A$5000,0)),INDEX(Ventas!$H$2:$H$5000,MATCH($A20,Ventas!$A$2:$A$5000,0)),INDEX(Ventas!$I$2:$I$5000,MATCH($A20,Ventas!$A$2:$A$5000,0)),INDEX(Ventas!$J$2:$J$5000,MATCH($A20,Ventas!$A$2:$A$5000,0)))/(AF20*4),"0%")&" de 4 meses",""))} | AD20: =IF(OR(X20="",X20=0),"",IF(E20+N(F20)<X20*$AD$5,"SÍ — "&TEXT(E20+N(F20),"#,##0")&" m vs "&TEXT(X20*$AD$5,"#,##0")&" m","")) | AE20: {=IF(X20="","",IF(AND(E20=0,AVERAGE(INDEX(Ventas!$C$2:$I$5000,MATCH($A20,Ventas!$A$2:$A$5000,0),0))>0,INDEX(Ventas!$J$2:$J$5000,MATCH($A20,Ventas!$A$2:$A$5000,0))<0.5*AVERAGE(INDEX(Ventas!$C$2:$I$5000,MATCH($A20,Ventas!$A$2:$A$5000,0),0))),"SÍ — stock 0 y Sep cayó (prom Feb-Ago "&TEXT(AVERAGE(INDEX(Ventas!$C$2:$I$5000,MATCH($A20,Ventas!$A$2:$A$5000,0),0)),"#,##0")&")",""))} | AF20: {=IF(X20="","",IF(AE20<>"",MAX(X20,AVERAGE(INDEX(Ventas!$C$2:$I$5000,MATCH($A20,Ventas!$A$2:$A$5000,0),0))),X20))} -> 0 | AG20: =IF(AF20="","",ROUND(AF20*4,0)-P20) -> -502 | AH20: =IF(A20="","",IF(AF20="","SIN HISTORIAL",IF(AF20=0,"SIN VENTAS",IF(AG20>0.1*ROUND(AF20*4,0),"COMPRAR",IF(AND(-AG20>0.1*ROUND(AF20*4,0),SUM(I20:M20)+IF($AD$3="SI",SUM(N20),0)>0),"PEDIR MENOS",IF(P20/AF20>8,"SOBRESTOCK","OK")))))) -> SIN VENTAS
A21: 4931098-0010 | B21: CAPELLADA | C21: CALI | D21: CHOCOLATE | E21: 0 | H21: 1000 | I21: 843 | K21: 3000 | O21: =IF(A21="","SIN SKU — cargar código para calcular",IF(X21="","SIN HISTORIAL DE VENTAS — artículo nuevo o código distinto en Ventas",IF(X21=0,IF(P21>0,"SIN VENTAS Jun-Sep — no comprar ("&TEXT(P21,"#,##0")&" m disponibles)","SIN VENTAS Jun-Sep — no comprar"),IF(AA21>0.1*Y21,"COMPRAR — faltan "&TEXT(AA21,"#,##0")&" m para 4 meses"&IF(P21-E21>0," (ya contando pedidos)",""),IF(AND(-AA21>0.1*Y21,SUM(I21:M21)+IF($AD$3="SI",SUM(N21),0)>0),"PEDIR MENOS — sobran "&TEXT(-AA21,"#,##0")&" m; revisar pedidos sin facturar ("&TEXT(SUM(I21:M21)+IF($AD$3="SI",SUM(N21),0),"#,##0")&" m)",IF(Z21>8,"SOBRESTOCK — "&TEXT(Z21,"0.0")&" meses de cobertura","OK — cubierto ("&TEXT(Z21,"0.0")&" meses)")))))) -> PEDIR MENOS — sobran 655 m; revisar pedidos sin facturar (3,843 m) | P21: =E21+N(F21)+SUM(G21:M21)+IF($AD$3="SI",SUM(N21),0) -> 4843 | Q21: Ingresaron 17998 mts desde agosto del año 2025 hasta junio del 2026 y no hay stock. | X21: =IFERROR(VLOOKUP($A21,Ventas!$A$2:$L$5000,12,FALSE()),"") -> 1047 | Y21: =IF(X21="","",ROUND(X21*4,0)) -> 4188 | Z21: =IF(OR(X21="",X21=0),"",ROUND(P21/X21,1)) -> 4.6 | AA21: =IF(Y21="","",Y21-P21) -> -655 | AB21: =IF(A21="","",IF(COUNTIF($A$8:$A$670,A21)>1,"DUPLICADO","")) | AC21: {=IF(AH21<>"COMPRAR","",IF(MAX(INDEX(Ventas!$G$2:$G$5000,MATCH($A21,Ventas!$A$2:$A$5000,0)),INDEX(Ventas!$H$2:$H$5000,MATCH($A21,Ventas!$A$2:$A$5000,0)),INDEX(Ventas!$I$2:$I$5000,MATCH($A21,Ventas!$A$2:$A$5000,0)),INDEX(Ventas!$J$2:$J$5000,MATCH($A21,Ventas!$A$2:$A$5000,0)))>0.5*AF21*4,"1 mes = "&TEXT(MAX(INDEX(Ventas!$G$2:$G$5000,MATCH($A21,Ventas!$A$2:$A$5000,0)),INDEX(Ventas!$H$2:$H$5000,MATCH($A21,Ventas!$A$2:$A$5000,0)),INDEX(Ventas!$I$2:$I$5000,MATCH($A21,Ventas!$A$2:$A$5000,0)),INDEX(Ventas!$J$2:$J$5000,MATCH($A21,Ventas!$A$2:$A$5000,0)))/(AF21*4),"0%")&" de 4 meses",""))} | AD21: =IF(OR(X21="",X21=0),"",IF(E21+N(F21)<X21*$AD$5,"SÍ — "&TEXT(E21+N(F21),"#,##0")&" m vs "&TEXT(X21*$AD$5,"#,##0")&" m","")) -> SÍ — 0 m vs 555 m | AE21: {=IF(X21="","",IF(AND(E21=0,AVERAGE(INDEX(Ventas!$C$2:$I$5000,MATCH($A21,Ventas!$A$2:$A$5000,0),0))>0,INDEX(Ventas!$J$2:$J$5000,MATCH($A21,Ventas!$A$2:$A$5000,0))<0.5*AVERAGE(INDEX(Ventas!$C$2:$I$5000,MATCH($A21,Ventas!$A$2:$A$5000,0),0))),"SÍ — stock 0 y Sep cayó (prom Feb-Ago "&TEXT(AVERAGE(INDEX(Ventas!$C$2:$I$5000,MATCH($A21,Ventas!$A$2:$A$5000,0),0)),"#,##0")&")",""))} -> SÍ — stock 0 y Sep cayó (prom Feb-Ago 2,504) | AF21: {=IF(X21="","",IF(AE21<>"",MAX(X21,AVERAGE(INDEX(Ventas!$C$2:$I$5000,MATCH($A21,Ventas!$A$2:$A$5000,0),0))),X21))} -> 2504.4286 | AG21: =IF(AF21="","",ROUND(AF21*4,0)-P21) -> 5175 | AH21: =IF(A21="","",IF(AF21="","SIN HISTORIAL",IF(AF21=0,"SIN VENTAS",IF(AG21>0.1*ROUND(AF21*4,0),"COMPRAR",IF(AND(-AG21>0.1*ROUND(AF21*4,0),SUM(I21:M21)+IF($AD$3="SI",SUM(N21),0)>0),"PEDIR MENOS",IF(P21/AF21>8,"SOBRESTOCK","OK")))))) -> COMPRAR
A22: 4931098-0044 | B22: CAPELLADA | C22: CALI | D22: MOCCA | E22: 2826 | O22: =IF(A22="","SIN SKU — cargar código para calcular",IF(X22="","SIN HISTORIAL DE VENTAS — artículo nuevo o código distinto en Ventas",IF(X22=0,IF(P22>0,"SIN VENTAS Jun-Sep — no comprar ("&TEXT(P22,"#,##0")&" m disponibles)","SIN VENTAS Jun-Sep — no comprar"),IF(AA22>0.1*Y22,"COMPRAR — faltan "&TEXT(AA22,"#,##0")&" m para 4 meses"&IF(P22-E22>0," (ya contando pedidos)",""),IF(AND(-AA22>0.1*Y22,SUM(I22:M22)+IF($AD$3="SI",SUM(N22),0)>0),"PEDIR MENOS — sobran "&TEXT(-AA22,"#,##0")&" m; revisar pedidos sin facturar ("&TEXT(SUM(I22:M22)+IF($AD$3="SI",SUM(N22),0),"#,##0")&" m)",IF(Z22>8,"SOBRESTOCK — "&TEXT(Z22,"0.0")&" meses de cobertura","OK — cubierto ("&TEXT(Z22,"0.0")&" meses)")))))) -> SOBRESTOCK — 70.7 meses de cobertura | P22: =E22+N(F22)+SUM(G22:M22)+IF($AD$3="SI",SUM(N22),0) -> 2826 | X22: =IFERROR(VLOOKUP($A22,Ventas!$A$2:$L$5000,12,FALSE()),"") -> 40 | Y22: =IF(X22="","",ROUND(X22*4,0)) -> 160 | Z22: =IF(OR(X22="",X22=0),"",ROUND(P22/X22,1)) -> 70.7 | AA22: =IF(Y22="","",Y22-P22) -> -2666 | AB22: =IF(A22="","",IF(COUNTIF($A$8:$A$670,A22)>1,"DUPLICADO","")) | AC22: {=IF(AH22<>"COMPRAR","",IF(MAX(INDEX(Ventas!$G$2:$G$5000,MATCH($A22,Ventas!$A$2:$A$5000,0)),INDEX(Ventas!$H$2:$H$5000,MATCH($A22,Ventas!$A$2:$A$5000,0)),INDEX(Ventas!$I$2:$I$5000,MATCH($A22,Ventas!$A$2:$A$5000,0)),INDEX(Ventas!$J$2:$J$5000,MATCH($A22,Ventas!$A$2:$A$5000,0)))>0.5*AF22*4,"1 mes = "&TEXT(MAX(INDEX(Ventas!$G$2:$G$5000,MATCH($A22,Ventas!$A$2:$A$5000,0)),INDEX(Ventas!$H$2:$H$5000,MATCH($A22,Ventas!$A$2:$A$5000,0)),INDEX(Ventas!$I$2:$I$5000,MATCH($A22,Ventas!$A$2:$A$5000,0)),INDEX(Ventas!$J$2:$J$5000,MATCH($A22,Ventas!$A$2:$A$5000,0)))/(AF22*4),"0%")&" de 4 meses",""))} | AD22: =IF(OR(X22="",X22=0),"",IF(E22+N(F22)<X22*$AD$5,"SÍ — "&TEXT(E22+N(F22),"#,##0")&" m vs "&TEXT(X22*$AD$5,"#,##0")&" m","")) | AE22: {=IF(X22="","",IF(AND(E22=0,AVERAGE(INDEX(Ventas!$C$2:$I$5000,MATCH($A22,Ventas!$A$2:$A$5000,0),0))>0,INDEX(Ventas!$J$2:$J$5000,MATCH($A22,Ventas!$A$2:$A$5000,0))<0.5*AVERAGE(INDEX(Ventas!$C$2:$I$5000,MATCH($A22,Ventas!$A$2:$A$5000,0),0))),"SÍ — stock 0 y Sep cayó (prom Feb-Ago "&TEXT(AVERAGE(INDEX(Ventas!$C$2:$I$5000,MATCH($A22,Ventas!$A$2:$A$5000,0),0)),"#,##0")&")",""))} | AF22: {=IF(X22="","",IF(AE22<>"",MAX(X22,AVERAGE(INDEX(Ventas!$C$2:$I$5000,MATCH($A22,Ventas!$A$2:$A$5000,0),0))),X22))} -> 40 | AG22: =IF(AF22="","",ROUND(AF22*4,0)-P22) -> -2666 | AH22: =IF(A22="","",IF(AF22="","SIN HISTORIAL",IF(AF22=0,"SIN VENTAS",IF(AG22>0.1*ROUND(AF22*4,0),"COMPRAR",IF(AND(-AG22>0.1*ROUND(AF22*4,0),SUM(I22:M22)+IF($AD$3="SI",SUM(N22),0)>0),"PEDIR MENOS",IF(P22/AF22>8,"SOBRESTOCK","OK")))))) -> SOBRESTOCK
A23: 581923-9999 | B23: CAPELLADA | C23: BOGOTA | D23: NEGRO ( Base Tejida ) | E23: 0 | H23: 1880 | I23: 4082 | K23: 6000 | L23: 6000 | O23: =IF(A23="","SIN SKU — cargar código para calcular",IF(X23="","SIN HISTORIAL DE VENTAS — artículo nuevo o código distinto en Ventas",IF(X23=0,IF(P23>0,"SIN VENTAS Jun-Sep — no comprar ("&TEXT(P23,"#,##0")&" m disponibles)","SIN VENTAS Jun-Sep — no comprar"),IF(AA23>0.1*Y23,"COMPRAR — faltan "&TEXT(AA23,"#,##0")&" m para 4 meses"&IF(P23-E23>0," (ya contando pedidos)",""),IF(AND(-AA23>0.1*Y23,SUM(I23:M23)+IF($AD$3="SI",SUM(N23),0)>0),"PEDIR MENOS — sobran "&TEXT(-AA23,"#,##0")&" m; revisar pedidos sin facturar ("&TEXT(SUM(I23:M23)+IF($AD$3="SI",SUM(N23),0),"#,##0")&" m)",IF(Z23>8,"SOBRESTOCK — "&TEXT(Z23,"0.0")&" meses de cobertura","OK — cubierto ("&TEXT(Z23,"0.0")&" meses)")))))) -> PEDIR MENOS — sobran 7,380 m; revisar pedidos sin facturar (16,082 m) | P23: =E23+N(F23)+SUM(G23:M23)+IF($AD$3="SI",SUM(N23),0) -> 17962 | Q23: 10000 | X23: =IFERROR(VLOOKUP($A23,Ventas!$A$2:$L$5000,12,FALSE()),"") -> 2645.5 | Y23: =IF(X23="","",ROUND(X23*4,0)) -> 10582 | Z23: =IF(OR(X23="",X23=0),"",ROUND(P23/X23,1)) -> 6.8 | AA23: =IF(Y23="","",Y23-P23) -> -7380 | AB23: =IF(A23="","",IF(COUNTIF($A$8:$A$670,A23)>1,"DUPLICADO","")) | AC23: {=IF(AH23<>"COMPRAR","",IF(MAX(INDEX(Ventas!$G$2:$G$5000,MATCH($A23,Ventas!$A$2:$A$5000,0)),INDEX(Ventas!$H$2:$H$5000,MATCH($A23,Ventas!$A$2:$A$5000,0)),INDEX(Ventas!$I$2:$I$5000,MATCH($A23,Ventas!$A$2:$A$5000,0)),INDEX(Ventas!$J$2:$J$5000,MATCH($A23,Ventas!$A$2:$A$5000,0)))>0.5*AF23*4,"1 mes = "&TEXT(MAX(INDEX(Ventas!$G$2:$G$5000,MATCH($A23,Ventas!$A$2:$A$5000,0)),INDEX(Ventas!$H$2:$H$5000,MATCH($A23,Ventas!$A$2:$A$5000,0)),INDEX(Ventas!$I$2:$I$5000,MATCH($A23,Ventas!$A$2:$A$5000,0)),INDEX(Ventas!$J$2:$J$5000,MATCH($A23,Ventas!$A$2:$A$5000,0)))/(AF23*4),"0%")&" de 4 meses",""))} | AD23: =IF(OR(X23="",X23=0),"",IF(E23+N(F23)<X23*$AD$5,"SÍ — "&TEXT(E23+N(F23),"#,##0")&" m vs "&TEXT(X23*$AD$5,"#,##0")&" m","")) -> SÍ — 0 m vs 1,402 m | AE23: {=IF(X23="","",IF(AND(E23=0,AVERAGE(INDEX(Ventas!$C$2:$I$5000,MATCH($A23,Ventas!$A$2:$A$5000,0),0))>0,INDEX(Ventas!$J$2:$J$5000,MATCH($A23,Ventas!$A$2:$A$5000,0))<0.5*AVERAGE(INDEX(Ventas!$C$2:$I$5000,MATCH($A23,Ventas!$A$2:$A$5000,0),0))),"SÍ — stock 0 y Sep cayó (prom Feb-Ago "&TEXT(AVERAGE(INDEX(Ventas!$C$2:$I$5000,MATCH($A23,Ventas!$A$2:$A$5000,0),0)),"#,##0")&")",""))} | AF23: {=IF(X23="","",IF(AE23<>"",MAX(X23,AVERAGE(INDEX(Ventas!$C$2:$I$5000,MATCH($A23,Ventas!$A$2:$A$5000,0),0))),X23))} -> 2645.5 | AG23: =IF(AF23="","",ROUND(AF23*4,0)-P23) -> -7380 | AH23: =IF(A23="","",IF(AF23="","SIN HISTORIAL",IF(AF23=0,"SIN VENTAS",IF(AG23>0.1*ROUND(AF23*4,0),"COMPRAR",IF(AND(-AG23>0.1*ROUND(AF23*4,0),SUM(I23:M23)+IF($AD$3="SI",SUM(N23),0)>0),"PEDIR MENOS",IF(P23/AF23>8,"SOBRESTOCK","OK")))))) -> PEDIR MENOS
A24: 581923-0000 | B24: CAPELLADA | C24: BOGOTA | D24: BLANCO | E24: 0 | H24: 1000 | I24: 1199 | O24: =IF(A24="","SIN SKU — cargar código para calcular",IF(X24="","SIN HISTORIAL DE VENTAS — artículo nuevo o código distinto en Ventas",IF(X24=0,IF(P24>0,"SIN VENTAS Jun-Sep — no comprar ("&TEXT(P24,"#,##0")&" m disponibles)","SIN VENTAS Jun-Sep — no comprar"),IF(AA24>0.1*Y24,"COMPRAR — faltan "&TEXT(AA24,"#,##0")&" m para 4 meses"&IF(P24-E24>0," (ya contando pedidos)",""),IF(AND(-AA24>0.1*Y24,SUM(I24:M24)+IF($AD$3="SI",SUM(N24),0)>0),"PEDIR MENOS — sobran "&TEXT(-AA24,"#,##0")&" m; revisar pedidos sin facturar ("&TEXT(SUM(I24:M24)+IF($AD$3="SI",SUM(N24),0),"#,##0")&" m)",IF(Z24>8,"SOBRESTOCK — "&TEXT(Z24,"0.0")&" meses de cobertura","OK — cubierto ("&TEXT(Z24,"0.0")&" meses)")))))) -> SIN HISTORIAL DE VENTAS — artículo nuevo o código distinto en Ventas | P24: =E24+N(F24)+SUM(G24:M24)+IF($AD$3="SI",SUM(N24),0) -> 2199 | Q24: 10000 | X24: =IFERROR(VLOOKUP($A24,Ventas!$A$2:$L$5000,12,FALSE()),"") | Y24: =IF(X24="","",ROUND(X24*4,0)) | Z24: =IF(OR(X24="",X24=0),"",ROUND(P24/X24,1)) | AA24: =IF(Y24="","",Y24-P24) | AB24: =IF(A24="","",IF(COUNTIF($A$8:$A$670,A24)>1,"DUPLICADO","")) | AC24: {=IF(AH24<>"COMPRAR","",IF(MAX(INDEX(Ventas!$G$2:$G$5000,MATCH($A24,Ventas!$A$2:$A$5000,0)),INDEX(Ventas!$H$2:$H$5000,MATCH($A24,Ventas!$A$2:$A$5000,0)),INDEX(Ventas!$I$2:$I$5000,MATCH($A24,Ventas!$A$2:$A$5000,0)),INDEX(Ventas!$J$2:$J$5000,MATCH($A24,Ventas!$A$2:$A$5000,0)))>0.5*AF24*4,"1 mes = "&TEXT(MAX(INDEX(Ventas!$G$2:$G$5000,MATCH($A24,Ventas!$A$2:$A$5000,0)),INDEX(Ventas!$H$2:$H$5000,MATCH($A24,Ventas!$A$2:$A$5000,0)),INDEX(Ventas!$I$2:$I$5000,MATCH($A24,Ventas!$A$2:$A$5000,0)),INDEX(Ventas!$J$2:$J$5000,MATCH($A24,Ventas!$A$2:$A$5000,0)))/(AF24*4),"0%")&" de 4 meses",""))} | AD24: =IF(OR(X24="",X24=0),"",IF(E24+N(F24)<X24*$AD$5,"SÍ — "&TEXT(E24+N(F24),"#,##0")&" m vs "&TEXT(X24*$AD$5,"#,##0")&" m","")) | AE24: {=IF(X24="","",IF(AND(E24=0,AVERAGE(INDEX(Ventas!$C$2:$I$5000,MATCH($A24,Ventas!$A$2:$A$5000,0),0))>0,INDEX(Ventas!$J$2:$J$5000,MATCH($A24,Ventas!$A$2:$A$5000,0))<0.5*AVERAGE(INDEX(Ventas!$C$2:$I$5000,MATCH($A24,Ventas!$A$2:$A$5000,0),0))),"SÍ — stock 0 y Sep cayó (prom Feb-Ago "&TEXT(AVERAGE(INDEX(Ventas!$C$2:$I$5000,MATCH($A24,Ventas!$A$2:$A$5000,0),0)),"#,##0")&")",""))} | AF24: {=IF(X24="","",IF(AE24<>"",MAX(X24,AVERAGE(INDEX(Ventas!$C$2:$I$5000,MATCH($A24,Ventas!$A$2:$A$5000,0),0))),X24))} | AG24: =IF(AF24="","",ROUND(AF24*4,0)-P24) | AH24: =IF(A24="","",IF(AF24="","SIN HISTORIAL",IF(AF24=0,"SIN VENTAS",IF(AG24>0.1*ROUND(AF24*4,0),"COMPRAR",IF(AND(-AG24>0.1*ROUND(AF24*4,0),SUM(I24:M24)+IF($AD$3="SI",SUM(N24),0)>0),"PEDIR MENOS",IF(P24/AF24>8,"SOBRESTOCK","OK")))))) -> SIN HISTORIAL
A25: 581923-0010 | B25: CAPELLADA | C25: BOGOTA | D25: CHOCOLATE | E25: 0 | H25: 1000 | I25: 1079 | K25: 2000 | O25: =IF(A25="","SIN SKU — cargar código para calcular",IF(X25="","SIN HISTORIAL DE VENTAS — artículo nuevo o código distinto en Ventas",IF(X25=0,IF(P25>0,"SIN VENTAS Jun-Sep — no comprar ("&TEXT(P25,"#,##0")&" m disponibles)","SIN VENTAS Jun-Sep — no comprar"),IF(AA25>0.1*Y25,"COMPRAR — faltan "&TEXT(AA25,"#,##0")&" m para 4 meses"&IF(P25-E25>0," (ya contando pedidos)",""),IF(AND(-AA25>0.1*Y25,SUM(I25:M25)+IF($AD$3="SI",SUM(N25),0)>0),"PEDIR MENOS — sobran "&TEXT(-AA25,"#,##0")&" m; revisar pedidos sin facturar ("&TEXT(SUM(I25:M25)+IF($AD$3="SI",SUM(N25),0),"#,##0")&" m)",IF(Z25>8,"SOBRESTOCK — "&TEXT(Z25,"0.0")&" meses de cobertura","OK — cubierto ("&TEXT(Z25,"0.0")&" meses)")))))) -> COMPRAR — faltan 1,382 m para 4 meses (ya contando pedidos) | P25: =E25+N(F25)+SUM(G25:M25)+IF($AD$3="SI",SUM(N25),0) -> 4079 | Q25: En lo que va del 2026 ingresaron 7936 mts y se vendió todo. | X25: =IFERROR(VLOOKUP($A25,Ventas!$A$2:$L$5000,12,FALSE()),"") -> 1365.25 | Y25: =IF(X25="","",ROUND(X25*4,0)) -> 5461 | Z25: =IF(OR(X25="",X25=0),"",ROUND(P25/X25,1)) -> 3 | AA25: =IF(Y25="","",Y25-P25) -> 1382 | AB25: =IF(A25="","",IF(COUNTIF($A$8:$A$670,A25)>1,"DUPLICADO","")) | AC25: {=IF(AH25<>"COMPRAR","",IF(MAX(INDEX(Ventas!$G$2:$G$5000,MATCH($A25,Ventas!$A$2:$A$5000,0)),INDEX(Ventas!$H$2:$H$5000,MATCH($A25,Ventas!$A$2:$A$5000,0)),INDEX(Ventas!$I$2:$I$5000,MATCH($A25,Ventas!$A$2:$A$5000,0)),INDEX(Ventas!$J$2:$J$5000,MATCH($A25,Ventas!$A$2:$A$5000,0)))>0.5*AF25*4,"1 mes = "&TEXT(MAX(INDEX(Ventas!$G$2:$G$5000,MATCH($A25,Ventas!$A$2:$A$5000,0)),INDEX(Ventas!$H$2:$H$5000,MATCH($A25,Ventas!$A$2:$A$5000,0)),INDEX(Ventas!$I$2:$I$5000,MATCH($A25,Ventas!$A$2:$A$5000,0)),INDEX(Ventas!$J$2:$J$5000,MATCH($A25,Ventas!$A$2:$A$5000,0)))/(AF25*4),"0%")&" de 4 meses",""))} | AD25: =IF(OR(X25="",X25=0),"",IF(E25+N(F25)<X25*$AD$5,"SÍ — "&TEXT(E25+N(F25),"#,##0")&" m vs "&TEXT(X25*$AD$5,"#,##0")&" m","")) -> SÍ — 0 m vs 724 m | AE25: {=IF(X25="","",IF(AND(E25=0,AVERAGE(INDEX(Ventas!$C$2:$I$5000,MATCH($A25,Ventas!$A$2:$A$5000,0),0))>0,INDEX(Ventas!$J$2:$J$5000,MATCH($A25,Ventas!$A$2:$A$5000,0))<0.5*AVERAGE(INDEX(Ventas!$C$2:$I$5000,MATCH($A25,Ventas!$A$2:$A$5000,0),0))),"SÍ — stock 0 y Sep cayó (prom Feb-Ago "&TEXT(AVERAGE(INDEX(Ventas!$C$2:$I$5000,MATCH($A25,Ventas!$A$2:$A$5000,0),0)),"#,##0")&")",""))} -> SÍ — stock 0 y Sep cayó (prom Feb-Ago 1,145) | AF25: {=IF(X25="","",IF(AE25<>"",MAX(X25,AVERAGE(INDEX(Ventas!$C$2:$I$5000,MATCH($A25,Ventas!$A$2:$A$5000,0),0))),X25))} -> 1365.25 | AG25: =IF(AF25="","",ROUND(AF25*4,0)-P25) -> 1382 | AH25: =IF(A25="","",IF(AF25="","SIN HISTORIAL",IF(AF25=0,"SIN VENTAS",IF(AG25>0.1*ROUND(AF25*4,0),"COMPRAR",IF(AND(-AG25>0.1*ROUND(AF25*4,0),SUM(I25:M25)+IF($AD$3="SI",SUM(N25),0)>0),"PEDIR MENOS",IF(P25/AF25>8,"SOBRESTOCK","OK")))))) -> COMPRAR
A26: 581923-0047 | B26: CAPELLADA | C26: BOGOTA | D26: VISON | E26: 40 | O26: =IF(A26="","SIN SKU — cargar código para calcular",IF(X26="","SIN HISTORIAL DE VENTAS — artículo nuevo o código distinto en Ventas",IF(X26=0,IF(P26>0,"SIN VENTAS Jun-Sep — no comprar ("&TEXT(P26,"#,##0")&" m disponibles)","SIN VENTAS Jun-Sep — no comprar"),IF(AA26>0.1*Y26,"COMPRAR — faltan "&TEXT(AA26,"#,##0")&" m para 4 meses"&IF(P26-E26>0," (ya contando pedidos)",""),IF(AND(-AA26>0.1*Y26,SUM(I26:M26)+IF($AD$3="SI",SUM(N26),0)>0),"PEDIR MENOS — sobran "&TEXT(-AA26,"#,##0")&" m; revisar pedidos sin facturar ("&TEXT(SUM(I26:M26)+IF($AD$3="SI",SUM(N26),0),"#,##0")&" m)",IF(Z26>8,"SOBRESTOCK — "&TEXT(Z26,"0.0")&" meses de cobertura","OK — cubierto ("&TEXT(Z26,"0.0")&" meses)")))))) -> COMPRAR — faltan 226 m para 4 meses | P26: =E26+N(F26)+SUM(G26:M26)+IF($AD$3="SI",SUM(N26),0) -> 40 | X26: =IFERROR(VLOOKUP($A26,Ventas!$A$2:$L$5000,12,FALSE()),"") -> 66.5 | Y26: =IF(X26="","",ROUND(X26*4,0)) -> 266 | Z26: =IF(OR(X26="",X26=0),"",ROUND(P26/X26,1)) -> 0.6 | AA26: =IF(Y26="","",Y26-P26) -> 226 | AB26: =IF(A26="","",IF(COUNTIF($A$8:$A$670,A26)>1,"DUPLICADO","")) | AC26: {=IF(AH26<>"COMPRAR","",IF(MAX(INDEX(Ventas!$G$2:$G$5000,MATCH($A26,Ventas!$A$2:$A$5000,0)),INDEX(Ventas!$H$2:$H$5000,MATCH($A26,Ventas!$A$2:$A$5000,0)),INDEX(Ventas!$I$2:$I$5000,MATCH($A26,Ventas!$A$2:$A$5000,0)),INDEX(Ventas!$J$2:$J$5000,MATCH($A26,Ventas!$A$2:$A$5000,0)))>0.5*AF26*4,"1 mes = "&TEXT(MAX(INDEX(Ventas!$G$2:$G$5000,MATCH($A26,Ventas!$A$2:$A$5000,0)),INDEX(Ventas!$H$2:$H$5000,MATCH($A26,Ventas!$A$2:$A$5000,0)),INDEX(Ventas!$I$2:$I$5000,MATCH($A26,Ventas!$A$2:$A$5000,0)),INDEX(Ventas!$J$2:$J$5000,MATCH($A26,Ventas!$A$2:$A$5000,0)))/(AF26*4),"0%")&" de 4 meses",""))} -> 1 mes = 100% de 4 meses | AD26: =IF(OR(X26="",X26=0),"",IF(E26+N(F26)<X26*$AD$5,"SÍ — "&TEXT(E26+N(F26),"#,##0")&" m vs "&TEXT(X26*$AD$5,"#,##0")&" m","")) | AE26: {=IF(X26="","",IF(AND(E26=0,AVERAGE(INDEX(Ventas!$C$2:$I$5000,MATCH($A26,Ventas!$A$2:$A$5000,0),0))>0,INDEX(Ventas!$J$2:$J$5000,MATCH($A26,Ventas!$A$2:$A$5000,0))<0.5*AVERAGE(INDEX(Ventas!$C$2:$I$5000,MATCH($A26,Ventas!$A$2:$A$5000,0),0))),"SÍ — stock 0 y Sep cayó (prom Feb-Ago "&TEXT(AVERAGE(INDEX(Ventas!$C$2:$I$5000,MATCH($A26,Ventas!$A$2:$A$5000,0),0)),"#,##0")&")",""))} | AF26: {=IF(X26="","",IF(AE26<>"",MAX(X26,AVERAGE(INDEX(Ventas!$C$2:$I$5000,MATCH($A26,Ventas!$A$2:$A$5000,0),0))),X26))} -> 66.5 | AG26: =IF(AF26="","",ROUND(AF26*4,0)-P26) -> 226 | AH26: =IF(A26="","",IF(AF26="","SIN HISTORIAL",IF(AF26=0,"SIN VENTAS",IF(AG26>0.1*ROUND(AF26*4,0),"COMPRAR",IF(AND(-AG26>0.1*ROUND(AF26*4,0),SUM(I26:M26)+IF($AD$3="SI",SUM(N26),0)>0),"PEDIR MENOS",IF(P26/AF26>8,"SOBRESTOCK","OK")))))) -> COMPRAR
A27: 5081098-9999 | B27: PU BONDEADO | C27: MILAN | D27: NEGRO | E27: 4552 | O27: =IF(A27="","SIN SKU — cargar código para calcular",IF(X27="","SIN HISTORIAL DE VENTAS — artículo nuevo o código distinto en Ventas",IF(X27=0,IF(P27>0,"SIN VENTAS Jun-Sep — no comprar ("&TEXT(P27,"#,##0")&" m disponibles)","SIN VENTAS Jun-Sep — no comprar"),IF(AA27>0.1*Y27,"COMPRAR — faltan "&TEXT(AA27,"#,##0")&" m para 4 meses"&IF(P27-E27>0," (ya contando pedidos)",""),IF(AND(-AA27>0.1*Y27,SUM(I27:M27)+IF($AD$3="SI",SUM(N27),0)>0),"PEDIR MENOS — sobran "&TEXT(-AA27,"#,##0")&" m; revisar pedidos sin facturar ("&TEXT(SUM(I27:M27)+IF($AD$3="SI",SUM(N27),0),"#,##0")&" m)",IF(Z27>8,"SOBRESTOCK — "&TEXT(Z27,"0.0")&" meses de cobertura","OK — cubierto ("&TEXT(Z27,"0.0")&" meses)")))))) -> SOBRESTOCK — 606.9 meses de cobertura | P27: =E27+N(F27)+SUM(G27:M27)+IF($AD$3="SI",SUM(N27),0) -> 4552 | X27: =IFERROR(VLOOKUP($A27,Ventas!$A$2:$L$5000,12,FALSE()),"") -> 7.5 | Y27: =IF(X27="","",ROUND(X27*4,0)) -> 30 | Z27: =IF(OR(X27="",X27=0),"",ROUND(P27/X27,1)) -> 606.9 | AA27: =IF(Y27="","",Y27-P27) -> -4522 | AB27: =IF(A27="","",IF(COUNTIF($A$8:$A$670,A27)>1,"DUPLICADO","")) | AC27: {=IF(AH27<>"COMPRAR","",IF(MAX(INDEX(Ventas!$G$2:$G$5000,MATCH($A27,Ventas!$A$2:$A$5000,0)),INDEX(Ventas!$H$2:$H$5000,MATCH($A27,Ventas!$A$2:$A$5000,0)),INDEX(Ventas!$I$2:$I$5000,MATCH($A27,Ventas!$A$2:$A$5000,0)),INDEX(Ventas!$J$2:$J$5000,MATCH($A27,Ventas!$A$2:$A$5000,0)))>0.5*AF27*4,"1 mes = "&TEXT(MAX(INDEX(Ventas!$G$2:$G$5000,MATCH($A27,Ventas!$A$2:$A$5000,0)),INDEX(Ventas!$H$2:$H$5000,MATCH($A27,Ventas!$A$2:$A$5000,0)),INDEX(Ventas!$I$2:$I$5000,MATCH($A27,Ventas!$A$2:$A$5000,0)),INDEX(Ventas!$J$2:$J$5000,MATCH($A27,Ventas!$A$2:$A$5000,0)))/(AF27*4),"0%")&" de 4 meses",""))} | AD27: =IF(OR(X27="",X27=0),"",IF(E27+N(F27)<X27*$AD$5,"SÍ — "&TEXT(E27+N(F27),"#,##0")&" m vs "&TEXT(X27*$AD$5,"#,##0")&" m","")) | AE27: {=IF(X27="","",IF(AND(E27=0,AVERAGE(INDEX(Ventas!$C$2:$I$5000,MATCH($A27,Ventas!$A$2:$A$5000,0),0))>0,INDEX(Ventas!$J$2:$J$5000,MATCH($A27,Ventas!$A$2:$A$5000,0))<0.5*AVERAGE(INDEX(Ventas!$C$2:$I$5000,MATCH($A27,Ventas!$A$2:$A$5000,0),0))),"SÍ — stock 0 y Sep cayó (prom Feb-Ago "&TEXT(AVERAGE(INDEX(Ventas!$C$2:$I$5000,MATCH($A27,Ventas!$A$2:$A$5000,0),0)),"#,##0")&")",""))} | AF27: {=IF(X27="","",IF(AE27<>"",MAX(X27,AVERAGE(INDEX(Ventas!$C$2:$I$5000,MATCH($A27,Ventas!$A$2:$A$5000,0),0))),X27))} -> 7.5 | AG27: =IF(AF27="","",ROUND(AF27*4,0)-P27) -> -4522 | AH27: =IF(A27="","",IF(AF27="","SIN HISTORIAL",IF(AF27=0,"SIN VENTAS",IF(AG27>0.1*ROUND(AF27*4,0),"COMPRAR",IF(AND(-AG27>0.1*ROUND(AF27*4,0),SUM(I27:M27)+IF($AD$3="SI",SUM(N27),0)>0),"PEDIR MENOS",IF(P27/AF27>8,"SOBRESTOCK","OK")))))) -> SOBRESTOCK
A28: 5089923-0000 | B28: PU BONDEADO | C28: TURIN EVA PIQUE | D28: BLANCO | E28: 845 | O28: =IF(A28="","SIN SKU — cargar código para calcular",IF(X28="","SIN HISTORIAL DE VENTAS — artículo nuevo o código distinto en Ventas",IF(X28=0,IF(P28>0,"SIN VENTAS Jun-Sep — no comprar ("&TEXT(P28,"#,##0")&" m disponibles)","SIN VENTAS Jun-Sep — no comprar"),IF(AA28>0.1*Y28,"COMPRAR — faltan "&TEXT(AA28,"#,##0")&" m para 4 meses"&IF(P28-E28>0," (ya contando pedidos)",""),IF(AND(-AA28>0.1*Y28,SUM(I28:M28)+IF($AD$3="SI",SUM(N28),0)>0),"PEDIR MENOS — sobran "&TEXT(-AA28,"#,##0")&" m; revisar pedidos sin facturar ("&TEXT(SUM(I28:M28)+IF($AD$3="SI",SUM(N28),0),"#,##0")&" m)",IF(Z28>8,"SOBRESTOCK — "&TEXT(Z28,"0.0")&" meses de cobertura","OK — cubierto ("&TEXT(Z28,"0.0")&" meses)")))))) -> SOBRESTOCK — 56.3 meses de cobertura | P28: =E28+N(F28)+SUM(G28:M28)+IF($AD$3="SI",SUM(N28),0) -> 845 | X28: =IFERROR(VLOOKUP($A28,Ventas!$A$2:$L$5000,12,FALSE()),"") -> 15 | Y28: =IF(X28="","",ROUND(X28*4,0)) -> 60 | Z28: =IF(OR(X28="",X28=0),"",ROUND(P28/X28,1)) -> 56.3 | AA28: =IF(Y28="","",Y28-P28) -> -785 | AB28: =IF(A28="","",IF(COUNTIF($A$8:$A$670,A28)>1,"DUPLICADO","")) | AC28: {=IF(AH28<>"COMPRAR","",IF(MAX(INDEX(Ventas!$G$2:$G$5000,MATCH($A28,Ventas!$A$2:$A$5000,0)),INDEX(Ventas!$H$2:$H$5000,MATCH($A28,Ventas!$A$2:$A$5000,0)),INDEX(Ventas!$I$2:$I$5000,MATCH($A28,Ventas!$A$2:$A$5000,0)),INDEX(Ventas!$J$2:$J$5000,MATCH($A28,Ventas!$A$2:$A$5000,0)))>0.5*AF28*4,"1 mes = "&TEXT(MAX(INDEX(Ventas!$G$2:$G$5000,MATCH($A28,Ventas!$A$2:$A$5000,0)),INDEX(Ventas!$H$2:$H$5000,MATCH($A28,Ventas!$A$2:$A$5000,0)),INDEX(Ventas!$I$2:$I$5000,MATCH($A28,Ventas!$A$2:$A$5000,0)),INDEX(Ventas!$J$2:$J$5000,MATCH($A28,Ventas!$A$2:$A$5000,0)))/(AF28*4),"0%")&" de 4 meses",""))} | AD28: =IF(OR(X28="",X28=0),"",IF(E28+N(F28)<X28*$AD$5,"SÍ — "&TEXT(E28+N(F28),"#,##0")&" m vs "&TEXT(X28*$AD$5,"#,##0")&" m","")) | AE28: {=IF(X28="","",IF(AND(E28=0,AVERAGE(INDEX(Ventas!$C$2:$I$5000,MATCH($A28,Ventas!$A$2:$A$5000,0),0))>0,INDEX(Ventas!$J$2:$J$5000,MATCH($A28,Ventas!$A$2:$A$5000,0))<0.5*AVERAGE(INDEX(Ventas!$C$2:$I$5000,MATCH($A28,Ventas!$A$2:$A$5000,0),0))),"SÍ — stock 0 y Sep cayó (prom Feb-Ago "&TEXT(AVERAGE(INDEX(Ventas!$C$2:$I$5000,MATCH($A28,Ventas!$A$2:$A$5000,0),0)),"#,##0")&")",""))} | AF28: {=IF(X28="","",IF(AE28<>"",MAX(X28,AVERAGE(INDEX(Ventas!$C$2:$I$5000,MATCH($A28,Ventas!$A$2:$A$5000,0),0))),X28))} -> 15 | AG28: =IF(AF28="","",ROUND(AF28*4,0)-P28) -> -785 | AH28: =IF(A28="","",IF(AF28="","SIN HISTORIAL",IF(AF28=0,"SIN VENTAS",IF(AG28>0.1*ROUND(AF28*4,0),"COMPRAR",IF(AND(-AG28>0.1*ROUND(AF28*4,0),SUM(I28:M28)+IF($AD$3="SI",SUM(N28),0)>0),"PEDIR MENOS",IF(P28/AF28>8,"SOBRESTOCK","OK")))))) -> SOBRESTOCK
A29: 5099923-9999 | B29: PU BONDEADO | C29: CALI EVA PIQUE 3.3mm | D29: NEGRO | E29: 0 | O29: =IF(A29="","SIN SKU — cargar código para calcular",IF(X29="","SIN HISTORIAL DE VENTAS — artículo nuevo o código distinto en Ventas",IF(X29=0,IF(P29>0,"SIN VENTAS Jun-Sep — no comprar ("&TEXT(P29,"#,##0")&" m disponibles)","SIN VENTAS Jun-Sep — no comprar"),IF(AA29>0.1*Y29,"COMPRAR — faltan "&TEXT(AA29,"#,##0")&" m para 4 meses"&IF(P29-E29>0," (ya contando pedidos)",""),IF(AND(-AA29>0.1*Y29,SUM(I29:M29)+IF($AD$3="SI",SUM(N29),0)>0),"PEDIR MENOS — sobran "&TEXT(-AA29,"#,##0")&" m; revisar pedidos sin facturar ("&TEXT(SUM(I29:M29)+IF($AD$3="SI",SUM(N29),0),"#,##0")&" m)",IF(Z29>8,"SOBRESTOCK — "&TEXT(Z29,"0.0")&" meses de cobertura","OK — cubierto ("&TEXT(Z29,"0.0")&" meses)")))))) -> COMPRAR — faltan 99 m para 4 meses | P29: =E29+N(F29)+SUM(G29:M29)+IF($AD$3="SI",SUM(N29),0) -> 0 | Q29: En los materiales bondeados quizá se deba tomar en cuenta el cierre de fábrica. | X29: =IFERROR(VLOOKUP($A29,Ventas!$A$2:$L$5000,12,FALSE()),"") -> 24.7 | Y29: =IF(X29="","",ROUND(X29*4,0)) -> 99 | Z29: =IF(OR(X29="",X29=0),"",ROUND(P29/X29,1)) -> 0 | AA29: =IF(Y29="","",Y29-P29) -> 99 | AB29: =IF(A29="","",IF(COUNTIF($A$8:$A$670,A29)>1,"DUPLICADO","")) | AC29: {=IF(AH29<>"COMPRAR","",IF(MAX(INDEX(Ventas!$G$2:$G$5000,MATCH($A29,Ventas!$A$2:$A$5000,0)),INDEX(Ventas!$H$2:$H$5000,MATCH($A29,Ventas!$A$2:$A$5000,0)),INDEX(Ventas!$I$2:$I$5000,MATCH($A29,Ventas!$A$2:$A$5000,0)),INDEX(Ventas!$J$2:$J$5000,MATCH($A29,Ventas!$A$2:$A$5000,0)))>0.5*AF29*4,"1 mes = "&TEXT(MAX(INDEX(Ventas!$G$2:$G$5000,MATCH($A29,Ventas!$A$2:$A$5000,0)),INDEX(Ventas!$H$2:$H$5000,MATCH($A29,Ventas!$A$2:$A$5000,0)),INDEX(Ventas!$I$2:$I$5000,MATCH($A29,Ventas!$A$2:$A$5000,0)),INDEX(Ventas!$J$2:$J$5000,MATCH($A29,Ventas!$A$2:$A$5000,0)))/(AF29*4),"0%")&" de 4 meses",""))} | AD29: =IF(OR(X29="",X29=0),"",IF(E29+N(F29)<X29*$AD$5,"SÍ — "&TEXT(E29+N(F29),"#,##0")&" m vs "&TEXT(X29*$AD$5,"#,##0")&" m","")) -> SÍ — 0 m vs 13 m | AE29: {=IF(X29="","",IF(AND(E29=0,AVERAGE(INDEX(Ventas!$C$2:$I$5000,MATCH($A29,Ventas!$A$2:$A$5000,0),0))>0,INDEX(Ventas!$J$2:$J$5000,MATCH($A29,Ventas!$A$2:$A$5000,0))<0.5*AVERAGE(INDEX(Ventas!$C$2:$I$5000,MATCH($A29,Ventas!$A$2:$A$5000,0),0))),"SÍ — stock 0 y Sep cayó (prom Feb-Ago "&TEXT(AVERAGE(INDEX(Ventas!$C$2:$I$5000,MATCH($A29,Ventas!$A$2:$A$5000,0),0)),"#,##0")&")",""))} -> SÍ — stock 0 y Sep cayó (prom Feb-Ago 512) | AF29: {=IF(X29="","",IF(AE29<>"",MAX(X29,AVERAGE(INDEX(Ventas!$C$2:$I$5000,MATCH($A29,Ventas!$A$2:$A$5000,0),0))),X29))} -> 511.68571 | AG29: =IF(AF29="","",ROUND(AF29*4,0)-P29) -> 2047 | AH29: =IF(A29="","",IF(AF29="","SIN HISTORIAL",IF(AF29=0,"SIN VENTAS",IF(AG29>0.1*ROUND(AF29*4,0),"COMPRAR",IF(AND(-AG29>0.1*ROUND(AF29*4,0),SUM(I29:M29)+IF($AD$3="SI",SUM(N29),0)>0),"PEDIR MENOS",IF(P29/AF29>8,"SOBRESTOCK","OK")))))) -> COMPRAR
A30: 5100923-9999 | B30: PU BONDEADO | C30: TOKIO EVA PIQUE 3.3mm | D30: NEGRO | E30: 0 | O30: =IF(A30="","SIN SKU — cargar código para calcular",IF(X30="","SIN HISTORIAL DE VENTAS — artículo nuevo o código distinto en Ventas",IF(X30=0,IF(P30>0,"SIN VENTAS Jun-Sep — no comprar ("&TEXT(P30,"#,##0")&" m disponibles)","SIN VENTAS Jun-Sep — no comprar"),IF(AA30>0.1*Y30,"COMPRAR — faltan "&TEXT(AA30,"#,##0")&" m para 4 meses"&IF(P30-E30>0," (ya contando pedidos)",""),IF(AND(-AA30>0.1*Y30,SUM(I30:M30)+IF($AD$3="SI",SUM(N30),0)>0),"PEDIR MENOS — sobran "&TEXT(-AA30,"#,##0")&" m; revisar pedidos sin facturar ("&TEXT(SUM(I30:M30)+IF($AD$3="SI",SUM(N30),0),"#,##0")&" m)",IF(Z30>8,"SOBRESTOCK — "&TEXT(Z30,"0.0")&" meses de cobertura","OK — cubierto ("&TEXT(Z30,"0.0")&" meses)")))))) -> SIN VENTAS Jun-Sep — no comprar | P30: =E30+N(F30)+SUM(G30:M30)+IF($AD$3="SI",SUM(N30),0) -> 0 | Q30: En los materiales bondeados quizá se deba tomar en cuenta el cierre de fábrica. | X30: =IFERROR(VLOOKUP($A30,Ventas!$A$2:$L$5000,12,FALSE()),"") -> 0 | Y30: =IF(X30="","",ROUND(X30*4,0)) -> 0 | Z30: =IF(OR(X30="",X30=0),"",ROUND(P30/X30,1)) | AA30: =IF(Y30="","",Y30-P30) -> 0 | AB30: =IF(A30="","",IF(COUNTIF($A$8:$A$670,A30)>1,"DUPLICADO","")) | AC30: {=IF(AH30<>"COMPRAR","",IF(MAX(INDEX(Ventas!$G$2:$G$5000,MATCH($A30,Ventas!$A$2:$A$5000,0)),INDEX(Ventas!$H$2:$H$5000,MATCH($A30,Ventas!$A$2:$A$5000,0)),INDEX(Ventas!$I$2:$I$5000,MATCH($A30,Ventas!$A$2:$A$5000,0)),INDEX(Ventas!$J$2:$J$5000,MATCH($A30,Ventas!$A$2:$A$5000,0)))>0.5*AF30*4,"1 mes = "&TEXT(MAX(INDEX(Ventas!$G$2:$G$5000,MATCH($A30,Ventas!$A$2:$A$5000,0)),INDEX(Ventas!$H$2:$H$5000,MATCH($A30,Ventas!$A$2:$A$5000,0)),INDEX(Ventas!$I$2:$I$5000,MATCH($A30,Ventas!$A$2:$A$5000,0)),INDEX(Ventas!$J$2:$J$5000,MATCH($A30,Ventas!$A$2:$A$5000,0)))/(AF30*4),"0%")&" de 4 meses",""))} | AD30: =IF(OR(X30="",X30=0),"",IF(E30+N(F30)<X30*$AD$5,"SÍ — "&TEXT(E30+N(F30),"#,##0")&" m vs "&TEXT(X30*$AD$5,"#,##0")&" m","")) | AE30: {=IF(X30="","",IF(AND(E30=0,AVERAGE(INDEX(Ventas!$C$2:$I$5000,MATCH($A30,Ventas!$A$2:$A$5000,0),0))>0,INDEX(Ventas!$J$2:$J$5000,MATCH($A30,Ventas!$A$2:$A$5000,0))<0.5*AVERAGE(INDEX(Ventas!$C$2:$I$5000,MATCH($A30,Ventas!$A$2:$A$5000,0),0))),"SÍ — stock 0 y Sep cayó (prom Feb-Ago "&TEXT(AVERAGE(INDEX(Ventas!$C$2:$I$5000,MATCH($A30,Ventas!$A$2:$A$5000,0),0)),"#,##0")&")",""))} -> SÍ — stock 0 y Sep cayó (prom Feb-Ago 172) | AF30: {=IF(X30="","",IF(AE30<>"",MAX(X30,AVERAGE(INDEX(Ventas!$C$2:$I$5000,MATCH($A30,Ventas!$A$2:$A$5000,0),0))),X30))} -> 172.14286 | AG30: =IF(AF30="","",ROUND(AF30*4,0)-P30) -> 689 | AH30: =IF(A30="","",IF(AF30="","SIN HISTORIAL",IF(AF30=0,"SIN VENTAS",IF(AG30>0.1*ROUND(AF30*4,0),"COMPRAR",IF(AND(-AG30>0.1*ROUND(AF30*4,0),SUM(I30:M30)+IF($AD$3="SI",SUM(N30),0)>0),"PEDIR MENOS",IF(P30/AF30>8,"SOBRESTOCK","OK")))))) -> COMPRAR
A31: 5110923-9999 | B31: PU BONDEADO | C31: NAPA EVA PIQUE 3.3mm | D31: NEGRO | E31: 0 | O31: =IF(A31="","SIN SKU — cargar código para calcular",IF(X31="","SIN HISTORIAL DE VENTAS — artículo nuevo o código distinto en Ventas",IF(X31=0,IF(P31>0,"SIN VENTAS Jun-Sep — no comprar ("&TEXT(P31,"#,##0")&" m disponibles)","SIN VENTAS Jun-Sep — no comprar"),IF(AA31>0.1*Y31,"COMPRAR — faltan "&TEXT(AA31,"#,##0")&" m para 4 meses"&IF(P31-E31>0," (ya contando pedidos)",""),IF(AND(-AA31>0.1*Y31,SUM(I31:M31)+IF($AD$3="SI",SUM(N31),0)>0),"PEDIR MENOS — sobran "&TEXT(-AA31,"#,##0")&" m; revisar pedidos sin facturar ("&TEXT(SUM(I31:M31)+IF($AD$3="SI",SUM(N31),0),"#,##0")&" m)",IF(Z31>8,"SOBRESTOCK — "&TEXT(Z31,"0.0")&" meses de cobertura","OK — cubierto ("&TEXT(Z31,"0.0")&" meses)")))))) -> SIN VENTAS Jun-Sep — no comprar | P31: =E31+N(F31)+SUM(G31:M31)+IF($AD$3="SI",SUM(N31),0) -> 0 | Q31: En los materiales bondeados quizá se deba tomar en cuenta el cierre de fábrica. | X31: =IFERROR(VLOOKUP($A31,Ventas!$A$2:$L$5000,12,FALSE()),"") -> 0 | Y31: =IF(X31="","",ROUND(X31*4,0)) -> 0 | Z31: =IF(OR(X31="",X31=0),"",ROUND(P31/X31,1)) | AA31: =IF(Y31="","",Y31-P31) -> 0 | AB31: =IF(A31="","",IF(COUNTIF($A$8:$A$670,A31)>1,"DUPLICADO","")) | AC31: {=IF(AH31<>"COMPRAR","",IF(MAX(INDEX(Ventas!$G$2:$G$5000,MATCH($A31,Ventas!$A$2:$A$5000,0)),INDEX(Ventas!$H$2:$H$5000,MATCH($A31,Ventas!$A$2:$A$5000,0)),INDEX(Ventas!$I$2:$I$5000,MATCH($A31,Ventas!$A$2:$A$5000,0)),INDEX(Ventas!$J$2:$J$5000,MATCH($A31,Ventas!$A$2:$A$5000,0)))>0.5*AF31*4,"1 mes = "&TEXT(MAX(INDEX(Ventas!$G$2:$G$5000,MATCH($A31,Ventas!$A$2:$A$5000,0)),INDEX(Ventas!$H$2:$H$5000,MATCH($A31,Ventas!$A$2:$A$5000,0)),INDEX(Ventas!$I$2:$I$5000,MATCH($A31,Ventas!$A$2:$A$5000,0)),INDEX(Ventas!$J$2:$J$5000,MATCH($A31,Ventas!$A$2:$A$5000,0)))/(AF31*4),"0%")&" de 4 meses",""))} | AD31: =IF(OR(X31="",X31=0),"",IF(E31+N(F31)<X31*$AD$5,"SÍ — "&TEXT(E31+N(F31),"#,##0")&" m vs "&TEXT(X31*$AD$5,"#,##0")&" m","")) | AE31: {=IF(X31="","",IF(AND(E31=0,AVERAGE(INDEX(Ventas!$C$2:$I$5000,MATCH($A31,Ventas!$A$2:$A$5000,0),0))>0,INDEX(Ventas!$J$2:$J$5000,MATCH($A31,Ventas!$A$2:$A$5000,0))<0.5*AVERAGE(INDEX(Ventas!$C$2:$I$5000,MATCH($A31,Ventas!$A$2:$A$5000,0),0))),"SÍ — stock 0 y Sep cayó (prom Feb-Ago "&TEXT(AVERAGE(INDEX(Ventas!$C$2:$I$5000,MATCH($A31,Ventas!$A$2:$A$5000,0),0)),"#,##0")&")",""))} -> SÍ — stock 0 y Sep cayó (prom Feb-Ago 97) | AF31: {=IF(X31="","",IF(AE31<>"",MAX(X31,AVERAGE(INDEX(Ventas!$C$2:$I$5000,MATCH($A31,Ventas!$A$2:$A$5000,0),0))),X31))} -> 96.642857 | AG31: =IF(AF31="","",ROUND(AF31*4,0)-P31) -> 387 | AH31: =IF(A31="","",IF(AF31="","SIN HISTORIAL",IF(AF31=0,"SIN VENTAS",IF(AG31>0.1*ROUND(AF31*4,0),"COMPRAR",IF(AND(-AG31>0.1*ROUND(AF31*4,0),SUM(I31:M31)+IF($AD$3="SI",SUM(N31),0)>0),"PEDIR MENOS",IF(P31/AF31>8,"SOBRESTOCK","OK")))))) -> COMPRAR
A32: 5099923-0000 | B32: PU BONDEADO | C32: CALI EVA PIQUE 3.3mm | D32: BLANCO | E32: 400 | O32: =IF(A32="","SIN SKU — cargar código para calcular",IF(X32="","SIN HISTORIAL DE VENTAS — artículo nuevo o código distinto en Ventas",IF(X32=0,IF(P32>0,"SIN VENTAS Jun-Sep — no comprar ("&TEXT(P32,"#,##0")&" m disponibles)","SIN VENTAS Jun-Sep — no comprar"),IF(AA32>0.1*Y32,"COMPRAR — faltan "&TEXT(AA32,"#,##0")&" m para 4 meses"&IF(P32-E32>0," (ya contando pedidos)",""),IF(AND(-AA32>0.1*Y32,SUM(I32:M32)+IF($AD$3="SI",SUM(N32),0)>0),"PEDIR MENOS — sobran "&TEXT(-AA32,"#,##0")&" m; revisar pedidos sin facturar ("&TEXT(SUM(I32:M32)+IF($AD$3="SI",SUM(N32),0),"#,##0")&" m)",IF(Z32>8,"SOBRESTOCK — "&TEXT(Z32,"0.0")&" meses de cobertura","OK — cubierto ("&TEXT(Z32,"0.0")&" meses)")))))) -> SOBRESTOCK — 10.4 meses de cobertura | P32: =E32+N(F32)+SUM(G32:M32)+IF($AD$3="SI",SUM(N32),0) -> 400 | Q32: En los materiales bondeados quizá se deba tomar en cuenta el cierre de fábrica. | X32: =IFERROR(VLOOKUP($A32,Ventas!$A$2:$L$5000,12,FALSE()),"") -> 38.5 | Y32: =IF(X32="","",ROUND(X32*4,0)) -> 154 | Z32: =IF(OR(X32="",X32=0),"",ROUND(P32/X32,1)) -> 10.4 | AA32: =IF(Y32="","",Y32-P32) -> -246 | AB32: =IF(A32="","",IF(COUNTIF($A$8:$A$670,A32)>1,"DUPLICADO","")) | AC32: {=IF(AH32<>"COMPRAR","",IF(MAX(INDEX(Ventas!$G$2:$G$5000,MATCH($A32,Ventas!$A$2:$A$5000,0)),INDEX(Ventas!$H$2:$H$5000,MATCH($A32,Ventas!$A$2:$A$5000,0)),INDEX(Ventas!$I$2:$I$5000,MATCH($A32,Ventas!$A$2:$A$5000,0)),INDEX(Ventas!$J$2:$J$5000,MATCH($A32,Ventas!$A$2:$A$5000,0)))>0.5*AF32*4,"1 mes = "&TEXT(MAX(INDEX(Ventas!$G$2:$G$5000,MATCH($A32,Ventas!$A$2:$A$5000,0)),INDEX(Ventas!$H$2:$H$5000,MATCH($A32,Ventas!$A$2:$A$5000,0)),INDEX(Ventas!$I$2:$I$5000,MATCH($A32,Ventas!$A$2:$A$5000,0)),INDEX(Ventas!$J$2:$J$5000,MATCH($A32,Ventas!$A$2:$A$5000,0)))/(AF32*4),"0%")&" de 4 meses",""))} | AD32: =IF(OR(X32="",X32=0),"",IF(E32+N(F32)<X32*$AD$5,"SÍ — "&TEXT(E32+N(F32),"#,##0")&" m vs "&TEXT(X32*$AD$5,"#,##0")&" m","")) | AE32: {=IF(X32="","",IF(AND(E32=0,AVERAGE(INDEX(Ventas!$C$2:$I$5000,MATCH($A32,Ventas!$A$2:$A$5000,0),0))>0,INDEX(Ventas!$J$2:$J$5000,MATCH($A32,Ventas!$A$2:$A$5000,0))<0.5*AVERAGE(INDEX(Ventas!$C$2:$I$5000,MATCH($A32,Ventas!$A$2:$A$5000,0),0))),"SÍ — stock 0 y Sep cayó (prom Feb-Ago "&TEXT(AVERAGE(INDEX(Ventas!$C$2:$I$5000,MATCH($A32,Ventas!$A$2:$A$5000,0),0)),"#,##0")&")",""))} | AF32: {=IF(X32="","",IF(AE32<>"",MAX(X32,AVERAGE(INDEX(Ventas!$C$2:$I$5000,MATCH($A32,Ventas!$A$2:$A$5000,0),0))),X32))} -> 38.5 | AG32: =IF(AF32="","",ROUND(AF32*4,0)-P32) -> -246 | AH32: =IF(A32="","",IF(AF32="","SIN HISTORIAL",IF(AF32=0,"SIN VENTAS",IF(AG32>0.1*ROUND(AF32*4,0),"COMPRAR",IF(AND(-AG32>0.1*ROUND(AF32*4,0),SUM(I32:M32)+IF($AD$3="SI",SUM(N32),0)>0),"PEDIR MENOS",IF(P32/AF32>8,"SOBRESTOCK","OK")))))) -> SOBRESTOCK
A33: 5100923-0000 | B33: PU BONDEADO | C33: TOKIO EVA PIQUE 3.3mm | D33: BLANCO | E33: 0 | O33: =IF(A33="","SIN SKU — cargar código para calcular",IF(X33="","SIN HISTORIAL DE VENTAS — artículo nuevo o código distinto en Ventas",IF(X33=0,IF(P33>0,"SIN VENTAS Jun-Sep — no comprar ("&TEXT(P33,"#,##0")&" m disponibles)","SIN VENTAS Jun-Sep — no comprar"),IF(AA33>0.1*Y33,"COMPRAR — faltan "&TEXT(AA33,"#,##0")&" m para 4 meses"&IF(P33-E33>0," (ya contando pedidos)",""),IF(AND(-AA33>0.1*Y33,SUM(I33:M33)+IF($AD$3="SI",SUM(N33),0)>0),"PEDIR MENOS — sobran "&TEXT(-AA33,"#,##0")&" m; revisar pedidos sin facturar ("&TEXT(SUM(I33:M33)+IF($AD$3="SI",SUM(N33),0),"#,##0")&" m)",IF(Z33>8,"SOBRESTOCK — "&TEXT(Z33,"0.0")&" meses de cobertura","OK — cubierto ("&TEXT(Z33,"0.0")&" meses)")))))) -> COMPRAR — faltan 120 m para 4 meses | P33: =E33+N(F33)+SUM(G33:M33)+IF($AD$3="SI",SUM(N33),0) -> 0 | Q33: En los materiales bondeados quizá se deba tomar en cuenta el cierre de fábrica. | X33: =IFERROR(VLOOKUP($A33,Ventas!$A$2:$L$5000,12,FALSE()),"") -> 30 | Y33: =IF(X33="","",ROUND(X33*4,0)) -> 120 | Z33: =IF(OR(X33="",X33=0),"",ROUND(P33/X33,1)) -> 0 | AA33: =IF(Y33="","",Y33-P33) -> 120 | AB33: =IF(A33="","",IF(COUNTIF($A$8:$A$670,A33)>1,"DUPLICADO","")) | AC33: {=IF(AH33<>"COMPRAR","",IF(MAX(INDEX(Ventas!$G$2:$G$5000,MATCH($A33,Ventas!$A$2:$A$5000,0)),INDEX(Ventas!$H$2:$H$5000,MATCH($A33,Ventas!$A$2:$A$5000,0)),INDEX(Ventas!$I$2:$I$5000,MATCH($A33,Ventas!$A$2:$A$5000,0)),INDEX(Ventas!$J$2:$J$5000,MATCH($A33,Ventas!$A$2:$A$5000,0)))>0.5*AF33*4,"1 mes = "&TEXT(MAX(INDEX(Ventas!$G$2:$G$5000,MATCH($A33,Ventas!$A$2:$A$5000,0)),INDEX(Ventas!$H$2:$H$5000,MATCH($A33,Ventas!$A$2:$A$5000,0)),INDEX(Ventas!$I$2:$I$5000,MATCH($A33,Ventas!$A$2:$A$5000,0)),INDEX(Ventas!$J$2:$J$5000,MATCH($A33,Ventas!$A$2:$A$5000,0)))/(AF33*4),"0%")&" de 4 meses",""))} | AD33: =IF(OR(X33="",X33=0),"",IF(E33+N(F33)<X33*$AD$5,"SÍ — "&TEXT(E33+N(F33),"#,##0")&" m vs "&TEXT(X33*$AD$5,"#,##0")&" m","")) -> SÍ — 0 m vs 16 m | AE33: {=IF(X33="","",IF(AND(E33=0,AVERAGE(INDEX(Ventas!$C$2:$I$5000,MATCH($A33,Ventas!$A$2:$A$5000,0),0))>0,INDEX(Ventas!$J$2:$J$5000,MATCH($A33,Ventas!$A$2:$A$5000,0))<0.5*AVERAGE(INDEX(Ventas!$C$2:$I$5000,MATCH($A33,Ventas!$A$2:$A$5000,0),0))),"SÍ — stock 0 y Sep cayó (prom Feb-Ago "&TEXT(AVERAGE(INDEX(Ventas!$C$2:$I$5000,MATCH($A33,Ventas!$A$2:$A$5000,0),0)),"#,##0")&")",""))} | AF33: {=IF(X33="","",IF(AE33<>"",MAX(X33,AVERAGE(INDEX(Ventas!$C$2:$I$5000,MATCH($A33,Ventas!$A$2:$A$5000,0),0))),X33))} -> 30 | AG33: =IF(AF33="","",ROUND(AF33*4,0)-P33) -> 120 | AH33: =IF(A33="","",IF(AF33="","SIN HISTORIAL",IF(AF33=0,"SIN VENTAS",IF(AG33>0.1*ROUND(AF33*4,0),"COMPRAR",IF(AND(-AG33>0.1*ROUND(AF33*4,0),SUM(I33:M33)+IF($AD$3="SI",SUM(N33),0)>0),"PEDIR MENOS",IF(P33/AF33>8,"SOBRESTOCK","OK")))))) -> COMPRAR
A34: 5110923-0000 | B34: PU BONDEADO | C34: NAPA EVA PIQUE 3.3mm | D34: BLANCO | E34: 387 | O34: =IF(A34="","SIN SKU — cargar código para calcular",IF(X34="","SIN HISTORIAL DE VENTAS — artículo nuevo o código distinto en Ventas",IF(X34=0,IF(P34>0,"SIN VENTAS Jun-Sep — no comprar ("&TEXT(P34,"#,##0")&" m disponibles)","SIN VENTAS Jun-Sep — no comprar"),IF(AA34>0.1*Y34,"COMPRAR — faltan "&TEXT(AA34,"#,##0")&" m para 4 meses"&IF(P34-E34>0," (ya contando pedidos)",""),IF(AND(-AA34>0.1*Y34,SUM(I34:M34)+IF($AD$3="SI",SUM(N34),0)>0),"PEDIR MENOS — sobran "&TEXT(-AA34,"#,##0")&" m; revisar pedidos sin facturar ("&TEXT(SUM(I34:M34)+IF($AD$3="SI",SUM(N34),0),"#,##0")&" m)",IF(Z34>8,"SOBRESTOCK — "&TEXT(Z34,"0.0")&" meses de cobertura","OK — cubierto ("&TEXT(Z34,"0.0")&" meses)")))))) -> SOBRESTOCK — 25.8 meses de cobertura | P34: =E34+N(F34)+SUM(G34:M34)+IF($AD$3="SI",SUM(N34),0) -> 387 | Q34: En los materiales bondeados quizá se deba tomar en cuenta el cierre de fábrica. | X34: =IFERROR(VLOOKUP($A34,Ventas!$A$2:$L$5000,12,FALSE()),"") -> 15 | Y34: =IF(X34="","",ROUND(X34*4,0)) -> 60 | Z34: =IF(OR(X34="",X34=0),"",ROUND(P34/X34,1)) -> 25.8 | AA34: =IF(Y34="","",Y34-P34) -> -327 | AB34: =IF(A34="","",IF(COUNTIF($A$8:$A$670,A34)>1,"DUPLICADO","")) | AC34: {=IF(AH34<>"COMPRAR","",IF(MAX(INDEX(Ventas!$G$2:$G$5000,MATCH($A34,Ventas!$A$2:$A$5000,0)),INDEX(Ventas!$H$2:$H$5000,MATCH($A34,Ventas!$A$2:$A$5000,0)),INDEX(Ventas!$I$2:$I$5000,MATCH($A34,Ventas!$A$2:$A$5000,0)),INDEX(Ventas!$J$2:$J$5000,MATCH($A34,Ventas!$A$2:$A$5000,0)))>0.5*AF34*4,"1 mes = "&TEXT(MAX(INDEX(Ventas!$G$2:$G$5000,MATCH($A34,Ventas!$A$2:$A$5000,0)),INDEX(Ventas!$H$2:$H$5000,MATCH($A34,Ventas!$A$2:$A$5000,0)),INDEX(Ventas!$I$2:$I$5000,MATCH($A34,Ventas!$A$2:$A$5000,0)),INDEX(Ventas!$J$2:$J$5000,MATCH($A34,Ventas!$A$2:$A$5000,0)))/(AF34*4),"0%")&" de 4 meses",""))} | AD34: =IF(OR(X34="",X34=0),"",IF(E34+N(F34)<X34*$AD$5,"SÍ — "&TEXT(E34+N(F34),"#,##0")&" m vs "&TEXT(X34*$AD$5,"#,##0")&" m","")) | AE34: {=IF(X34="","",IF(AND(E34=0,AVERAGE(INDEX(Ventas!$C$2:$I$5000,MATCH($A34,Ventas!$A$2:$A$5000,0),0))>0,INDEX(Ventas!$J$2:$J$5000,MATCH($A34,Ventas!$A$2:$A$5000,0))<0.5*AVERAGE(INDEX(Ventas!$C$2:$I$5000,MATCH($A34,Ventas!$A$2:$A$5000,0),0))),"SÍ — stock 0 y Sep cayó (prom Feb-Ago "&TEXT(AVERAGE(INDEX(Ventas!$C$2:$I$5000,MATCH($A34,Ventas!$A$2:$A$5000,0),0)),"#,##0")&")",""))} | AF34: {=IF(X34="","",IF(AE34<>"",MAX(X34,AVERAGE(INDEX(Ventas!$C$2:$I$5000,MATCH($A34,Ventas!$A$2:$A$5000,0),0))),X34))} -> 15 | AG34: =IF(AF34="","",ROUND(AF34*4,0)-P34) -> -327 | AH34: =IF(A34="","",IF(AF34="","SIN HISTORIAL",IF(AF34=0,"SIN VENTAS",IF(AG34>0.1*ROUND(AF34*4,0),"COMPRAR",IF(AND(-AG34>0.1*ROUND(AF34*4,0),SUM(I34:M34)+IF($AD$3="SI",SUM(N34),0)>0),"PEDIR MENOS",IF(P34/AF34>8,"SOBRESTOCK","OK")))))) -> SOBRESTOCK
A35: 5130923-9999 | B35: PU BONDEADO | C35: CALI EVA pique 2.4mm | D35: NEGRO | E35: 0 | L35: 4000 | O35: =IF(A35="","SIN SKU — cargar código para calcular",IF(X35="","SIN HISTORIAL DE VENTAS — artículo nuevo o código distinto en Ventas",IF(X35=0,IF(P35>0,"SIN VENTAS Jun-Sep — no comprar ("&TEXT(P35,"#,##0")&" m disponibles)","SIN VENTAS Jun-Sep — no comprar"),IF(AA35>0.1*Y35,"COMPRAR — faltan "&TEXT(AA35,"#,##0")&" m para 4 meses"&IF(P35-E35>0," (ya contando pedidos)",""),IF(AND(-AA35>0.1*Y35,SUM(I35:M35)+IF($AD$3="SI",SUM(N35),0)>0),"PEDIR MENOS — sobran "&TEXT(-AA35,"#,##0")&" m; revisar pedidos sin facturar ("&TEXT(SUM(I35:M35)+IF($AD$3="SI",SUM(N35),0),"#,##0")&" m)",IF(Z35>8,"SOBRESTOCK — "&TEXT(Z35,"0.0")&" meses de cobertura","OK — cubierto ("&TEXT(Z35,"0.0")&" meses)")))))) -> PEDIR MENOS — sobran 413 m; revisar pedidos sin facturar (4,000 m) | P35: =E35+N(F35)+SUM(G35:M35)+IF($AD$3="SI",SUM(N35),0) -> 4000 | Q35: En los materiales bondeados quizá se deba tomar en cuenta el cierre de fábrica. | X35: =IFERROR(VLOOKUP($A35,Ventas!$A$2:$L$5000,12,FALSE()),"") -> 896.75 | Y35: =IF(X35="","",ROUND(X35*4,0)) -> 3587 | Z35: =IF(OR(X35="",X35=0),"",ROUND(P35/X35,1)) -> 4.5 | AA35: =IF(Y35="","",Y35-P35) -> -413 | AB35: =IF(A35="","",IF(COUNTIF($A$8:$A$670,A35)>1,"DUPLICADO","")) | AC35: {=IF(AH35<>"COMPRAR","",IF(MAX(INDEX(Ventas!$G$2:$G$5000,MATCH($A35,Ventas!$A$2:$A$5000,0)),INDEX(Ventas!$H$2:$H$5000,MATCH($A35,Ventas!$A$2:$A$5000,0)),INDEX(Ventas!$I$2:$I$5000,MATCH($A35,Ventas!$A$2:$A$5000,0)),INDEX(Ventas!$J$2:$J$5000,MATCH($A35,Ventas!$A$2:$A$5000,0)))>0.5*AF35*4,"1 mes = "&TEXT(MAX(INDEX(Ventas!$G$2:$G$5000,MATCH($A35,Ventas!$A$2:$A$5000,0)),INDEX(Ventas!$H$2:$H$5000,MATCH($A35,Ventas!$A$2:$A$5000,0)),INDEX(Ventas!$I$2:$I$5000,MATCH($A35,Ventas!$A$2:$A$5000,0)),INDEX(Ventas!$J$2:$J$5000,MATCH($A35,Ventas!$A$2:$A$5000,0)))/(AF35*4),"0%")&" de 4 meses",""))} | AD35: =IF(OR(X35="",X35=0),"",IF(E35+N(F35)<X35*$AD$5,"SÍ — "&TEXT(E35+N(F35),"#,##0")&" m vs "&TEXT(X35*$AD$5,"#,##0")&" m","")) -> SÍ — 0 m vs 475 m | AE35: {=IF(X35="","",IF(AND(E35=0,AVERAGE(INDEX(Ventas!$C$2:$I$5000,MATCH($A35,Ventas!$A$2:$A$5000,0),0))>0,INDEX(Ventas!$J$2:$J$5000,MATCH($A35,Ventas!$A$2:$A$5000,0))<0.5*AVERAGE(INDEX(Ventas!$C$2:$I$5000,MATCH($A35,Ventas!$A$2:$A$5000,0),0))),"SÍ — stock 0 y Sep cayó (prom Feb-Ago "&TEXT(AVERAGE(INDEX(Ventas!$C$2:$I$5000,MATCH($A35,Ventas!$A$2:$A$5000,0),0)),"#,##0")&")",""))} -> SÍ — stock 0 y Sep cayó (prom Feb-Ago 1,140) | AF35: {=IF(X35="","",IF(AE35<>"",MAX(X35,AVERAGE(INDEX(Ventas!$C$2:$I$5000,MATCH($A35,Ventas!$A$2:$A$5000,0),0))),X35))} -> 1139.7143 | AG35: =IF(AF35="","",ROUND(AF35*4,0)-P35) -> 559 | AH35: =IF(A35="","",IF(AF35="","SIN HISTORIAL",IF(AF35=0,"SIN VENTAS",IF(AG35>0.1*ROUND(AF35*4,0),"COMPRAR",IF(AND(-AG35>0.1*ROUND(AF35*4,0),SUM(I35:M35)+IF($AD$3="SI",SUM(N35),0)>0),"PEDIR MENOS",IF(P35/AF35>8,"SOBRESTOCK","OK")))))) -> COMPRAR
A36: 5130923-0000 | B36: PU BONDEADO | C36: CALI EVA pique 2.4mm | D36: BLANCO | E36: 0 | O36: =IF(A36="","SIN SKU — cargar código para calcular",IF(X36="","SIN HISTORIAL DE VENTAS — artículo nuevo o código distinto en Ventas",IF(X36=0,IF(P36>0,"SIN VENTAS Jun-Sep — no comprar ("&TEXT(P36,"#,##0")&" m disponibles)","SIN VENTAS Jun-Sep — no comprar"),IF(AA36>0.1*Y36,"COMPRAR — faltan "&TEXT(AA36,"#,##0")&" m para 4 meses"&IF(P36-E36>0," (ya contando pedidos)",""),IF(AND(-AA36>0.1*Y36,SUM(I36:M36)+IF($AD$3="SI",SUM(N36),0)>0),"PEDIR MENOS — sobran "&TEXT(-AA36,"#,##0")&" m; revisar pedidos sin facturar ("&TEXT(SUM(I36:M36)+IF($AD$3="SI",SUM(N36),0),"#,##0")&" m)",IF(Z36>8,"SOBRESTOCK — "&TEXT(Z36,"0.0")&" meses de cobertura","OK — cubierto ("&TEXT(Z36,"0.0")&" meses)")))))) -> SIN VENTAS Jun-Sep — no comprar | P36: =E36+N(F36)+SUM(G36:M36)+IF($AD$3="SI",SUM(N36),0) -> 0 | Q36: En los materiales bondeados quizá se deba tomar en cuenta el cierre de fábrica. | X36: =IFERROR(VLOOKUP($A36,Ventas!$A$2:$L$5000,12,FALSE()),"") -> 0 | Y36: =IF(X36="","",ROUND(X36*4,0)) -> 0 | Z36: =IF(OR(X36="",X36=0),"",ROUND(P36/X36,1)) | AA36: =IF(Y36="","",Y36-P36) -> 0 | AB36: =IF(A36="","",IF(COUNTIF($A$8:$A$670,A36)>1,"DUPLICADO","")) | AC36: {=IF(AH36<>"COMPRAR","",IF(MAX(INDEX(Ventas!$G$2:$G$5000,MATCH($A36,Ventas!$A$2:$A$5000,0)),INDEX(Ventas!$H$2:$H$5000,MATCH($A36,Ventas!$A$2:$A$5000,0)),INDEX(Ventas!$I$2:$I$5000,MATCH($A36,Ventas!$A$2:$A$5000,0)),INDEX(Ventas!$J$2:$J$5000,MATCH($A36,Ventas!$A$2:$A$5000,0)))>0.5*AF36*4,"1 mes = "&TEXT(MAX(INDEX(Ventas!$G$2:$G$5000,MATCH($A36,Ventas!$A$2:$A$5000,0)),INDEX(Ventas!$H$2:$H$5000,MATCH($A36,Ventas!$A$2:$A$5000,0)),INDEX(Ventas!$I$2:$I$5000,MATCH($A36,Ventas!$A$2:$A$5000,0)),INDEX(Ventas!$J$2:$J$5000,MATCH($A36,Ventas!$A$2:$A$5000,0)))/(AF36*4),"0%")&" de 4 meses",""))} | AD36: =IF(OR(X36="",X36=0),"",IF(E36+N(F36)<X36*$AD$5,"SÍ — "&TEXT(E36+N(F36),"#,##0")&" m vs "&TEXT(X36*$AD$5,"#,##0")&" m","")) | AE36: {=IF(X36="","",IF(AND(E36=0,AVERAGE(INDEX(Ventas!$C$2:$I$5000,MATCH($A36,Ventas!$A$2:$A$5000,0),0))>0,INDEX(Ventas!$J$2:$J$5000,MATCH($A36,Ventas!$A$2:$A$5000,0))<0.5*AVERAGE(INDEX(Ventas!$C$2:$I$5000,MATCH($A36,Ventas!$A$2:$A$5000,0),0))),"SÍ — stock 0 y Sep cayó (prom Feb-Ago "&TEXT(AVERAGE(INDEX(Ventas!$C$2:$I$5000,MATCH($A36,Ventas!$A$2:$A$5000,0),0)),"#,##0")&")",""))} | AF36: {=IF(X36="","",IF(AE36<>"",MAX(X36,AVERAGE(INDEX(Ventas!$C$2:$I$5000,MATCH($A36,Ventas!$A$2:$A$5000,0),0))),X36))} -> 0 | AG36: =IF(AF36="","",ROUND(AF36*4,0)-P36) -> 0 | AH36: =IF(A36="","",IF(AF36="","SIN HISTORIAL",IF(AF36=0,"SIN VENTAS",IF(AG36>0.1*ROUND(AF36*4,0),"COMPRAR",IF(AND(-AG36>0.1*ROUND(AF36*4,0),SUM(I36:M36)+IF($AD$3="SI",SUM(N36),0)>0),"PEDIR MENOS",IF(P36/AF36>8,"SOBRESTOCK","OK")))))) -> SIN VENTAS
A37: 582923-0297 | B37: PU BONDEADO | C37: BOGOTA eva pique 2.4mm | D37: SUELA | E37: 2014 | O37: =IF(A37="","SIN SKU — cargar código para calcular",IF(X37="","SIN HISTORIAL DE VENTAS — artículo nuevo o código distinto en Ventas",IF(X37=0,IF(P37>0,"SIN VENTAS Jun-Sep — no comprar ("&TEXT(P37,"#,##0")&" m disponibles)","SIN VENTAS Jun-Sep — no comprar"),IF(AA37>0.1*Y37,"COMPRAR — faltan "&TEXT(AA37,"#,##0")&" m para 4 meses"&IF(P37-E37>0," (ya contando pedidos)",""),IF(AND(-AA37>0.1*Y37,SUM(I37:M37)+IF($AD$3="SI",SUM(N37),0)>0),"PEDIR MENOS — sobran "&TEXT(-AA37,"#,##0")&" m; revisar pedidos sin facturar ("&TEXT(SUM(I37:M37)+IF($AD$3="SI",SUM(N37),0),"#,##0")&" m)",IF(Z37>8,"SOBRESTOCK — "&TEXT(Z37,"0.0")&" meses de cobertura","OK — cubierto ("&TEXT(Z37,"0.0")&" meses)")))))) -> SOBRESTOCK — 37.5 meses de cobertura | P37: =E37+N(F37)+SUM(G37:M37)+IF($AD$3="SI",SUM(N37),0) -> 2014 | Q37: En los materiales bondeados quizá se deba tomar en cuenta el cierre de fábrica. | X37: =IFERROR(VLOOKUP($A37,Ventas!$A$2:$L$5000,12,FALSE()),"") -> 53.75 | Y37: =IF(X37="","",ROUND(X37*4,0)) -> 215 | Z37: =IF(OR(X37="",X37=0),"",ROUND(P37/X37,1)) -> 37.5 | AA37: =IF(Y37="","",Y37-P37) -> -1799 | AB37: =IF(A37="","",IF(COUNTIF($A$8:$A$670,A37)>1,"DUPLICADO","")) | AC37: {=IF(AH37<>"COMPRAR","",IF(MAX(INDEX(Ventas!$G$2:$G$5000,MATCH($A37,Ventas!$A$2:$A$5000,0)),INDEX(Ventas!$H$2:$H$5000,MATCH($A37,Ventas!$A$2:$A$5000,0)),INDEX(Ventas!$I$2:$I$5000,MATCH($A37,Ventas!$A$2:$A$5000,0)),INDEX(Ventas!$J$2:$J$5000,MATCH($A37,Ventas!$A$2:$A$5000,0)))>0.5*AF37*4,"1 mes = "&TEXT(MAX(INDEX(Ventas!$G$2:$G$5000,MATCH($A37,Ventas!$A$2:$A$5000,0)),INDEX(Ventas!$H$2:$H$5000,MATCH($A37,Ventas!$A$2:$A$5000,0)),INDEX(Ventas!$I$2:$I$5000,MATCH($A37,Ventas!$A$2:$A$5000,0)),INDEX(Ventas!$J$2:$J$5000,MATCH($A37,Ventas!$A$2:$A$5000,0)))/(AF37*4),"0%")&" de 4 meses",""))} | AD37: =IF(OR(X37="",X37=0),"",IF(E37+N(F37)<X37*$AD$5,"SÍ — "&TEXT(E37+N(F37),"#,##0")&" m vs "&TEXT(X37*$AD$5,"#,##0")&" m","")) | AE37: {=IF(X37="","",IF(AND(E37=0,AVERAGE(INDEX(Ventas!$C$2:$I$5000,MATCH($A37,Ventas!$A$2:$A$5000,0),0))>0,INDEX(Ventas!$J$2:$J$5000,MATCH($A37,Ventas!$A$2:$A$5000,0))<0.5*AVERAGE(INDEX(Ventas!$C$2:$I$5000,MATCH($A37,Ventas!$A$2:$A$5000,0),0))),"SÍ — stock 0 y Sep cayó (prom Feb-Ago "&TEXT(AVERAGE(INDEX(Ventas!$C$2:$I$5000,MATCH($A37,Ventas!$A$2:$A$5000,0),0)),"#,##0")&")",""))} | AF37: {=IF(X37="","",IF(AE37<>"",MAX(X37,AVERAGE(INDEX(Ventas!$C$2:$I$5000,MATCH($A37,Ventas!$A$2:$A$5000,0),0))),X37))} -> 53.75 | AG37: =IF(AF37="","",ROUND(AF37*4,0)-P37) -> -1799 | AH37: =IF(A37="","",IF(AF37="","SIN HISTORIAL",IF(AF37=0,"SIN VENTAS",IF(AG37>0.1*ROUND(AF37*4,0),"COMPRAR",IF(AND(-AG37>0.1*ROUND(AF37*4,0),SUM(I37:M37)+IF($AD$3="SI",SUM(N37),0)>0),"PEDIR MENOS",IF(P37/AF37>8,"SOBRESTOCK","OK")))))) -> SOBRESTOCK
A38: 5130923-0010 | B38: PU BONDEADO | C38: CALI EVA pique 2.4mm | D38: CHOCOLATE | E38: 0 | I38: 1000 | L38: 1500 | O38: =IF(A38="","SIN SKU — cargar código para calcular",IF(X38="","SIN HISTORIAL DE VENTAS — artículo nuevo o código distinto en Ventas",IF(X38=0,IF(P38>0,"SIN VENTAS Jun-Sep — no comprar ("&TEXT(P38,"#,##0")&" m disponibles)","SIN VENTAS Jun-Sep — no comprar"),IF(AA38>0.1*Y38,"COMPRAR — faltan "&TEXT(AA38,"#,##0")&" m para 4 meses"&IF(P38-E38>0," (ya contando pedidos)",""),IF(AND(-AA38>0.1*Y38,SUM(I38:M38)+IF($AD$3="SI",SUM(N38),0)>0),"PEDIR MENOS — sobran "&TEXT(-AA38,"#,##0")&" m; revisar pedidos sin facturar ("&TEXT(SUM(I38:M38)+IF($AD$3="SI",SUM(N38),0),"#,##0")&" m)",IF(Z38>8,"SOBRESTOCK — "&TEXT(Z38,"0.0")&" meses de cobertura","OK — cubierto ("&TEXT(Z38,"0.0")&" meses)")))))) -> PEDIR MENOS — sobran 1,690 m; revisar pedidos sin facturar (2,500 m) | P38: =E38+N(F38)+SUM(G38:M38)+IF($AD$3="SI",SUM(N38),0) -> 2500 | Q38: En los materiales bondeados quizá se deba tomar en cuenta el cierre de fábrica. | X38: =IFERROR(VLOOKUP($A38,Ventas!$A$2:$L$5000,12,FALSE()),"") -> 202.5 | Y38: =IF(X38="","",ROUND(X38*4,0)) -> 810 | Z38: =IF(OR(X38="",X38=0),"",ROUND(P38/X38,1)) -> 12.3 | AA38: =IF(Y38="","",Y38-P38) -> -1690 | AB38: =IF(A38="","",IF(COUNTIF($A$8:$A$670,A38)>1,"DUPLICADO","")) | AC38: {=IF(AH38<>"COMPRAR","",IF(MAX(INDEX(Ventas!$G$2:$G$5000,MATCH($A38,Ventas!$A$2:$A$5000,0)),INDEX(Ventas!$H$2:$H$5000,MATCH($A38,Ventas!$A$2:$A$5000,0)),INDEX(Ventas!$I$2:$I$5000,MATCH($A38,Ventas!$A$2:$A$5000,0)),INDEX(Ventas!$J$2:$J$5000,MATCH($A38,Ventas!$A$2:$A$5000,0)))>0.5*AF38*4,"1 mes = "&TEXT(MAX(INDEX(Ventas!$G$2:$G$5000,MATCH($A38,Ventas!$A$2:$A$5000,0)),INDEX(Ventas!$H$2:$H$5000,MATCH($A38,Ventas!$A$2:$A$5000,0)),INDEX(Ventas!$I$2:$I$5000,MATCH($A38,Ventas!$A$2:$A$5000,0)),INDEX(Ventas!$J$2:$J$5000,MATCH($A38,Ventas!$A$2:$A$5000,0)))/(AF38*4),"0%")&" de 4 meses",""))} | AD38: =IF(OR(X38="",X38=0),"",IF(E38+N(F38)<X38*$AD$5,"SÍ — "&TEXT(E38+N(F38),"#,##0")&" m vs "&TEXT(X38*$AD$5,"#,##0")&" m","")) -> SÍ — 0 m vs 107 m | AE38: {=IF(X38="","",IF(AND(E38=0,AVERAGE(INDEX(Ventas!$C$2:$I$5000,MATCH($A38,Ventas!$A$2:$A$5000,0),0))>0,INDEX(Ventas!$J$2:$J$5000,MATCH($A38,Ventas!$A$2:$A$5000,0))<0.5*AVERAGE(INDEX(Ventas!$C$2:$I$5000,MATCH($A38,Ventas!$A$2:$A$5000,0),0))),"SÍ — stock 0 y Sep cayó (prom Feb-Ago "&TEXT(AVERAGE(INDEX(Ventas!$C$2:$I$5000,MATCH($A38,Ventas!$A$2:$A$5000,0),0)),"#,##0")&")",""))} -> SÍ — stock 0 y Sep cayó (prom Feb-Ago 529) | AF38: {=IF(X38="","",IF(AE38<>"",MAX(X38,AVERAGE(INDEX(Ventas!$C$2:$I$5000,MATCH($A38,Ventas!$A$2:$A$5000,0),0))),X38))} -> 529.14286 | AG38: =IF(AF38="","",ROUND(AF38*4,0)-P38) -> -383 | AH38: =IF(A38="","",IF(AF38="","SIN HISTORIAL",IF(AF38=0,"SIN VENTAS",IF(AG38>0.1*ROUND(AF38*4,0),"COMPRAR",IF(AND(-AG38>0.1*ROUND(AF38*4,0),SUM(I38:M38)+IF($AD$3="SI",SUM(N38),0)>0),"PEDIR MENOS",IF(P38/AF38>8,"SOBRESTOCK","OK")))))) -> PEDIR MENOS
A39: 5120923-9999 | B39: PU BONDEADO | C39: NAPA eva pique 2.4mm | D39: NEGRO | E39: 1535 | O39: =IF(A39="","SIN SKU — cargar código para calcular",IF(X39="","SIN HISTORIAL DE VENTAS — artículo nuevo o código distinto en Ventas",IF(X39=0,IF(P39>0,"SIN VENTAS Jun-Sep — no comprar ("&TEXT(P39,"#,##0")&" m disponibles)","SIN VENTAS Jun-Sep — no comprar"),IF(AA39>0.1*Y39,"COMPRAR — faltan "&TEXT(AA39,"#,##0")&" m para 4 meses"&IF(P39-E39>0," (ya contando pedidos)",""),IF(AND(-AA39>0.1*Y39,SUM(I39:M39)+IF($AD$3="SI",SUM(N39),0)>0),"PEDIR MENOS — sobran "&TEXT(-AA39,"#,##0")&" m; revisar pedidos sin facturar ("&TEXT(SUM(I39:M39)+IF($AD$3="SI",SUM(N39),0),"#,##0")&" m)",IF(Z39>8,"SOBRESTOCK — "&TEXT(Z39,"0.0")&" meses de cobertura","OK — cubierto ("&TEXT(Z39,"0.0")&" meses)")))))) -> OK — cubierto (5.0 meses) | P39: =E39+N(F39)+SUM(G39:M39)+IF($AD$3="SI",SUM(N39),0) -> 1535 | Q39: En los materiales bondeados quizá se deba tomar en cuenta el cierre de fábrica. | X39: =IFERROR(VLOOKUP($A39,Ventas!$A$2:$L$5000,12,FALSE()),"") -> 307 | Y39: =IF(X39="","",ROUND(X39*4,0)) -> 1228 | Z39: =IF(OR(X39="",X39=0),"",ROUND(P39/X39,1)) -> 5 | AA39: =IF(Y39="","",Y39-P39) -> -307 | AB39: =IF(A39="","",IF(COUNTIF($A$8:$A$670,A39)>1,"DUPLICADO","")) | AC39: {=IF(AH39<>"COMPRAR","",IF(MAX(INDEX(Ventas!$G$2:$G$5000,MATCH($A39,Ventas!$A$2:$A$5000,0)),INDEX(Ventas!$H$2:$H$5000,MATCH($A39,Ventas!$A$2:$A$5000,0)),INDEX(Ventas!$I$2:$I$5000,MATCH($A39,Ventas!$A$2:$A$5000,0)),INDEX(Ventas!$J$2:$J$5000,MATCH($A39,Ventas!$A$2:$A$5000,0)))>0.5*AF39*4,"1 mes = "&TEXT(MAX(INDEX(Ventas!$G$2:$G$5000,MATCH($A39,Ventas!$A$2:$A$5000,0)),INDEX(Ventas!$H$2:$H$5000,MATCH($A39,Ventas!$A$2:$A$5000,0)),INDEX(Ventas!$I$2:$I$5000,MATCH($A39,Ventas!$A$2:$A$5000,0)),INDEX(Ventas!$J$2:$J$5000,MATCH($A39,Ventas!$A$2:$A$5000,0)))/(AF39*4),"0%")&" de 4 meses",""))} | AD39: =IF(OR(X39="",X39=0),"",IF(E39+N(F39)<X39*$AD$5,"SÍ — "&TEXT(E39+N(F39),"#,##0")&" m vs "&TEXT(X39*$AD$5,"#,##0")&" m","")) | AE39: {=IF(X39="","",IF(AND(E39=0,AVERAGE(INDEX(Ventas!$C$2:$I$5000,MATCH($A39,Ventas!$A$2:$A$5000,0),0))>0,INDEX(Ventas!$J$2:$J$5000,MATCH($A39,Ventas!$A$2:$A$5000,0))<0.5*AVERAGE(INDEX(Ventas!$C$2:$I$5000,MATCH($A39,Ventas!$A$2:$A$5000,0),0))),"SÍ — stock 0 y Sep cayó (prom Feb-Ago "&TEXT(AVERAGE(INDEX(Ventas!$C$2:$I$5000,MATCH($A39,Ventas!$A$2:$A$5000,0),0)),"#,##0")&")",""))} | AF39: {=IF(X39="","",IF(AE39<>"",MAX(X39,AVERAGE(INDEX(Ventas!$C$2:$I$5000,MATCH($A39,Ventas!$A$2:$A$5000,0),0))),X39))} -> 307 | AG39: =IF(AF39="","",ROUND(AF39*4,0)-P39) -> -307 | AH39: =IF(A39="","",IF(AF39="","SIN HISTORIAL",IF(AF39=0,"SIN VENTAS",IF(AG39>0.1*ROUND(AF39*4,0),"COMPRAR",IF(AND(-AG39>0.1*ROUND(AF39*4,0),SUM(I39:M39)+IF($AD$3="SI",SUM(N39),0)>0),"PEDIR MENOS",IF(P39/AF39>8,"SOBRESTOCK","OK")))))) -> OK
A40: 585923-9999 | B40: PU BONDEADO | C40: BOGOTA ev microf. 2.4mm | D40: NEGRO | E40: 2724 | O40: =IF(A40="","SIN SKU — cargar código para calcular",IF(X40="","SIN HISTORIAL DE VENTAS — artículo nuevo o código distinto en Ventas",IF(X40=0,IF(P40>0,"SIN VENTAS Jun-Sep — no comprar ("&TEXT(P40,"#,##0")&" m disponibles)","SIN VENTAS Jun-Sep — no comprar"),IF(AA40>0.1*Y40,"COMPRAR — faltan "&TEXT(AA40,"#,##0")&" m para 4 meses"&IF(P40-E40>0," (ya contando pedidos)",""),IF(AND(-AA40>0.1*Y40,SUM(I40:M40)+IF($AD$3="SI",SUM(N40),0)>0),"PEDIR MENOS — sobran "&TEXT(-AA40,"#,##0")&" m; revisar pedidos sin facturar ("&TEXT(SUM(I40:M40)+IF($AD$3="SI",SUM(N40),0),"#,##0")&" m)",IF(Z40>8,"SOBRESTOCK — "&TEXT(Z40,"0.0")&" meses de cobertura","OK — cubierto ("&TEXT(Z40,"0.0")&" meses)")))))) -> SOBRESTOCK — 33.2 meses de cobertura | P40: =E40+N(F40)+SUM(G40:M40)+IF($AD$3="SI",SUM(N40),0) -> 2724 | Q40: En los materiales bondeados quizá se deba tomar en cuenta el cierre de fábrica. | X40: =IFERROR(VLOOKUP($A40,Ventas!$A$2:$L$5000,12,FALSE()),"") -> 82 | Y40: =IF(X40="","",ROUND(X40*4,0)) -> 328 | Z40: =IF(OR(X40="",X40=0),"",ROUND(P40/X40,1)) -> 33.2 | AA40: =IF(Y40="","",Y40-P40) -> -2396 | AB40: =IF(A40="","",IF(COUNTIF($A$8:$A$670,A40)>1,"DUPLICADO","")) | AC40: {=IF(AH40<>"COMPRAR","",IF(MAX(INDEX(Ventas!$G$2:$G$5000,MATCH($A40,Ventas!$A$2:$A$5000,0)),INDEX(Ventas!$H$2:$H$5000,MATCH($A40,Ventas!$A$2:$A$5000,0)),INDEX(Ventas!$I$2:$I$5000,MATCH($A40,Ventas!$A$2:$A$5000,0)),INDEX(Ventas!$J$2:$J$5000,MATCH($A40,Ventas!$A$2:$A$5000,0)))>0.5*AF40*4,"1 mes = "&TEXT(MAX(INDEX(Ventas!$G$2:$G$5000,MATCH($A40,Ventas!$A$2:$A$5000,0)),INDEX(Ventas!$H$2:$H$5000,MATCH($A40,Ventas!$A$2:$A$5000,0)),INDEX(Ventas!$I$2:$I$5000,MATCH($A40,Ventas!$A$2:$A$5000,0)),INDEX(Ventas!$J$2:$J$5000,MATCH($A40,Ventas!$A$2:$A$5000,0)))/(AF40*4),"0%")&" de 4 meses",""))} | AD40: =IF(OR(X40="",X40=0),"",IF(E40+N(F40)<X40*$AD$5,"SÍ — "&TEXT(E40+N(F40),"#,##0")&" m vs "&TEXT(X40*$AD$5,"#,##0")&" m","")) | AE40: {=IF(X40="","",IF(AND(E40=0,AVERAGE(INDEX(Ventas!$C$2:$I$5000,MATCH($A40,Ventas!$A$2:$A$5000,0),0))>0,INDEX(Ventas!$J$2:$J$5000,MATCH($A40,Ventas!$A$2:$A$5000,0))<0.5*AVERAGE(INDEX(Ventas!$C$2:$I$5000,MATCH($A40,Ventas!$A$2:$A$5000,0),0))),"SÍ — stock 0 y Sep cayó (prom Feb-Ago "&TEXT(AVERAGE(INDEX(Ventas!$C$2:$I$5000,MATCH($A40,Ventas!$A$2:$A$5000,0),0)),"#,##0")&")",""))} | AF40: {=IF(X40="","",IF(AE40<>"",MAX(X40,AVERAGE(INDEX(Ventas!$C$2:$I$5000,MATCH($A40,Ventas!$A$2:$A$5000,0),0))),X40))} -> 82 | AG40: =IF(AF40="","",ROUND(AF40*4,0)-P40) -> -2396 | AH40: =IF(A40="","",IF(AF40="","SIN HISTORIAL",IF(AF40=0,"SIN VENTAS",IF(AG40>0.1*ROUND(AF40*4,0),"COMPRAR",IF(AND(-AG40>0.1*ROUND(AF40*4,0),SUM(I40:M40)+IF($AD$3="SI",SUM(N40),0)>0),"PEDIR MENOS",IF(P40/AF40>8,"SOBRESTOCK","OK")))))) -> SOBRESTOCK
A41: 5140923-9999 | B41: PU BONDEADO | C41: CALI eva microf. 2.4mm | D41: NEGRO | E41: 1204 | O41: =IF(A41="","SIN SKU — cargar código para calcular",IF(X41="","SIN HISTORIAL DE VENTAS — artículo nuevo o código distinto en Ventas",IF(X41=0,IF(P41>0,"SIN VENTAS Jun-Sep — no comprar ("&TEXT(P41,"#,##0")&" m disponibles)","SIN VENTAS Jun-Sep — no comprar"),IF(AA41>0.1*Y41,"COMPRAR — faltan "&TEXT(AA41,"#,##0")&" m para 4 meses"&IF(P41-E41>0," (ya contando pedidos)",""),IF(AND(-AA41>0.1*Y41,SUM(I41:M41)+IF($AD$3="SI",SUM(N41),0)>0),"PEDIR MENOS — sobran "&TEXT(-AA41,"#,##0")&" m; revisar pedidos sin facturar ("&TEXT(SUM(I41:M41)+IF($AD$3="SI",SUM(N41),0),"#,##0")&" m)",IF(Z41>8,"SOBRESTOCK — "&TEXT(Z41,"0.0")&" meses de cobertura","OK — cubierto ("&TEXT(Z41,"0.0")&" meses)")))))) -> OK — cubierto (4.2 meses) | P41: =E41+N(F41)+SUM(G41:M41)+IF($AD$3="SI",SUM(N41),0) -> 1204 | Q41: En los materiales bondeados quizá se deba tomar en cuenta el cierre de fábrica. | X41: =IFERROR(VLOOKUP($A41,Ventas!$A$2:$L$5000,12,FALSE()),"") -> 285 | Y41: =IF(X41="","",ROUND(X41*4,0)) -> 1140 | Z41: =IF(OR(X41="",X41=0),"",ROUND(P41/X41,1)) -> 4.2 | AA41: =IF(Y41="","",Y41-P41) -> -64 | AB41: =IF(A41="","",IF(COUNTIF($A$8:$A$670,A41)>1,"DUPLICADO","")) | AC41: {=IF(AH41<>"COMPRAR","",IF(MAX(INDEX(Ventas!$G$2:$G$5000,MATCH($A41,Ventas!$A$2:$A$5000,0)),INDEX(Ventas!$H$2:$H$5000,MATCH($A41,Ventas!$A$2:$A$5000,0)),INDEX(Ventas!$I$2:$I$5000,MATCH($A41,Ventas!$A$2:$A$5000,0)),INDEX(Ventas!$J$2:$J$5000,MATCH($A41,Ventas!$A$2:$A$5000,0)))>0.5*AF41*4,"1 mes = "&TEXT(MAX(INDEX(Ventas!$G$2:$G$5000,MATCH($A41,Ventas!$A$2:$A$5000,0)),INDEX(Ventas!$H$2:$H$5000,MATCH($A41,Ventas!$A$2:$A$5000,0)),INDEX(Ventas!$I$2:$I$5000,MATCH($A41,Ventas!$A$2:$A$5000,0)),INDEX(Ventas!$J$2:$J$5000,MATCH($A41,Ventas!$A$2:$A$5000,0)))/(AF41*4),"0%")&" de 4 meses",""))} | AD41: =IF(OR(X41="",X41=0),"",IF(E41+N(F41)<X41*$AD$5,"SÍ — "&TEXT(E41+N(F41),"#,##0")&" m vs "&TEXT(X41*$AD$5,"#,##0")&" m","")) | AE41: {=IF(X41="","",IF(AND(E41=0,AVERAGE(INDEX(Ventas!$C$2:$I$5000,MATCH($A41,Ventas!$A$2:$A$5000,0),0))>0,INDEX(Ventas!$J$2:$J$5000,MATCH($A41,Ventas!$A$2:$A$5000,0))<0.5*AVERAGE(INDEX(Ventas!$C$2:$I$5000,MATCH($A41,Ventas!$A$2:$A$5000,0),0))),"SÍ — stock 0 y Sep cayó (prom Feb-Ago "&TEXT(AVERAGE(INDEX(Ventas!$C$2:$I$5000,MATCH($A41,Ventas!$A$2:$A$5000,0),0)),"#,##0")&")",""))} | AF41: {=IF(X41="","",IF(AE41<>"",MAX(X41,AVERAGE(INDEX(Ventas!$C$2:$I$5000,MATCH($A41,Ventas!$A$2:$A$5000,0),0))),X41))} -> 285 | AG41: =IF(AF41="","",ROUND(AF41*4,0)-P41) -> -64 | AH41: =IF(A41="","",IF(AF41="","SIN HISTORIAL",IF(AF41=0,"SIN VENTAS",IF(AG41>0.1*ROUND(AF41*4,0),"COMPRAR",IF(AND(-AG41>0.1*ROUND(AF41*4,0),SUM(I41:M41)+IF($AD$3="SI",SUM(N41),0)>0),"PEDIR MENOS",IF(P41/AF41>8,"SOBRESTOCK","OK")))))) -> OK
A42: 5140923-0010 | B42: PU BONDEADO | C42: CALI eva microf. 2.4mm | D42: CHOCOLATE | E42: 30 | O42: =IF(A42="","SIN SKU — cargar código para calcular",IF(X42="","SIN HISTORIAL DE VENTAS — artículo nuevo o código distinto en Ventas",IF(X42=0,IF(P42>0,"SIN VENTAS Jun-Sep — no comprar ("&TEXT(P42,"#,##0")&" m disponibles)","SIN VENTAS Jun-Sep — no comprar"),IF(AA42>0.1*Y42,"COMPRAR — faltan "&TEXT(AA42,"#,##0")&" m para 4 meses"&IF(P42-E42>0," (ya contando pedidos)",""),IF(AND(-AA42>0.1*Y42,SUM(I42:M42)+IF($AD$3="SI",SUM(N42),0)>0),"PEDIR MENOS — sobran "&TEXT(-AA42,"#,##0")&" m; revisar pedidos sin facturar ("&TEXT(SUM(I42:M42)+IF($AD$3="SI",SUM(N42),0),"#,##0")&" m)",IF(Z42>8,"SOBRESTOCK — "&TEXT(Z42,"0.0")&" meses de cobertura","OK — cubierto ("&TEXT(Z42,"0.0")&" meses)")))))) -> COMPRAR — faltan 1,525 m para 4 meses | P42: =E42+N(F42)+SUM(G42:M42)+IF($AD$3="SI",SUM(N42),0) -> 30 | Q42: En los materiales bondeados quizá se deba tomar en cuenta el cierre de fábrica. | X42: =IFERROR(VLOOKUP($A42,Ventas!$A$2:$L$5000,12,FALSE()),"") -> 388.75 | Y42: =IF(X42="","",ROUND(X42*4,0)) -> 1555 | Z42: =IF(OR(X42="",X42=0),"",ROUND(P42/X42,1)) -> 0.1 | AA42: =IF(Y42="","",Y42-P42) -> 1525 | AB42: =IF(A42="","",IF(COUNTIF($A$8:$A$670,A42)>1,"DUPLICADO","")) | AC42: {=IF(AH42<>"COMPRAR","",IF(MAX(INDEX(Ventas!$G$2:$G$5000,MATCH($A42,Ventas!$A$2:$A$5000,0)),INDEX(Ventas!$H$2:$H$5000,MATCH($A42,Ventas!$A$2:$A$5000,0)),INDEX(Ventas!$I$2:$I$5000,MATCH($A42,Ventas!$A$2:$A$5000,0)),INDEX(Ventas!$J$2:$J$5000,MATCH($A42,Ventas!$A$2:$A$5000,0)))>0.5*AF42*4,"1 mes = "&TEXT(MAX(INDEX(Ventas!$G$2:$G$5000,MATCH($A42,Ventas!$A$2:$A$5000,0)),INDEX(Ventas!$H$2:$H$5000,MATCH($A42,Ventas!$A$2:$A$5000,0)),INDEX(Ventas!$I$2:$I$5000,MATCH($A42,Ventas!$A$2:$A$5000,0)),INDEX(Ventas!$J$2:$J$5000,MATCH($A42,Ventas!$A$2:$A$5000,0)))/(AF42*4),"0%")&" de 4 meses",""))} | AD42: =IF(OR(X42="",X42=0),"",IF(E42+N(F42)<X42*$AD$5,"SÍ — "&TEXT(E42+N(F42),"#,##0")&" m vs "&TEXT(X42*$AD$5,"#,##0")&" m","")) -> SÍ — 30 m vs 206 m | AE42: {=IF(X42="","",IF(AND(E42=0,AVERAGE(INDEX(Ventas!$C$2:$I$5000,MATCH($A42,Ventas!$A$2:$A$5000,0),0))>0,INDEX(Ventas!$J$2:$J$5000,MATCH($A42,Ventas!$A$2:$A$5000,0))<0.5*AVERAGE(INDEX(Ventas!$C$2:$I$5000,MATCH($A42,Ventas!$A$2:$A$5000,0),0))),"SÍ — stock 0 y Sep cayó (prom Feb-Ago "&TEXT(AVERAGE(INDEX(Ventas!$C$2:$I$5000,MATCH($A42,Ventas!$A$2:$A$5000,0),0)),"#,##0")&")",""))} | AF42: {=IF(X42="","",IF(AE42<>"",MAX(X42,AVERAGE(INDEX(Ventas!$C$2:$I$5000,MATCH($A42,Ventas!$A$2:$A$5000,0),0))),X42))} -> 388.75 | AG42: =IF(AF42="","",ROUND(AF42*4,0)-P42) -> 1525 | AH42: =IF(A42="","",IF(AF42="","SIN HISTORIAL",IF(AF42=0,"SIN VENTAS",IF(AG42>0.1*ROUND(AF42*4,0),"COMPRAR",IF(AND(-AG42>0.1*ROUND(AF42*4,0),SUM(I42:M42)+IF($AD$3="SI",SUM(N42),0)>0),"PEDIR MENOS",IF(P42/AF42>8,"SOBRESTOCK","OK")))))) -> COMPRAR
B43: PU BONDEADO | C43: Cali c eva y set | D43: NEGRO | L43: 3000 | O43: =IF(A43="","SIN SKU — cargar código para calcular",IF(X43="","SIN HISTORIAL DE VENTAS — artículo nuevo o código distinto en Ventas",IF(X43=0,IF(P43>0,"SIN VENTAS Jun-Sep — no comprar ("&TEXT(P43,"#,##0")&" m disponibles)","SIN VENTAS Jun-Sep — no comprar"),IF(AA43>0.1*Y43,"COMPRAR — faltan "&TEXT(AA43,"#,##0")&" m para 4 meses"&IF(P43-E43>0," (ya contando pedidos)",""),IF(AND(-AA43>0.1*Y43,SUM(I43:M43)+IF($AD$3="SI",SUM(N43),0)>0),"PEDIR MENOS — sobran "&TEXT(-AA43,"#,##0")&" m; revisar pedidos sin facturar ("&TEXT(SUM(I43:M43)+IF($AD$3="SI",SUM(N43),0),"#,##0")&" m)",IF(Z43>8,"SOBRESTOCK — "&TEXT(Z43,"0.0")&" meses de cobertura","OK — cubierto ("&TEXT(Z43,"0.0")&" meses)")))))) -> SIN SKU — cargar código para calcular | P43: =E43+N(F43)+SUM(G43:M43)+IF($AD$3="SI",SUM(N43),0) -> 3000 | X43: =IFERROR(VLOOKUP($A43,Ventas!$A$2:$L$5000,12,FALSE()),"") | Y43: =IF(X43="","",ROUND(X43*4,0)) | Z43: =IF(OR(X43="",X43=0),"",ROUND(P43/X43,1)) | AA43: =IF(Y43="","",Y43-P43) | AB43: =IF(A43="","",IF(COUNTIF($A$8:$A$670,A43)>1,"DUPLICADO","")) | AC43: {=IF(AH43<>"COMPRAR","",IF(MAX(INDEX(Ventas!$G$2:$G$5000,MATCH($A43,Ventas!$A$2:$A$5000,0)),INDEX(Ventas!$H$2:$H$5000,MATCH($A43,Ventas!$A$2:$A$5000,0)),INDEX(Ventas!$I$2:$I$5000,MATCH($A43,Ventas!$A$2:$A$5000,0)),INDEX(Ventas!$J$2:$J$5000,MATCH($A43,Ventas!$A$2:$A$5000,0)))>0.5*AF43*4,"1 mes = "&TEXT(MAX(INDEX(Ventas!$G$2:$G$5000,MATCH($A43,Ventas!$A$2:$A$5000,0)),INDEX(Ventas!$H$2:$H$5000,MATCH($A43,Ventas!$A$2:$A$5000,0)),INDEX(Ventas!$I$2:$I$5000,MATCH($A43,Ventas!$A$2:$A$5000,0)),INDEX(Ventas!$J$2:$J$5000,MATCH($A43,Ventas!$A$2:$A$5000,0)))/(AF43*4),"0%")&" de 4 meses",""))} | AD43: =IF(OR(X43="",X43=0),"",IF(E43+N(F43)<X43*$AD$5,"SÍ — "&TEXT(E43+N(F43),"#,##0")&" m vs "&TEXT(X43*$AD$5,"#,##0")&" m","")) | AE43: {=IF(X43="","",IF(AND(E43=0,AVERAGE(INDEX(Ventas!$C$2:$I$5000,MATCH($A43,Ventas!$A$2:$A$5000,0),0))>0,INDEX(Ventas!$J$2:$J$5000,MATCH($A43,Ventas!$A$2:$A$5000,0))<0.5*AVERAGE(INDEX(Ventas!$C$2:$I$5000,MATCH($A43,Ventas!$A$2:$A$5000,0),0))),"SÍ — stock 0 y Sep cayó (prom Feb-Ago "&TEXT(AVERAGE(INDEX(Ventas!$C$2:$I$5000,MATCH($A43,Ventas!$A$2:$A$5000,0),0)),"#,##0")&")",""))} | AF43: {=IF(X43="","",IF(AE43<>"",MAX(X43,AVERAGE(INDEX(Ventas!$C$2:$I$5000,MATCH($A43,Ventas!$A$2:$A$5000,0),0))),X43))} | AG43: =IF(AF43="","",ROUND(AF43*4,0)-P43) | AH43: =IF(A43="","",IF(AF43="","SIN HISTORIAL",IF(AF43=0,"SIN VENTAS",IF(AG43>0.1*ROUND(AF43*4,0),"COMPRAR",IF(AND(-AG43>0.1*ROUND(AF43*4,0),SUM(I43:M43)+IF($AD$3="SI",SUM(N43),0)>0),"PEDIR MENOS",IF(P43/AF43>8,"SOBRESTOCK","OK"))))))
B44: PU BONDEADO | C44: CALI EVA y set | D44: CHOCOLATE | L44: 1500 | O44: =IF(A44="","SIN SKU — cargar código para calcular",IF(X44="","SIN HISTORIAL DE VENTAS — artículo nuevo o código distinto en Ventas",IF(X44=0,IF(P44>0,"SIN VENTAS Jun-Sep — no comprar ("&TEXT(P44,"#,##0")&" m disponibles)","SIN VENTAS Jun-Sep — no comprar"),IF(AA44>0.1*Y44,"COMPRAR — faltan "&TEXT(AA44,"#,##0")&" m para 4 meses"&IF(P44-E44>0," (ya contando pedidos)",""),IF(AND(-AA44>0.1*Y44,SUM(I44:M44)+IF($AD$3="SI",SUM(N44),0)>0),"PEDIR MENOS — sobran "&TEXT(-AA44,"#,##0")&" m; revisar pedidos sin facturar ("&TEXT(SUM(I44:M44)+IF($AD$3="SI",SUM(N44),0),"#,##0")&" m)",IF(Z44>8,"SOBRESTOCK — "&TEXT(Z44,"0.0")&" meses de cobertura","OK — cubierto ("&TEXT(Z44,"0.0")&" meses)")))))) -> SIN SKU — cargar código para calcular | P44: =E44+N(F44)+SUM(G44:M44)+IF($AD$3="SI",SUM(N44),0) -> 1500 | X44: =IFERROR(VLOOKUP($A44,Ventas!$A$2:$L$5000,12,FALSE()),"") | Y44: =IF(X44="","",ROUND(X44*4,0)) | Z44: =IF(OR(X44="",X44=0),"",ROUND(P44/X44,1)) | AA44: =IF(Y44="","",Y44-P44) | AB44: =IF(A44="","",IF(COUNTIF($A$8:$A$670,A44)>1,"DUPLICADO","")) | AC44: {=IF(AH44<>"COMPRAR","",IF(MAX(INDEX(Ventas!$G$2:$G$5000,MATCH($A44,Ventas!$A$2:$A$5000,0)),INDEX(Ventas!$H$2:$H$5000,MATCH($A44,Ventas!$A$2:$A$5000,0)),INDEX(Ventas!$I$2:$I$5000,MATCH($A44,Ventas!$A$2:$A$5000,0)),INDEX(Ventas!$J$2:$J$5000,MATCH($A44,Ventas!$A$2:$A$5000,0)))>0.5*AF44*4,"1 mes = "&TEXT(MAX(INDEX(Ventas!$G$2:$G$5000,MATCH($A44,Ventas!$A$2:$A$5000,0)),INDEX(Ventas!$H$2:$H$5000,MATCH($A44,Ventas!$A$2:$A$5000,0)),INDEX(Ventas!$I$2:$I$5000,MATCH($A44,Ventas!$A$2:$A$5000,0)),INDEX(Ventas!$J$2:$J$5000,MATCH($A44,Ventas!$A$2:$A$5000,0)))/(AF44*4),"0%")&" de 4 meses",""))} | AD44: =IF(OR(X44="",X44=0),"",IF(E44+N(F44)<X44*$AD$5,"SÍ — "&TEXT(E44+N(F44),"#,##0")&" m vs "&TEXT(X44*$AD$5,"#,##0")&" m","")) | AE44: {=IF(X44="","",IF(AND(E44=0,AVERAGE(INDEX(Ventas!$C$2:$I$5000,MATCH($A44,Ventas!$A$2:$A$5000,0),0))>0,INDEX(Ventas!$J$2:$J$5000,MATCH($A44,Ventas!$A$2:$A$5000,0))<0.5*AVERAGE(INDEX(Ventas!$C$2:$I$5000,MATCH($A44,Ventas!$A$2:$A$5000,0),0))),"SÍ — stock 0 y Sep cayó (prom Feb-Ago "&TEXT(AVERAGE(INDEX(Ventas!$C$2:$I$5000,MATCH($A44,Ventas!$A$2:$A$5000,0),0)),"#,##0")&")",""))} | AF44: {=IF(X44="","",IF(AE44<>"",MAX(X44,AVERAGE(INDEX(Ventas!$C$2:$I$5000,MATCH($A44,Ventas!$A$2:$A$5000,0),0))),X44))} | AG44: =IF(AF44="","",ROUND(AF44*4,0)-P44) | AH44: =IF(A44="","",IF(AF44="","SIN HISTORIAL",IF(AF44=0,"SIN VENTAS",IF(AG44>0.1*ROUND(AF44*4,0),"COMPRAR",IF(AND(-AG44>0.1*ROUND(AF44*4,0),SUM(I44:M44)+IF($AD$3="SI",SUM(N44),0)>0),"PEDIR MENOS",IF(P44/AF44>8,"SOBRESTOCK","OK"))))))
A45: 394923-9999 | B45: CAPELLADA | C45: TOKIO | D45: NEGRO | E45: 8860 | L45: 4000 | O45: =IF(A45="","SIN SKU — cargar código para calcular",IF(X45="","SIN HISTORIAL DE VENTAS — artículo nuevo o código distinto en Ventas",IF(X45=0,IF(P45>0,"SIN VENTAS Jun-Sep — no comprar ("&TEXT(P45,"#,##0")&" m disponibles)","SIN VENTAS Jun-Sep — no comprar"),IF(AA45>0.1*Y45,"COMPRAR — faltan "&TEXT(AA45,"#,##0")&" m para 4 meses"&IF(P45-E45>0," (ya contando pedidos)",""),IF(AND(-AA45>0.1*Y45,SUM(I45:M45)+IF($AD$3="SI",SUM(N45),0)>0),"PEDIR MENOS — sobran "&TEXT(-AA45,"#,##0")&" m; revisar pedidos sin facturar ("&TEXT(SUM(I45:M45)+IF($AD$3="SI",SUM(N45),0),"#,##0")&" m)",IF(Z45>8,"SOBRESTOCK — "&TEXT(Z45,"0.0")&" meses de cobertura","OK — cubierto ("&TEXT(Z45,"0.0")&" meses)")))))) -> PEDIR MENOS — sobran 3,637 m; revisar pedidos sin facturar (4,000 m) | P45: =E45+N(F45)+SUM(G45:M45)+IF($AD$3="SI",SUM(N45),0) -> 12860 | Q45: 5000 | X45: =IFERROR(VLOOKUP($A45,Ventas!$A$2:$L$5000,12,FALSE()),"") -> 2305.75 | Y45: =IF(X45="","",ROUND(X45*4,0)) -> 9223 | Z45: =IF(OR(X45="",X45=0),"",ROUND(P45/X45,1)) -> 5.6 | AA45: =IF(Y45="","",Y45-P45) -> -3637 | AB45: =IF(A45="","",IF(COUNTIF($A$8:$A$670,A45)>1,"DUPLICADO","")) | AC45: {=IF(AH45<>"COMPRAR","",IF(MAX(INDEX(Ventas!$G$2:$G$5000,MATCH($A45,Ventas!$A$2:$A$5000,0)),INDEX(Ventas!$H$2:$H$5000,MATCH($A45,Ventas!$A$2:$A$5000,0)),INDEX(Ventas!$I$2:$I$5000,MATCH($A45,Ventas!$A$2:$A$5000,0)),INDEX(Ventas!$J$2:$J$5000,MATCH($A45,Ventas!$A$2:$A$5000,0)))>0.5*AF45*4,"1 mes = "&TEXT(MAX(INDEX(Ventas!$G$2:$G$5000,MATCH($A45,Ventas!$A$2:$A$5000,0)),INDEX(Ventas!$H$2:$H$5000,MATCH($A45,Ventas!$A$2:$A$5000,0)),INDEX(Ventas!$I$2:$I$5000,MATCH($A45,Ventas!$A$2:$A$5000,0)),INDEX(Ventas!$J$2:$J$5000,MATCH($A45,Ventas!$A$2:$A$5000,0)))/(AF45*4),"0%")&" de 4 meses",""))} | AD45: =IF(OR(X45="",X45=0),"",IF(E45+N(F45)<X45*$AD$5,"SÍ — "&TEXT(E45+N(F45),"#,##0")&" m vs "&TEXT(X45*$AD$5,"#,##0")&" m","")) | AE45: {=IF(X45="","",IF(AND(E45=0,AVERAGE(INDEX(Ventas!$C$2:$I$5000,MATCH($A45,Ventas!$A$2:$A$5000,0),0))>0,INDEX(Ventas!$J$2:$J$5000,MATCH($A45,Ventas!$A$2:$A$5000,0))<0.5*AVERAGE(INDEX(Ventas!$C$2:$I$5000,MATCH($A45,Ventas!$A$2:$A$5000,0),0))),"SÍ — stock 0 y Sep cayó (prom Feb-Ago "&TEXT(AVERAGE(INDEX(Ventas!$C$2:$I$5000,MATCH($A45,Ventas!$A$2:$A$5000,0),0)),"#,##0")&")",""))} | AF45: {=IF(X45="","",IF(AE45<>"",MAX(X45,AVERAGE(INDEX(Ventas!$C$2:$I$5000,MATCH($A45,Ventas!$A$2:$A$5000,0),0))),X45))} -> 2305.75 | AG45: =IF(AF45="","",ROUND(AF45*4,0)-P45) -> -3637 | AH45: =IF(A45="","",IF(AF45="","SIN HISTORIAL",IF(AF45=0,"SIN VENTAS",IF(AG45>0.1*ROUND(AF45*4,0),"COMPRAR",IF(AND(-AG45>0.1*ROUND(AF45*4,0),SUM(I45:M45)+IF($AD$3="SI",SUM(N45),0)>0),"PEDIR MENOS",IF(P45/AF45>8,"SOBRESTOCK","OK")))))) -> PEDIR MENOS
A46: 394923-0159 | B46: CAPELLADA | C46: TOKIO | D46: NUDE | E46: 2518 | O46: =IF(A46="","SIN SKU — cargar código para calcular",IF(X46="","SIN HISTORIAL DE VENTAS — artículo nuevo o código distinto en Ventas",IF(X46=0,IF(P46>0,"SIN VENTAS Jun-Sep — no comprar ("&TEXT(P46,"#,##0")&" m disponibles)","SIN VENTAS Jun-Sep — no comprar"),IF(AA46>0.1*Y46,"COMPRAR — faltan "&TEXT(AA46,"#,##0")&" m para 4 meses"&IF(P46-E46>0," (ya contando pedidos)",""),IF(AND(-AA46>0.1*Y46,SUM(I46:M46)+IF($AD$3="SI",SUM(N46),0)>0),"PEDIR MENOS — sobran "&TEXT(-AA46,"#,##0")&" m; revisar pedidos sin facturar ("&TEXT(SUM(I46:M46)+IF($AD$3="SI",SUM(N46),0),"#,##0")&" m)",IF(Z46>8,"SOBRESTOCK — "&TEXT(Z46,"0.0")&" meses de cobertura","OK — cubierto ("&TEXT(Z46,"0.0")&" meses)")))))) -> SOBRESTOCK — 229.4 meses de cobertura | P46: =E46+N(F46)+SUM(G46:M46)+IF($AD$3="SI",SUM(N46),0) -> 2518 | X46: =IFERROR(VLOOKUP($A46,Ventas!$A$2:$L$5000,12,FALSE()),"") -> 10.975 | Y46: =IF(X46="","",ROUND(X46*4,0)) -> 44 | Z46: =IF(OR(X46="",X46=0),"",ROUND(P46/X46,1)) -> 229.4 | AA46: =IF(Y46="","",Y46-P46) -> -2474 | AB46: =IF(A46="","",IF(COUNTIF($A$8:$A$670,A46)>1,"DUPLICADO","")) | AC46: {=IF(AH46<>"COMPRAR","",IF(MAX(INDEX(Ventas!$G$2:$G$5000,MATCH($A46,Ventas!$A$2:$A$5000,0)),INDEX(Ventas!$H$2:$H$5000,MATCH($A46,Ventas!$A$2:$A$5000,0)),INDEX(Ventas!$I$2:$I$5000,MATCH($A46,Ventas!$A$2:$A$5000,0)),INDEX(Ventas!$J$2:$J$5000,MATCH($A46,Ventas!$A$2:$A$5000,0)))>0.5*AF46*4,"1 mes = "&TEXT(MAX(INDEX(Ventas!$G$2:$G$5000,MATCH($A46,Ventas!$A$2:$A$5000,0)),INDEX(Ventas!$H$2:$H$5000,MATCH($A46,Ventas!$A$2:$A$5000,0)),INDEX(Ventas!$I$2:$I$5000,MATCH($A46,Ventas!$A$2:$A$5000,0)),INDEX(Ventas!$J$2:$J$5000,MATCH($A46,Ventas!$A$2:$A$5000,0)))/(AF46*4),"0%")&" de 4 meses",""))} | AD46: =IF(OR(X46="",X46=0),"",IF(E46+N(F46)<X46*$AD$5,"SÍ — "&TEXT(E46+N(F46),"#,##0")&" m vs "&TEXT(X46*$AD$5,"#,##0")&" m","")) | AE46: {=IF(X46="","",IF(AND(E46=0,AVERAGE(INDEX(Ventas!$C$2:$I$5000,MATCH($A46,Ventas!$A$2:$A$5000,0),0))>0,INDEX(Ventas!$J$2:$J$5000,MATCH($A46,Ventas!$A$2:$A$5000,0))<0.5*AVERAGE(INDEX(Ventas!$C$2:$I$5000,MATCH($A46,Ventas!$A$2:$A$5000,0),0))),"SÍ — stock 0 y Sep cayó (prom Feb-Ago "&TEXT(AVERAGE(INDEX(Ventas!$C$2:$I$5000,MATCH($A46,Ventas!$A$2:$A$5000,0),0)),"#,##0")&")",""))} | AF46: {=IF(X46="","",IF(AE46<>"",MAX(X46,AVERAGE(INDEX(Ventas!$C$2:$I$5000,MATCH($A46,Ventas!$A$2:$A$5000,0),0))),X46))} -> 10.975 | AG46: =IF(AF46="","",ROUND(AF46*4,0)-P46) -> -2474 | AH46: =IF(A46="","",IF(AF46="","SIN HISTORIAL",IF(AF46=0,"SIN VENTAS",IF(AG46>0.1*ROUND(AF46*4,0),"COMPRAR",IF(AND(-AG46>0.1*ROUND(AF46*4,0),SUM(I46:M46)+IF($AD$3="SI",SUM(N46),0)>0),"PEDIR MENOS",IF(P46/AF46>8,"SOBRESTOCK","OK")))))) -> SOBRESTOCK
A47: 394923-0000 | B47: CAPELLADA | C47: TOKIO | D47: BLANCO | E47: 851 | I47: 1097 | O47: =IF(A47="","SIN SKU — cargar código para calcular",IF(X47="","SIN HISTORIAL DE VENTAS — artículo nuevo o código distinto en Ventas",IF(X47=0,IF(P47>0,"SIN VENTAS Jun-Sep — no comprar ("&TEXT(P47,"#,##0")&" m disponibles)","SIN VENTAS Jun-Sep — no comprar"),IF(AA47>0.1*Y47,"COMPRAR — faltan "&TEXT(AA47,"#,##0")&" m para 4 meses"&IF(P47-E47>0," (ya contando pedidos)",""),IF(AND(-AA47>0.1*Y47,SUM(I47:M47)+IF($AD$3="SI",SUM(N47),0)>0),"PEDIR MENOS — sobran "&TEXT(-AA47,"#,##0")&" m; revisar pedidos sin facturar ("&TEXT(SUM(I47:M47)+IF($AD$3="SI",SUM(N47),0),"#,##0")&" m)",IF(Z47>8,"SOBRESTOCK — "&TEXT(Z47,"0.0")&" meses de cobertura","OK — cubierto ("&TEXT(Z47,"0.0")&" meses)")))))) -> COMPRAR — faltan 678 m para 4 meses (ya contando pedidos) | P47: =E47+N(F47)+SUM(G47:M47)+IF($AD$3="SI",SUM(N47),0) -> 1948 | X47: =IFERROR(VLOOKUP($A47,Ventas!$A$2:$L$5000,12,FALSE()),"") -> 656.5 | Y47: =IF(X47="","",ROUND(X47*4,0)) -> 2626 | Z47: =IF(OR(X47="",X47=0),"",ROUND(P47/X47,1)) -> 3 | AA47: =IF(Y47="","",Y47-P47) -> 678 | AB47: =IF(A47="","",IF(COUNTIF($A$8:$A$670,A47)>1,"DUPLICADO","")) | AC47: {=IF(AH47<>"COMPRAR","",IF(MAX(INDEX(Ventas!$G$2:$G$5000,MATCH($A47,Ventas!$A$2:$A$5000,0)),INDEX(Ventas!$H$2:$H$5000,MATCH($A47,Ventas!$A$2:$A$5000,0)),INDEX(Ventas!$I$2:$I$5000,MATCH($A47,Ventas!$A$2:$A$5000,0)),INDEX(Ventas!$J$2:$J$5000,MATCH($A47,Ventas!$A$2:$A$5000,0)))>0.5*AF47*4,"1 mes = "&TEXT(MAX(INDEX(Ventas!$G$2:$G$5000,MATCH($A47,Ventas!$A$2:$A$5000,0)),INDEX(Ventas!$H$2:$H$5000,MATCH($A47,Ventas!$A$2:$A$5000,0)),INDEX(Ventas!$I$2:$I$5000,MATCH($A47,Ventas!$A$2:$A$5000,0)),INDEX(Ventas!$J$2:$J$5000,MATCH($A47,Ventas!$A$2:$A$5000,0)))/(AF47*4),"0%")&" de 4 meses",""))} | AD47: =IF(OR(X47="",X47=0),"",IF(E47+N(F47)<X47*$AD$5,"SÍ — "&TEXT(E47+N(F47),"#,##0")&" m vs "&TEXT(X47*$AD$5,"#,##0")&" m","")) | AE47: {=IF(X47="","",IF(AND(E47=0,AVERAGE(INDEX(Ventas!$C$2:$I$5000,MATCH($A47,Ventas!$A$2:$A$5000,0),0))>0,INDEX(Ventas!$J$2:$J$5000,MATCH($A47,Ventas!$A$2:$A$5000,0))<0.5*AVERAGE(INDEX(Ventas!$C$2:$I$5000,MATCH($A47,Ventas!$A$2:$A$5000,0),0))),"SÍ — stock 0 y Sep cayó (prom Feb-Ago "&TEXT(AVERAGE(INDEX(Ventas!$C$2:$I$5000,MATCH($A47,Ventas!$A$2:$A$5000,0),0)),"#,##0")&")",""))} | AF47: {=IF(X47="","",IF(AE47<>"",MAX(X47,AVERAGE(INDEX(Ventas!$C$2:$I$5000,MATCH($A47,Ventas!$A$2:$A$5000,0),0))),X47))} -> 656.5 | AG47: =IF(AF47="","",ROUND(AF47*4,0)-P47) -> 678 | AH47: =IF(A47="","",IF(AF47="","SIN HISTORIAL",IF(AF47=0,"SIN VENTAS",IF(AG47>0.1*ROUND(AF47*4,0),"COMPRAR",IF(AND(-AG47>0.1*ROUND(AF47*4,0),SUM(I47:M47)+IF($AD$3="SI",SUM(N47),0)>0),"PEDIR MENOS",IF(P47/AF47>8,"SOBRESTOCK","OK")))))) -> COMPRAR
A48: 394923-0156 | B48: CAPELLADA | C48: TOKIO | D48: OLIVA | E48: 762 | O48: =IF(A48="","SIN SKU — cargar código para calcular",IF(X48="","SIN HISTORIAL DE VENTAS — artículo nuevo o código distinto en Ventas",IF(X48=0,IF(P48>0,"SIN VENTAS Jun-Sep — no comprar ("&TEXT(P48,"#,##0")&" m disponibles)","SIN VENTAS Jun-Sep — no comprar"),IF(AA48>0.1*Y48,"COMPRAR — faltan "&TEXT(AA48,"#,##0")&" m para 4 meses"&IF(P48-E48>0," (ya contando pedidos)",""),IF(AND(-AA48>0.1*Y48,SUM(I48:M48)+IF($AD$3="SI",SUM(N48),0)>0),"PEDIR MENOS — sobran "&TEXT(-AA48,"#,##0")&" m; revisar pedidos sin facturar ("&TEXT(SUM(I48:M48)+IF($AD$3="SI",SUM(N48),0),"#,##0")&" m)",IF(Z48>8,"SOBRESTOCK — "&TEXT(Z48,"0.0")&" meses de cobertura","OK — cubierto ("&TEXT(Z48,"0.0")&" meses)")))))) -> SOBRESTOCK — 25.4 meses de cobertura | P48: =E48+N(F48)+SUM(G48:M48)+IF($AD$3="SI",SUM(N48),0) -> 762 | X48: =IFERROR(VLOOKUP($A48,Ventas!$A$2:$L$5000,12,FALSE()),"") -> 30 | Y48: =IF(X48="","",ROUND(X48*4,0)) -> 120 | Z48: =IF(OR(X48="",X48=0),"",ROUND(P48/X48,1)) -> 25.4 | AA48: =IF(Y48="","",Y48-P48) -> -642 | AB48: =IF(A48="","",IF(COUNTIF($A$8:$A$670,A48)>1,"DUPLICADO","")) | AC48: {=IF(AH48<>"COMPRAR","",IF(MAX(INDEX(Ventas!$G$2:$G$5000,MATCH($A48,Ventas!$A$2:$A$5000,0)),INDEX(Ventas!$H$2:$H$5000,MATCH($A48,Ventas!$A$2:$A$5000,0)),INDEX(Ventas!$I$2:$I$5000,MATCH($A48,Ventas!$A$2:$A$5000,0)),INDEX(Ventas!$J$2:$J$5000,MATCH($A48,Ventas!$A$2:$A$5000,0)))>0.5*AF48*4,"1 mes = "&TEXT(MAX(INDEX(Ventas!$G$2:$G$5000,MATCH($A48,Ventas!$A$2:$A$5000,0)),INDEX(Ventas!$H$2:$H$5000,MATCH($A48,Ventas!$A$2:$A$5000,0)),INDEX(Ventas!$I$2:$I$5000,MATCH($A48,Ventas!$A$2:$A$5000,0)),INDEX(Ventas!$J$2:$J$5000,MATCH($A48,Ventas!$A$2:$A$5000,0)))/(AF48*4),"0%")&" de 4 meses",""))} | AD48: =IF(OR(X48="",X48=0),"",IF(E48+N(F48)<X48*$AD$5,"SÍ — "&TEXT(E48+N(F48),"#,##0")&" m vs "&TEXT(X48*$AD$5,"#,##0")&" m","")) | AE48: {=IF(X48="","",IF(AND(E48=0,AVERAGE(INDEX(Ventas!$C$2:$I$5000,MATCH($A48,Ventas!$A$2:$A$5000,0),0))>0,INDEX(Ventas!$J$2:$J$5000,MATCH($A48,Ventas!$A$2:$A$5000,0))<0.5*AVERAGE(INDEX(Ventas!$C$2:$I$5000,MATCH($A48,Ventas!$A$2:$A$5000,0),0))),"SÍ — stock 0 y Sep cayó (prom Feb-Ago "&TEXT(AVERAGE(INDEX(Ventas!$C$2:$I$5000,MATCH($A48,Ventas!$A$2:$A$5000,0),0)),"#,##0")&")",""))} | AF48: {=IF(X48="","",IF(AE48<>"",MAX(X48,AVERAGE(INDEX(Ventas!$C$2:$I$5000,MATCH($A48,Ventas!$A$2:$A$5000,0),0))),X48))} -> 30 | AG48: =IF(AF48="","",ROUND(AF48*4,0)-P48) -> -642 | AH48: =IF(A48="","",IF(AF48="","SIN HISTORIAL",IF(AF48=0,"SIN VENTAS",IF(AG48>0.1*ROUND(AF48*4,0),"COMPRAR",IF(AND(-AG48>0.1*ROUND(AF48*4,0),SUM(I48:M48)+IF($AD$3="SI",SUM(N48),0)>0),"PEDIR MENOS",IF(P48/AF48>8,"SOBRESTOCK","OK")))))) -> SOBRESTOCK
A49: 394923-0065 | B49: CAPELLADA | C49: TOKIO | D49: MANZANA | E49: 770 | O49: =IF(A49="","SIN SKU — cargar código para calcular",IF(X49="","SIN HISTORIAL DE VENTAS — artículo nuevo o código distinto en Ventas",IF(X49=0,IF(P49>0,"SIN VENTAS Jun-Sep — no comprar ("&TEXT(P49,"#,##0")&" m disponibles)","SIN VENTAS Jun-Sep — no comprar"),IF(AA49>0.1*Y49,"COMPRAR — faltan "&TEXT(AA49,"#,##0")&" m para 4 meses"&IF(P49-E49>0," (ya contando pedidos)",""),IF(AND(-AA49>0.1*Y49,SUM(I49:M49)+IF($AD$3="SI",SUM(N49),0)>0),"PEDIR MENOS — sobran "&TEXT(-AA49,"#,##0")&" m; revisar pedidos sin facturar ("&TEXT(SUM(I49:M49)+IF($AD$3="SI",SUM(N49),0),"#,##0")&" m)",IF(Z49>8,"SOBRESTOCK — "&TEXT(Z49,"0.0")&" meses de cobertura","OK — cubierto ("&TEXT(Z49,"0.0")&" meses)")))))) -> SIN VENTAS Jun-Sep — no comprar (770 m disponibles) | P49: =E49+N(F49)+SUM(G49:M49)+IF($AD$3="SI",SUM(N49),0) -> 770 | X49: =IFERROR(VLOOKUP($A49,Ventas!$A$2:$L$5000,12,FALSE()),"") -> 0 | Y49: =IF(X49="","",ROUND(X49*4,0)) -> 0 | Z49: =IF(OR(X49="",X49=0),"",ROUND(P49/X49,1)) | AA49: =IF(Y49="","",Y49-P49) -> -770 | AB49: =IF(A49="","",IF(COUNTIF($A$8:$A$670,A49)>1,"DUPLICADO","")) | AC49: {=IF(AH49<>"COMPRAR","",IF(MAX(INDEX(Ventas!$G$2:$G$5000,MATCH($A49,Ventas!$A$2:$A$5000,0)),INDEX(Ventas!$H$2:$H$5000,MATCH($A49,Ventas!$A$2:$A$5000,0)),INDEX(Ventas!$I$2:$I$5000,MATCH($A49,Ventas!$A$2:$A$5000,0)),INDEX(Ventas!$J$2:$J$5000,MATCH($A49,Ventas!$A$2:$A$5000,0)))>0.5*AF49*4,"1 mes = "&TEXT(MAX(INDEX(Ventas!$G$2:$G$5000,MATCH($A49,Ventas!$A$2:$A$5000,0)),INDEX(Ventas!$H$2:$H$5000,MATCH($A49,Ventas!$A$2:$A$5000,0)),INDEX(Ventas!$I$2:$I$5000,MATCH($A49,Ventas!$A$2:$A$5000,0)),INDEX(Ventas!$J$2:$J$5000,MATCH($A49,Ventas!$A$2:$A$5000,0)))/(AF49*4),"0%")&" de 4 meses",""))} | AD49: =IF(OR(X49="",X49=0),"",IF(E49+N(F49)<X49*$AD$5,"SÍ — "&TEXT(E49+N(F49),"#,##0")&" m vs "&TEXT(X49*$AD$5,"#,##0")&" m","")) | AE49: {=IF(X49="","",IF(AND(E49=0,AVERAGE(INDEX(Ventas!$C$2:$I$5000,MATCH($A49,Ventas!$A$2:$A$5000,0),0))>0,INDEX(Ventas!$J$2:$J$5000,MATCH($A49,Ventas!$A$2:$A$5000,0))<0.5*AVERAGE(INDEX(Ventas!$C$2:$I$5000,MATCH($A49,Ventas!$A$2:$A$5000,0),0))),"SÍ — stock 0 y Sep cayó (prom Feb-Ago "&TEXT(AVERAGE(INDEX(Ventas!$C$2:$I$5000,MATCH($A49,Ventas!$A$2:$A$5000,0),0)),"#,##0")&")",""))} | AF49: {=IF(X49="","",IF(AE49<>"",MAX(X49,AVERAGE(INDEX(Ventas!$C$2:$I$5000,MATCH($A49,Ventas!$A$2:$A$5000,0),0))),X49))} -> 0 | AG49: =IF(AF49="","",ROUND(AF49*4,0)-P49) -> -770 | AH49: =IF(A49="","",IF(AF49="","SIN HISTORIAL",IF(AF49=0,"SIN VENTAS",IF(AG49>0.1*ROUND(AF49*4,0),"COMPRAR",IF(AND(-AG49>0.1*ROUND(AF49*4,0),SUM(I49:M49)+IF($AD$3="SI",SUM(N49),0)>0),"PEDIR MENOS",IF(P49/AF49>8,"SOBRESTOCK","OK")))))) -> SIN VENTAS
A50: 394923-0014 | B50: CAPELLADA | C50: TOKIO | D50: LILA | E50: 288 | O50: =IF(A50="","SIN SKU — cargar código para calcular",IF(X50="","SIN HISTORIAL DE VENTAS — artículo nuevo o código distinto en Ventas",IF(X50=0,IF(P50>0,"SIN VENTAS Jun-Sep — no comprar ("&TEXT(P50,"#,##0")&" m disponibles)","SIN VENTAS Jun-Sep — no comprar"),IF(AA50>0.1*Y50,"COMPRAR — faltan "&TEXT(AA50,"#,##0")&" m para 4 meses"&IF(P50-E50>0," (ya contando pedidos)",""),IF(AND(-AA50>0.1*Y50,SUM(I50:M50)+IF($AD$3="SI",SUM(N50),0)>0),"PEDIR MENOS — sobran "&TEXT(-AA50,"#,##0")&" m; revisar pedidos sin facturar ("&TEXT(SUM(I50:M50)+IF($AD$3="SI",SUM(N50),0),"#,##0")&" m)",IF(Z50>8,"SOBRESTOCK — "&TEXT(Z50,"0.0")&" meses de cobertura","OK — cubierto ("&TEXT(Z50,"0.0")&" meses)")))))) -> SOBRESTOCK — 9.6 meses de cobertura | P50: =E50+N(F50)+SUM(G50:M50)+IF($AD$3="SI",SUM(N50),0) -> 288 | X50: =IFERROR(VLOOKUP($A50,Ventas!$A$2:$L$5000,12,FALSE()),"") -> 30 | Y50: =IF(X50="","",ROUND(X50*4,0)) -> 120 | Z50: =IF(OR(X50="",X50=0),"",ROUND(P50/X50,1)) -> 9.6 | AA50: =IF(Y50="","",Y50-P50) -> -168 | AB50: =IF(A50="","",IF(COUNTIF($A$8:$A$670,A50)>1,"DUPLICADO","")) | AC50: {=IF(AH50<>"COMPRAR","",IF(MAX(INDEX(Ventas!$G$2:$G$5000,MATCH($A50,Ventas!$A$2:$A$5000,0)),INDEX(Ventas!$H$2:$H$5000,MATCH($A50,Ventas!$A$2:$A$5000,0)),INDEX(Ventas!$I$2:$I$5000,MATCH($A50,Ventas!$A$2:$A$5000,0)),INDEX(Ventas!$J$2:$J$5000,MATCH($A50,Ventas!$A$2:$A$5000,0)))>0.5*AF50*4,"1 mes = "&TEXT(MAX(INDEX(Ventas!$G$2:$G$5000,MATCH($A50,Ventas!$A$2:$A$5000,0)),INDEX(Ventas!$H$2:$H$5000,MATCH($A50,Ventas!$A$2:$A$5000,0)),INDEX(Ventas!$I$2:$I$5000,MATCH($A50,Ventas!$A$2:$A$5000,0)),INDEX(Ventas!$J$2:$J$5000,MATCH($A50,Ventas!$A$2:$A$5000,0)))/(AF50*4),"0%")&" de 4 meses",""))} | AD50: =IF(OR(X50="",X50=0),"",IF(E50+N(F50)<X50*$AD$5,"SÍ — "&TEXT(E50+N(F50),"#,##0")&" m vs "&TEXT(X50*$AD$5,"#,##0")&" m","")) | AE50: {=IF(X50="","",IF(AND(E50=0,AVERAGE(INDEX(Ventas!$C$2:$I$5000,MATCH($A50,Ventas!$A$2:$A$5000,0),0))>0,INDEX(Ventas!$J$2:$J$5000,MATCH($A50,Ventas!$A$2:$A$5000,0))<0.5*AVERAGE(INDEX(Ventas!$C$2:$I$5000,MATCH($A50,Ventas!$A$2:$A$5000,0),0))),"SÍ — stock 0 y Sep cayó (prom Feb-Ago "&TEXT(AVERAGE(INDEX(Ventas!$C$2:$I$5000,MATCH($A50,Ventas!$A$2:$A$5000,0),0)),"#,##0")&")",""))} | AF50: {=IF(X50="","",IF(AE50<>"",MAX(X50,AVERAGE(INDEX(Ventas!$C$2:$I$5000,MATCH($A50,Ventas!$A$2:$A$5000,0),0))),X50))} -> 30 | AG50: =IF(AF50="","",ROUND(AF50*4,0)-P50) -> -168 | AH50: =IF(A50="","",IF(AF50="","SIN HISTORIAL",IF(AF50=0,"SIN VENTAS",IF(AG50>0.1*ROUND(AF50*4,0),"COMPRAR",IF(AND(-AG50>0.1*ROUND(AF50*4,0),SUM(I50:M50)+IF($AD$3="SI",SUM(N50),0)>0),"PEDIR MENOS",IF(P50/AF50>8,"SOBRESTOCK","OK")))))) -> SOBRESTOCK
A51: 394923-0022 | B51: CAPELLADA | C51: TOKIO | D51: ROSA | E51: 720 | O51: =IF(A51="","SIN SKU — cargar código para calcular",IF(X51="","SIN HISTORIAL DE VENTAS — artículo nuevo o código distinto en Ventas",IF(X51=0,IF(P51>0,"SIN VENTAS Jun-Sep — no comprar ("&TEXT(P51,"#,##0")&" m disponibles)","SIN VENTAS Jun-Sep — no comprar"),IF(AA51>0.1*Y51,"COMPRAR — faltan "&TEXT(AA51,"#,##0")&" m para 4 meses"&IF(P51-E51>0," (ya contando pedidos)",""),IF(AND(-AA51>0.1*Y51,SUM(I51:M51)+IF($AD$3="SI",SUM(N51),0)>0),"PEDIR MENOS — sobran "&TEXT(-AA51,"#,##0")&" m; revisar pedidos sin facturar ("&TEXT(SUM(I51:M51)+IF($AD$3="SI",SUM(N51),0),"#,##0")&" m)",IF(Z51>8,"SOBRESTOCK — "&TEXT(Z51,"0.0")&" meses de cobertura","OK — cubierto ("&TEXT(Z51,"0.0")&" meses)")))))) -> SOBRESTOCK — 22.0 meses de cobertura | P51: =E51+N(F51)+SUM(G51:M51)+IF($AD$3="SI",SUM(N51),0) -> 720 | X51: =IFERROR(VLOOKUP($A51,Ventas!$A$2:$L$5000,12,FALSE()),"") -> 32.75 | Y51: =IF(X51="","",ROUND(X51*4,0)) -> 131 | Z51: =IF(OR(X51="",X51=0),"",ROUND(P51/X51,1)) -> 22 | AA51: =IF(Y51="","",Y51-P51) -> -589 | AB51: =IF(A51="","",IF(COUNTIF($A$8:$A$670,A51)>1,"DUPLICADO","")) | AC51: {=IF(AH51<>"COMPRAR","",IF(MAX(INDEX(Ventas!$G$2:$G$5000,MATCH($A51,Ventas!$A$2:$A$5000,0)),INDEX(Ventas!$H$2:$H$5000,MATCH($A51,Ventas!$A$2:$A$5000,0)),INDEX(Ventas!$I$2:$I$5000,MATCH($A51,Ventas!$A$2:$A$5000,0)),INDEX(Ventas!$J$2:$J$5000,MATCH($A51,Ventas!$A$2:$A$5000,0)))>0.5*AF51*4,"1 mes = "&TEXT(MAX(INDEX(Ventas!$G$2:$G$5000,MATCH($A51,Ventas!$A$2:$A$5000,0)),INDEX(Ventas!$H$2:$H$5000,MATCH($A51,Ventas!$A$2:$A$5000,0)),INDEX(Ventas!$I$2:$I$5000,MATCH($A51,Ventas!$A$2:$A$5000,0)),INDEX(Ventas!$J$2:$J$5000,MATCH($A51,Ventas!$A$2:$A$5000,0)))/(AF51*4),"0%")&" de 4 meses",""))} | AD51: =IF(OR(X51="",X51=0),"",IF(E51+N(F51)<X51*$AD$5,"SÍ — "&TEXT(E51+N(F51),"#,##0")&" m vs "&TEXT(X51*$AD$5,"#,##0")&" m","")) | AE51: {=IF(X51="","",IF(AND(E51=0,AVERAGE(INDEX(Ventas!$C$2:$I$5000,MATCH($A51,Ventas!$A$2:$A$5000,0),0))>0,INDEX(Ventas!$J$2:$J$5000,MATCH($A51,Ventas!$A$2:$A$5000,0))<0.5*AVERAGE(INDEX(Ventas!$C$2:$I$5000,MATCH($A51,Ventas!$A$2:$A$5000,0),0))),"SÍ — stock 0 y Sep cayó (prom Feb-Ago "&TEXT(AVERAGE(INDEX(Ventas!$C$2:$I$5000,MATCH($A51,Ventas!$A$2:$A$5000,0),0)),"#,##0")&")",""))} | AF51: {=IF(X51="","",IF(AE51<>"",MAX(X51,AVERAGE(INDEX(Ventas!$C$2:$I$5000,MATCH($A51,Ventas!$A$2:$A$5000,0),0))),X51))} -> 32.75 | AG51: =IF(AF51="","",ROUND(AF51*4,0)-P51) -> -589 | AH51: =IF(A51="","",IF(AF51="","SIN HISTORIAL",IF(AF51=0,"SIN VENTAS",IF(AG51>0.1*ROUND(AF51*4,0),"COMPRAR",IF(AND(-AG51>0.1*ROUND(AF51*4,0),SUM(I51:M51)+IF($AD$3="SI",SUM(N51),0)>0),"PEDIR MENOS",IF(P51/AF51>8,"SOBRESTOCK","OK")))))) -> SOBRESTOCK
A52: 394923-0009 | B52: CAPELLADA | C52: TOKIO | D52: CELESTE | E52: 160 | O52: =IF(A52="","SIN SKU — cargar código para calcular",IF(X52="","SIN HISTORIAL DE VENTAS — artículo nuevo o código distinto en Ventas",IF(X52=0,IF(P52>0,"SIN VENTAS Jun-Sep — no comprar ("&TEXT(P52,"#,##0")&" m disponibles)","SIN VENTAS Jun-Sep — no comprar"),IF(AA52>0.1*Y52,"COMPRAR — faltan "&TEXT(AA52,"#,##0")&" m para 4 meses"&IF(P52-E52>0," (ya contando pedidos)",""),IF(AND(-AA52>0.1*Y52,SUM(I52:M52)+IF($AD$3="SI",SUM(N52),0)>0),"PEDIR MENOS — sobran "&TEXT(-AA52,"#,##0")&" m; revisar pedidos sin facturar ("&TEXT(SUM(I52:M52)+IF($AD$3="SI",SUM(N52),0),"#,##0")&" m)",IF(Z52>8,"SOBRESTOCK — "&TEXT(Z52,"0.0")&" meses de cobertura","OK — cubierto ("&TEXT(Z52,"0.0")&" meses)")))))) -> OK — cubierto (4.0 meses) | P52: =E52+N(F52)+SUM(G52:M52)+IF($AD$3="SI",SUM(N52),0) -> 160 | X52: =IFERROR(VLOOKUP($A52,Ventas!$A$2:$L$5000,12,FALSE()),"") -> 40 | Y52: =IF(X52="","",ROUND(X52*4,0)) -> 160 | Z52: =IF(OR(X52="",X52=0),"",ROUND(P52/X52,1)) -> 4 | AA52: =IF(Y52="","",Y52-P52) -> 0 | AB52: =IF(A52="","",IF(COUNTIF($A$8:$A$670,A52)>1,"DUPLICADO","")) | AC52: {=IF(AH52<>"COMPRAR","",IF(MAX(INDEX(Ventas!$G$2:$G$5000,MATCH($A52,Ventas!$A$2:$A$5000,0)),INDEX(Ventas!$H$2:$H$5000,MATCH($A52,Ventas!$A$2:$A$5000,0)),INDEX(Ventas!$I$2:$I$5000,MATCH($A52,Ventas!$A$2:$A$5000,0)),INDEX(Ventas!$J$2:$J$5000,MATCH($A52,Ventas!$A$2:$A$5000,0)))>0.5*AF52*4,"1 mes = "&TEXT(MAX(INDEX(Ventas!$G$2:$G$5000,MATCH($A52,Ventas!$A$2:$A$5000,0)),INDEX(Ventas!$H$2:$H$5000,MATCH($A52,Ventas!$A$2:$A$5000,0)),INDEX(Ventas!$I$2:$I$5000,MATCH($A52,Ventas!$A$2:$A$5000,0)),INDEX(Ventas!$J$2:$J$5000,MATCH($A52,Ventas!$A$2:$A$5000,0)))/(AF52*4),"0%")&" de 4 meses",""))} | AD52: =IF(OR(X52="",X52=0),"",IF(E52+N(F52)<X52*$AD$5,"SÍ — "&TEXT(E52+N(F52),"#,##0")&" m vs "&TEXT(X52*$AD$5,"#,##0")&" m","")) | AE52: {=IF(X52="","",IF(AND(E52=0,AVERAGE(INDEX(Ventas!$C$2:$I$5000,MATCH($A52,Ventas!$A$2:$A$5000,0),0))>0,INDEX(Ventas!$J$2:$J$5000,MATCH($A52,Ventas!$A$2:$A$5000,0))<0.5*AVERAGE(INDEX(Ventas!$C$2:$I$5000,MATCH($A52,Ventas!$A$2:$A$5000,0),0))),"SÍ — stock 0 y Sep cayó (prom Feb-Ago "&TEXT(AVERAGE(INDEX(Ventas!$C$2:$I$5000,MATCH($A52,Ventas!$A$2:$A$5000,0),0)),"#,##0")&")",""))} | AF52: {=IF(X52="","",IF(AE52<>"",MAX(X52,AVERAGE(INDEX(Ventas!$C$2:$I$5000,MATCH($A52,Ventas!$A$2:$A$5000,0),0))),X52))} -> 40 | AG52: =IF(AF52="","",ROUND(AF52*4,0)-P52) -> 0 | AH52: =IF(A52="","",IF(AF52="","SIN HISTORIAL",IF(AF52=0,"SIN VENTAS",IF(AG52>0.1*ROUND(AF52*4,0),"COMPRAR",IF(AND(-AG52>0.1*ROUND(AF52*4,0),SUM(I52:M52)+IF($AD$3="SI",SUM(N52),0)>0),"PEDIR MENOS",IF(P52/AF52>8,"SOBRESTOCK","OK")))))) -> OK
A53: 394923-0198 | B53: CAPELLADA | C53: TOKIO | D53: MANTECA | E53: 1386 | O53: =IF(A53="","SIN SKU — cargar código para calcular",IF(X53="","SIN HISTORIAL DE VENTAS — artículo nuevo o código distinto en Ventas",IF(X53=0,IF(P53>0,"SIN VENTAS Jun-Sep — no comprar ("&TEXT(P53,"#,##0")&" m disponibles)","SIN VENTAS Jun-Sep — no comprar"),IF(AA53>0.1*Y53,"COMPRAR — faltan "&TEXT(AA53,"#,##0")&" m para 4 meses"&IF(P53-E53>0," (ya contando pedidos)",""),IF(AND(-AA53>0.1*Y53,SUM(I53:M53)+IF($AD$3="SI",SUM(N53),0)>0),"PEDIR MENOS — sobran "&TEXT(-AA53,"#,##0")&" m; revisar pedidos sin facturar ("&TEXT(SUM(I53:M53)+IF($AD$3="SI",SUM(N53),0),"#,##0")&" m)",IF(Z53>8,"SOBRESTOCK — "&TEXT(Z53,"0.0")&" meses de cobertura","OK — cubierto ("&TEXT(Z53,"0.0")&" meses)")))))) -> SOBRESTOCK — 9.0 meses de cobertura | P53: =E53+N(F53)+SUM(G53:M53)+IF($AD$3="SI",SUM(N53),0) -> 1386 | X53: =IFERROR(VLOOKUP($A53,Ventas!$A$2:$L$5000,12,FALSE()),"") -> 154.75 | Y53: =IF(X53="","",ROUND(X53*4,0)) -> 619 | Z53: =IF(OR(X53="",X53=0),"",ROUND(P53/X53,1)) -> 9 | AA53: =IF(Y53="","",Y53-P53) -> -767 | AB53: =IF(A53="","",IF(COUNTIF($A$8:$A$670,A53)>1,"DUPLICADO","")) | AC53: {=IF(AH53<>"COMPRAR","",IF(MAX(INDEX(Ventas!$G$2:$G$5000,MATCH($A53,Ventas!$A$2:$A$5000,0)),INDEX(Ventas!$H$2:$H$5000,MATCH($A53,Ventas!$A$2:$A$5000,0)),INDEX(Ventas!$I$2:$I$5000,MATCH($A53,Ventas!$A$2:$A$5000,0)),INDEX(Ventas!$J$2:$J$5000,MATCH($A53,Ventas!$A$2:$A$5000,0)))>0.5*AF53*4,"1 mes = "&TEXT(MAX(INDEX(Ventas!$G$2:$G$5000,MATCH($A53,Ventas!$A$2:$A$5000,0)),INDEX(Ventas!$H$2:$H$5000,MATCH($A53,Ventas!$A$2:$A$5000,0)),INDEX(Ventas!$I$2:$I$5000,MATCH($A53,Ventas!$A$2:$A$5000,0)),INDEX(Ventas!$J$2:$J$5000,MATCH($A53,Ventas!$A$2:$A$5000,0)))/(AF53*4),"0%")&" de 4 meses",""))} | AD53: =IF(OR(X53="",X53=0),"",IF(E53+N(F53)<X53*$AD$5,"SÍ — "&TEXT(E53+N(F53),"#,##0")&" m vs "&TEXT(X53*$AD$5,"#,##0")&" m","")) | AE53: {=IF(X53="","",IF(AND(E53=0,AVERAGE(INDEX(Ventas!$C$2:$I$5000,MATCH($A53,Ventas!$A$2:$A$5000,0),0))>0,INDEX(Ventas!$J$2:$J$5000,MATCH($A53,Ventas!$A$2:$A$5000,0))<0.5*AVERAGE(INDEX(Ventas!$C$2:$I$5000,MATCH($A53,Ventas!$A$2:$A$5000,0),0))),"SÍ — stock 0 y Sep cayó (prom Feb-Ago "&TEXT(AVERAGE(INDEX(Ventas!$C$2:$I$5000,MATCH($A53,Ventas!$A$2:$A$5000,0),0)),"#,##0")&")",""))} | AF53: {=IF(X53="","",IF(AE53<>"",MAX(X53,AVERAGE(INDEX(Ventas!$C$2:$I$5000,MATCH($A53,Ventas!$A$2:$A$5000,0),0))),X53))} -> 154.75 | AG53: =IF(AF53="","",ROUND(AF53*4,0)-P53) -> -767 | AH53: =IF(A53="","",IF(AF53="","SIN HISTORIAL",IF(AF53=0,"SIN VENTAS",IF(AG53>0.1*ROUND(AF53*4,0),"COMPRAR",IF(AND(-AG53>0.1*ROUND(AF53*4,0),SUM(I53:M53)+IF($AD$3="SI",SUM(N53),0)>0),"PEDIR MENOS",IF(P53/AF53>8,"SOBRESTOCK","OK")))))) -> SOBRESTOCK
A54: 394923-0003 | B54: CAPELLADA | C54: TOKIO | D54: BEIGE | E54: 0 | O54: =IF(A54="","SIN SKU — cargar código para calcular",IF(X54="","SIN HISTORIAL DE VENTAS — artículo nuevo o código distinto en Ventas",IF(X54=0,IF(P54>0,"SIN VENTAS Jun-Sep — no comprar ("&TEXT(P54,"#,##0")&" m disponibles)","SIN VENTAS Jun-Sep — no comprar"),IF(AA54>0.1*Y54,"COMPRAR — faltan "&TEXT(AA54,"#,##0")&" m para 4 meses"&IF(P54-E54>0," (ya contando pedidos)",""),IF(AND(-AA54>0.1*Y54,SUM(I54:M54)+IF($AD$3="SI",SUM(N54),0)>0),"PEDIR MENOS — sobran "&TEXT(-AA54,"#,##0")&" m; revisar pedidos sin facturar ("&TEXT(SUM(I54:M54)+IF($AD$3="SI",SUM(N54),0),"#,##0")&" m)",IF(Z54>8,"SOBRESTOCK — "&TEXT(Z54,"0.0")&" meses de cobertura","OK — cubierto ("&TEXT(Z54,"0.0")&" meses)")))))) -> SIN VENTAS Jun-Sep — no comprar | P54: =E54+N(F54)+SUM(G54:M54)+IF($AD$3="SI",SUM(N54),0) -> 0 | Q54: Ingreso de 3239 mts entre 26/07/2023 y 10/10/2023 y se vendieron en 23 meses. 140 mts por mes en promedio. | X54: =IFERROR(VLOOKUP($A54,Ventas!$A$2:$L$5000,12,FALSE()),"") -> 0 | Y54: =IF(X54="","",ROUND(X54*4,0)) -> 0 | Z54: =IF(OR(X54="",X54=0),"",ROUND(P54/X54,1)) | AA54: =IF(Y54="","",Y54-P54) -> 0 | AB54: =IF(A54="","",IF(COUNTIF($A$8:$A$670,A54)>1,"DUPLICADO","")) | AC54: {=IF(AH54<>"COMPRAR","",IF(MAX(INDEX(Ventas!$G$2:$G$5000,MATCH($A54,Ventas!$A$2:$A$5000,0)),INDEX(Ventas!$H$2:$H$5000,MATCH($A54,Ventas!$A$2:$A$5000,0)),INDEX(Ventas!$I$2:$I$5000,MATCH($A54,Ventas!$A$2:$A$5000,0)),INDEX(Ventas!$J$2:$J$5000,MATCH($A54,Ventas!$A$2:$A$5000,0)))>0.5*AF54*4,"1 mes = "&TEXT(MAX(INDEX(Ventas!$G$2:$G$5000,MATCH($A54,Ventas!$A$2:$A$5000,0)),INDEX(Ventas!$H$2:$H$5000,MATCH($A54,Ventas!$A$2:$A$5000,0)),INDEX(Ventas!$I$2:$I$5000,MATCH($A54,Ventas!$A$2:$A$5000,0)),INDEX(Ventas!$J$2:$J$5000,MATCH($A54,Ventas!$A$2:$A$5000,0)))/(AF54*4),"0%")&" de 4 meses",""))} | AD54: =IF(OR(X54="",X54=0),"",IF(E54+N(F54)<X54*$AD$5,"SÍ — "&TEXT(E54+N(F54),"#,##0")&" m vs "&TEXT(X54*$AD$5,"#,##0")&" m","")) | AE54: {=IF(X54="","",IF(AND(E54=0,AVERAGE(INDEX(Ventas!$C$2:$I$5000,MATCH($A54,Ventas!$A$2:$A$5000,0),0))>0,INDEX(Ventas!$J$2:$J$5000,MATCH($A54,Ventas!$A$2:$A$5000,0))<0.5*AVERAGE(INDEX(Ventas!$C$2:$I$5000,MATCH($A54,Ventas!$A$2:$A$5000,0),0))),"SÍ — stock 0 y Sep cayó (prom Feb-Ago "&TEXT(AVERAGE(INDEX(Ventas!$C$2:$I$5000,MATCH($A54,Ventas!$A$2:$A$5000,0),0)),"#,##0")&")",""))} | AF54: {=IF(X54="","",IF(AE54<>"",MAX(X54,AVERAGE(INDEX(Ventas!$C$2:$I$5000,MATCH($A54,Ventas!$A$2:$A$5000,0),0))),X54))} -> 0 | AG54: =IF(AF54="","",ROUND(AF54*4,0)-P54) -> 0 | AH54: =IF(A54="","",IF(AF54="","SIN HISTORIAL",IF(AF54=0,"SIN VENTAS",IF(AG54>0.1*ROUND(AF54*4,0),"COMPRAR",IF(AND(-AG54>0.1*ROUND(AF54*4,0),SUM(I54:M54)+IF($AD$3="SI",SUM(N54),0)>0),"PEDIR MENOS",IF(P54/AF54>8,"SOBRESTOCK","OK")))))) -> SIN VENTAS
A55: 394923-0045 | B55: CAPELLADA | C55: TOKIO | D55: GRIS | E55: 361 | O55: =IF(A55="","SIN SKU — cargar código para calcular",IF(X55="","SIN HISTORIAL DE VENTAS — artículo nuevo o código distinto en Ventas",IF(X55=0,IF(P55>0,"SIN VENTAS Jun-Sep — no comprar ("&TEXT(P55,"#,##0")&" m disponibles)","SIN VENTAS Jun-Sep — no comprar"),IF(AA55>0.1*Y55,"COMPRAR — faltan "&TEXT(AA55,"#,##0")&" m para 4 meses"&IF(P55-E55>0," (ya contando pedidos)",""),IF(AND(-AA55>0.1*Y55,SUM(I55:M55)+IF($AD$3="SI",SUM(N55),0)>0),"PEDIR MENOS — sobran "&TEXT(-AA55,"#,##0")&" m; revisar pedidos sin facturar ("&TEXT(SUM(I55:M55)+IF($AD$3="SI",SUM(N55),0),"#,##0")&" m)",IF(Z55>8,"SOBRESTOCK — "&TEXT(Z55,"0.0")&" meses de cobertura","OK — cubierto ("&TEXT(Z55,"0.0")&" meses)")))))) -> SIN VENTAS Jun-Sep — no comprar (361 m disponibles) | P55: =E55+N(F55)+SUM(G55:M55)+IF($AD$3="SI",SUM(N55),0) -> 361 | X55: =IFERROR(VLOOKUP($A55,Ventas!$A$2:$L$5000,12,FALSE()),"") -> 0 | Y55: =IF(X55="","",ROUND(X55*4,0)) -> 0 | Z55: =IF(OR(X55="",X55=0),"",ROUND(P55/X55,1)) | AA55: =IF(Y55="","",Y55-P55) -> -361 | AB55: =IF(A55="","",IF(COUNTIF($A$8:$A$670,A55)>1,"DUPLICADO","")) | AC55: {=IF(AH55<>"COMPRAR","",IF(MAX(INDEX(Ventas!$G$2:$G$5000,MATCH($A55,Ventas!$A$2:$A$5000,0)),INDEX(Ventas!$H$2:$H$5000,MATCH($A55,Ventas!$A$2:$A$5000,0)),INDEX(Ventas!$I$2:$I$5000,MATCH($A55,Ventas!$A$2:$A$5000,0)),INDEX(Ventas!$J$2:$J$5000,MATCH($A55,Ventas!$A$2:$A$5000,0)))>0.5*AF55*4,"1 mes = "&TEXT(MAX(INDEX(Ventas!$G$2:$G$5000,MATCH($A55,Ventas!$A$2:$A$5000,0)),INDEX(Ventas!$H$2:$H$5000,MATCH($A55,Ventas!$A$2:$A$5000,0)),INDEX(Ventas!$I$2:$I$5000,MATCH($A55,Ventas!$A$2:$A$5000,0)),INDEX(Ventas!$J$2:$J$5000,MATCH($A55,Ventas!$A$2:$A$5000,0)))/(AF55*4),"0%")&" de 4 meses",""))} | AD55: =IF(OR(X55="",X55=0),"",IF(E55+N(F55)<X55*$AD$5,"SÍ — "&TEXT(E55+N(F55),"#,##0")&" m vs "&TEXT(X55*$AD$5,"#,##0")&" m","")) | AE55: {=IF(X55="","",IF(AND(E55=0,AVERAGE(INDEX(Ventas!$C$2:$I$5000,MATCH($A55,Ventas!$A$2:$A$5000,0),0))>0,INDEX(Ventas!$J$2:$J$5000,MATCH($A55,Ventas!$A$2:$A$5000,0))<0.5*AVERAGE(INDEX(Ventas!$C$2:$I$5000,MATCH($A55,Ventas!$A$2:$A$5000,0),0))),"SÍ — stock 0 y Sep cayó (prom Feb-Ago "&TEXT(AVERAGE(INDEX(Ventas!$C$2:$I$5000,MATCH($A55,Ventas!$A$2:$A$5000,0),0)),"#,##0")&")",""))} | AF55: {=IF(X55="","",IF(AE55<>"",MAX(X55,AVERAGE(INDEX(Ventas!$C$2:$I$5000,MATCH($A55,Ventas!$A$2:$A$5000,0),0))),X55))} -> 0 | AG55: =IF(AF55="","",ROUND(AF55*4,0)-P55) -> -361 | AH55: =IF(A55="","",IF(AF55="","SIN HISTORIAL",IF(AF55=0,"SIN VENTAS",IF(AG55>0.1*ROUND(AF55*4,0),"COMPRAR",IF(AND(-AG55>0.1*ROUND(AF55*4,0),SUM(I55:M55)+IF($AD$3="SI",SUM(N55),0)>0),"PEDIR MENOS",IF(P55/AF55>8,"SOBRESTOCK","OK")))))) -> SIN VENTAS
A56: 285127-9999 | B56: CAPELLADA | C56: NAPA | D56: NEGRO | E56: 3084 | I56: 7000 | K56: 9000 | L56: 3000 | O56: =IF(A56="","SIN SKU — cargar código para calcular",IF(X56="","SIN HISTORIAL DE VENTAS — artículo nuevo o código distinto en Ventas",IF(X56=0,IF(P56>0,"SIN VENTAS Jun-Sep — no comprar ("&TEXT(P56,"#,##0")&" m disponibles)","SIN VENTAS Jun-Sep — no comprar"),IF(AA56>0.1*Y56,"COMPRAR — faltan "&TEXT(AA56,"#,##0")&" m para 4 meses"&IF(P56-E56>0," (ya contando pedidos)",""),IF(AND(-AA56>0.1*Y56,SUM(I56:M56)+IF($AD$3="SI",SUM(N56),0)>0),"PEDIR MENOS — sobran "&TEXT(-AA56,"#,##0")&" m; revisar pedidos sin facturar ("&TEXT(SUM(I56:M56)+IF($AD$3="SI",SUM(N56),0),"#,##0")&" m)",IF(Z56>8,"SOBRESTOCK — "&TEXT(Z56,"0.0")&" meses de cobertura","OK — cubierto ("&TEXT(Z56,"0.0")&" meses)")))))) -> OK — cubierto (4.0 meses) | P56: =E56+N(F56)+SUM(G56:M56)+IF($AD$3="SI",SUM(N56),0) -> 22084 | Q56: 609 | R56: 2520 | X56: =IFERROR(VLOOKUP($A56,Ventas!$A$2:$L$5000,12,FALSE()),"") -> 5580.75 | Y56: =IF(X56="","",ROUND(X56*4,0)) -> 22323 | Z56: =IF(OR(X56="",X56=0),"",ROUND(P56/X56,1)) -> 4 | AA56: =IF(Y56="","",Y56-P56) -> 239 | AB56: =IF(A56="","",IF(COUNTIF($A$8:$A$670,A56)>1,"DUPLICADO","")) | AC56: {=IF(AH56<>"COMPRAR","",IF(MAX(INDEX(Ventas!$G$2:$G$5000,MATCH($A56,Ventas!$A$2:$A$5000,0)),INDEX(Ventas!$H$2:$H$5000,MATCH($A56,Ventas!$A$2:$A$5000,0)),INDEX(Ventas!$I$2:$I$5000,MATCH($A56,Ventas!$A$2:$A$5000,0)),INDEX(Ventas!$J$2:$J$5000,MATCH($A56,Ventas!$A$2:$A$5000,0)))>0.5*AF56*4,"1 mes = "&TEXT(MAX(INDEX(Ventas!$G$2:$G$5000,MATCH($A56,Ventas!$A$2:$A$5000,0)),INDEX(Ventas!$H$2:$H$5000,MATCH($A56,Ventas!$A$2:$A$5000,0)),INDEX(Ventas!$I$2:$I$5000,MATCH($A56,Ventas!$A$2:$A$5000,0)),INDEX(Ventas!$J$2:$J$5000,MATCH($A56,Ventas!$A$2:$A$5000,0)))/(AF56*4),"0%")&" de 4 meses",""))} | AD56: =IF(OR(X56="",X56=0),"",IF(E56+N(F56)<X56*$AD$5,"SÍ — "&TEXT(E56+N(F56),"#,##0")&" m vs "&TEXT(X56*$AD$5,"#,##0")&" m","")) | AE56: {=IF(X56="","",IF(AND(E56=0,AVERAGE(INDEX(Ventas!$C$2:$I$5000,MATCH($A56,Ventas!$A$2:$A$5000,0),0))>0,INDEX(Ventas!$J$2:$J$5000,MATCH($A56,Ventas!$A$2:$A$5000,0))<0.5*AVERAGE(INDEX(Ventas!$C$2:$I$5000,MATCH($A56,Ventas!$A$2:$A$5000,0),0))),"SÍ — stock 0 y Sep cayó (prom Feb-Ago "&TEXT(AVERAGE(INDEX(Ventas!$C$2:$I$5000,MATCH($A56,Ventas!$A$2:$A$5000,0),0)),"#,##0")&")",""))} | AF56: {=IF(X56="","",IF(AE56<>"",MAX(X56,AVERAGE(INDEX(Ventas!$C$2:$I$5000,MATCH($A56,Ventas!$A$2:$A$5000,0),0))),X56))} -> 5580.75 | AG56: =IF(AF56="","",ROUND(AF56*4,0)-P56) -> 239 | AH56: =IF(A56="","",IF(AF56="","SIN HISTORIAL",IF(AF56=0,"SIN VENTAS",IF(AG56>0.1*ROUND(AF56*4,0),"COMPRAR",IF(AND(-AG56>0.1*ROUND(AF56*4,0),SUM(I56:M56)+IF($AD$3="SI",SUM(N56),0)>0),"PEDIR MENOS",IF(P56/AF56>8,"SOBRESTOCK","OK")))))) -> OK
A57: 285127-0000 | B57: CAPELLADA | C57: NAPA | D57: BLANCO | E57: 328 | I57: 2000 | K57: 2000 | O57: =IF(A57="","SIN SKU — cargar código para calcular",IF(X57="","SIN HISTORIAL DE VENTAS — artículo nuevo o código distinto en Ventas",IF(X57=0,IF(P57>0,"SIN VENTAS Jun-Sep — no comprar ("&TEXT(P57,"#,##0")&" m disponibles)","SIN VENTAS Jun-Sep — no comprar"),IF(AA57>0.1*Y57,"COMPRAR — faltan "&TEXT(AA57,"#,##0")&" m para 4 meses"&IF(P57-E57>0," (ya contando pedidos)",""),IF(AND(-AA57>0.1*Y57,SUM(I57:M57)+IF($AD$3="SI",SUM(N57),0)>0),"PEDIR MENOS — sobran "&TEXT(-AA57,"#,##0")&" m; revisar pedidos sin facturar ("&TEXT(SUM(I57:M57)+IF($AD$3="SI",SUM(N57),0),"#,##0")&" m)",IF(Z57>8,"SOBRESTOCK — "&TEXT(Z57,"0.0")&" meses de cobertura","OK — cubierto ("&TEXT(Z57,"0.0")&" meses)")))))) -> COMPRAR — faltan 631 m para 4 meses (ya contando pedidos) | P57: =E57+N(F57)+SUM(G57:M57)+IF($AD$3="SI",SUM(N57),0) -> 4328 | X57: =IFERROR(VLOOKUP($A57,Ventas!$A$2:$L$5000,12,FALSE()),"") -> 1239.75 | Y57: =IF(X57="","",ROUND(X57*4,0)) -> 4959 | Z57: =IF(OR(X57="",X57=0),"",ROUND(P57/X57,1)) -> 3.5 | AA57: =IF(Y57="","",Y57-P57) -> 631 | AB57: =IF(A57="","",IF(COUNTIF($A$8:$A$670,A57)>1,"DUPLICADO","")) | AC57: {=IF(AH57<>"COMPRAR","",IF(MAX(INDEX(Ventas!$G$2:$G$5000,MATCH($A57,Ventas!$A$2:$A$5000,0)),INDEX(Ventas!$H$2:$H$5000,MATCH($A57,Ventas!$A$2:$A$5000,0)),INDEX(Ventas!$I$2:$I$5000,MATCH($A57,Ventas!$A$2:$A$5000,0)),INDEX(Ventas!$J$2:$J$5000,MATCH($A57,Ventas!$A$2:$A$5000,0)))>0.5*AF57*4,"1 mes = "&TEXT(MAX(INDEX(Ventas!$G$2:$G$5000,MATCH($A57,Ventas!$A$2:$A$5000,0)),INDEX(Ventas!$H$2:$H$5000,MATCH($A57,Ventas!$A$2:$A$5000,0)),INDEX(Ventas!$I$2:$I$5000,MATCH($A57,Ventas!$A$2:$A$5000,0)),INDEX(Ventas!$J$2:$J$5000,MATCH($A57,Ventas!$A$2:$A$5000,0)))/(AF57*4),"0%")&" de 4 meses",""))} | AD57: =IF(OR(X57="",X57=0),"",IF(E57+N(F57)<X57*$AD$5,"SÍ — "&TEXT(E57+N(F57),"#,##0")&" m vs "&TEXT(X57*$AD$5,"#,##0")&" m","")) -> SÍ — 328 m vs 657 m | AE57: {=IF(X57="","",IF(AND(E57=0,AVERAGE(INDEX(Ventas!$C$2:$I$5000,MATCH($A57,Ventas!$A$2:$A$5000,0),0))>0,INDEX(Ventas!$J$2:$J$5000,MATCH($A57,Ventas!$A$2:$A$5000,0))<0.5*AVERAGE(INDEX(Ventas!$C$2:$I$5000,MATCH($A57,Ventas!$A$2:$A$5000,0),0))),"SÍ — stock 0 y Sep cayó (prom Feb-Ago "&TEXT(AVERAGE(INDEX(Ventas!$C$2:$I$5000,MATCH($A57,Ventas!$A$2:$A$5000,0),0)),"#,##0")&")",""))} | AF57: {=IF(X57="","",IF(AE57<>"",MAX(X57,AVERAGE(INDEX(Ventas!$C$2:$I$5000,MATCH($A57,Ventas!$A$2:$A$5000,0),0))),X57))} -> 1239.75 | AG57: =IF(AF57="","",ROUND(AF57*4,0)-P57) -> 631 | AH57: =IF(A57="","",IF(AF57="","SIN HISTORIAL",IF(AF57=0,"SIN VENTAS",IF(AG57>0.1*ROUND(AF57*4,0),"COMPRAR",IF(AND(-AG57>0.1*ROUND(AF57*4,0),SUM(I57:M57)+IF($AD$3="SI",SUM(N57),0)>0),"PEDIR MENOS",IF(P57/AF57>8,"SOBRESTOCK","OK")))))) -> COMPRAR
A58: 285127-0021 | B58: CAPELLADA | C58: NAPA | D58: ROJO | E58: 436 | O58: =IF(A58="","SIN SKU — cargar código para calcular",IF(X58="","SIN HISTORIAL DE VENTAS — artículo nuevo o código distinto en Ventas",IF(X58=0,IF(P58>0,"SIN VENTAS Jun-Sep — no comprar ("&TEXT(P58,"#,##0")&" m disponibles)","SIN VENTAS Jun-Sep — no comprar"),IF(AA58>0.1*Y58,"COMPRAR — faltan "&TEXT(AA58,"#,##0")&" m para 4 meses"&IF(P58-E58>0," (ya contando pedidos)",""),IF(AND(-AA58>0.1*Y58,SUM(I58:M58)+IF($AD$3="SI",SUM(N58),0)>0),"PEDIR MENOS — sobran "&TEXT(-AA58,"#,##0")&" m; revisar pedidos sin facturar ("&TEXT(SUM(I58:M58)+IF($AD$3="SI",SUM(N58),0),"#,##0")&" m)",IF(Z58>8,"SOBRESTOCK — "&TEXT(Z58,"0.0")&" meses de cobertura","OK — cubierto ("&TEXT(Z58,"0.0")&" meses)")))))) -> OK — cubierto (5.4 meses) | P58: =E58+N(F58)+SUM(G58:M58)+IF($AD$3="SI",SUM(N58),0) -> 436 | X58: =IFERROR(VLOOKUP($A58,Ventas!$A$2:$L$5000,12,FALSE()),"") -> 80.5 | Y58: =IF(X58="","",ROUND(X58*4,0)) -> 322 | Z58: =IF(OR(X58="",X58=0),"",ROUND(P58/X58,1)) -> 5.4 | AA58: =IF(Y58="","",Y58-P58) -> -114 | AB58: =IF(A58="","",IF(COUNTIF($A$8:$A$670,A58)>1,"DUPLICADO","")) | AC58: {=IF(AH58<>"COMPRAR","",IF(MAX(INDEX(Ventas!$G$2:$G$5000,MATCH($A58,Ventas!$A$2:$A$5000,0)),INDEX(Ventas!$H$2:$H$5000,MATCH($A58,Ventas!$A$2:$A$5000,0)),INDEX(Ventas!$I$2:$I$5000,MATCH($A58,Ventas!$A$2:$A$5000,0)),INDEX(Ventas!$J$2:$J$5000,MATCH($A58,Ventas!$A$2:$A$5000,0)))>0.5*AF58*4,"1 mes = "&TEXT(MAX(INDEX(Ventas!$G$2:$G$5000,MATCH($A58,Ventas!$A$2:$A$5000,0)),INDEX(Ventas!$H$2:$H$5000,MATCH($A58,Ventas!$A$2:$A$5000,0)),INDEX(Ventas!$I$2:$I$5000,MATCH($A58,Ventas!$A$2:$A$5000,0)),INDEX(Ventas!$J$2:$J$5000,MATCH($A58,Ventas!$A$2:$A$5000,0)))/(AF58*4),"0%")&" de 4 meses",""))} | AD58: =IF(OR(X58="",X58=0),"",IF(E58+N(F58)<X58*$AD$5,"SÍ — "&TEXT(E58+N(F58),"#,##0")&" m vs "&TEXT(X58*$AD$5,"#,##0")&" m","")) | AE58: {=IF(X58="","",IF(AND(E58=0,AVERAGE(INDEX(Ventas!$C$2:$I$5000,MATCH($A58,Ventas!$A$2:$A$5000,0),0))>0,INDEX(Ventas!$J$2:$J$5000,MATCH($A58,Ventas!$A$2:$A$5000,0))<0.5*AVERAGE(INDEX(Ventas!$C$2:$I$5000,MATCH($A58,Ventas!$A$2:$A$5000,0),0))),"SÍ — stock 0 y Sep cayó (prom Feb-Ago "&TEXT(AVERAGE(INDEX(Ventas!$C$2:$I$5000,MATCH($A58,Ventas!$A$2:$A$5000,0),0)),"#,##0")&")",""))} | AF58: {=IF(X58="","",IF(AE58<>"",MAX(X58,AVERAGE(INDEX(Ventas!$C$2:$I$5000,MATCH($A58,Ventas!$A$2:$A$5000,0),0))),X58))} -> 80.5 | AG58: =IF(AF58="","",ROUND(AF58*4,0)-P58) -> -114 | AH58: =IF(A58="","",IF(AF58="","SIN HISTORIAL",IF(AF58=0,"SIN VENTAS",IF(AG58>0.1*ROUND(AF58*4,0),"COMPRAR",IF(AND(-AG58>0.1*ROUND(AF58*4,0),SUM(I58:M58)+IF($AD$3="SI",SUM(N58),0)>0),"PEDIR MENOS",IF(P58/AF58>8,"SOBRESTOCK","OK")))))) -> OK
A59: 285127-0199 | B59: CAPELLADA | C59: NAPA | D59: CARAMELO d/t | E59: 0 | O59: =IF(A59="","SIN SKU — cargar código para calcular",IF(X59="","SIN HISTORIAL DE VENTAS — artículo nuevo o código distinto en Ventas",IF(X59=0,IF(P59>0,"SIN VENTAS Jun-Sep — no comprar ("&TEXT(P59,"#,##0")&" m disponibles)","SIN VENTAS Jun-Sep — no comprar"),IF(AA59>0.1*Y59,"COMPRAR — faltan "&TEXT(AA59,"#,##0")&" m para 4 meses"&IF(P59-E59>0," (ya contando pedidos)",""),IF(AND(-AA59>0.1*Y59,SUM(I59:M59)+IF($AD$3="SI",SUM(N59),0)>0),"PEDIR MENOS — sobran "&TEXT(-AA59,"#,##0")&" m; revisar pedidos sin facturar ("&TEXT(SUM(I59:M59)+IF($AD$3="SI",SUM(N59),0),"#,##0")&" m)",IF(Z59>8,"SOBRESTOCK — "&TEXT(Z59,"0.0")&" meses de cobertura","OK — cubierto ("&TEXT(Z59,"0.0")&" meses)")))))) -> COMPRAR — faltan 1,522 m para 4 meses | P59: =E59+N(F59)+SUM(G59:M59)+IF($AD$3="SI",SUM(N59),0) -> 0 | Q59: 1040 | R59: 156 | X59: =IFERROR(VLOOKUP($A59,Ventas!$A$2:$L$5000,12,FALSE()),"") -> 380.5 | Y59: =IF(X59="","",ROUND(X59*4,0)) -> 1522 | Z59: =IF(OR(X59="",X59=0),"",ROUND(P59/X59,1)) -> 0 | AA59: =IF(Y59="","",Y59-P59) -> 1522 | AB59: =IF(A59="","",IF(COUNTIF($A$8:$A$670,A59)>1,"DUPLICADO","")) | AC59: {=IF(AH59<>"COMPRAR","",IF(MAX(INDEX(Ventas!$G$2:$G$5000,MATCH($A59,Ventas!$A$2:$A$5000,0)),INDEX(Ventas!$H$2:$H$5000,MATCH($A59,Ventas!$A$2:$A$5000,0)),INDEX(Ventas!$I$2:$I$5000,MATCH($A59,Ventas!$A$2:$A$5000,0)),INDEX(Ventas!$J$2:$J$5000,MATCH($A59,Ventas!$A$2:$A$5000,0)))>0.5*AF59*4,"1 mes = "&TEXT(MAX(INDEX(Ventas!$G$2:$G$5000,MATCH($A59,Ventas!$A$2:$A$5000,0)),INDEX(Ventas!$H$2:$H$5000,MATCH($A59,Ventas!$A$2:$A$5000,0)),INDEX(Ventas!$I$2:$I$5000,MATCH($A59,Ventas!$A$2:$A$5000,0)),INDEX(Ventas!$J$2:$J$5000,MATCH($A59,Ventas!$A$2:$A$5000,0)))/(AF59*4),"0%")&" de 4 meses",""))} | AD59: =IF(OR(X59="",X59=0),"",IF(E59+N(F59)<X59*$AD$5,"SÍ — "&TEXT(E59+N(F59),"#,##0")&" m vs "&TEXT(X59*$AD$5,"#,##0")&" m","")) -> SÍ — 0 m vs 202 m | AE59: {=IF(X59="","",IF(AND(E59=0,AVERAGE(INDEX(Ventas!$C$2:$I$5000,MATCH($A59,Ventas!$A$2:$A$5000,0),0))>0,INDEX(Ventas!$J$2:$J$5000,MATCH($A59,Ventas!$A$2:$A$5000,0))<0.5*AVERAGE(INDEX(Ventas!$C$2:$I$5000,MATCH($A59,Ventas!$A$2:$A$5000,0),0))),"SÍ — stock 0 y Sep cayó (prom Feb-Ago "&TEXT(AVERAGE(INDEX(Ventas!$C$2:$I$5000,MATCH($A59,Ventas!$A$2:$A$5000,0),0)),"#,##0")&")",""))} | AF59: {=IF(X59="","",IF(AE59<>"",MAX(X59,AVERAGE(INDEX(Ventas!$C$2:$I$5000,MATCH($A59,Ventas!$A$2:$A$5000,0),0))),X59))} -> 380.5 | AG59: =IF(AF59="","",ROUND(AF59*4,0)-P59) -> 1522 | AH59: =IF(A59="","",IF(AF59="","SIN HISTORIAL",IF(AF59=0,"SIN VENTAS",IF(AG59>0.1*ROUND(AF59*4,0),"COMPRAR",IF(AND(-AG59>0.1*ROUND(AF59*4,0),SUM(I59:M59)+IF($AD$3="SI",SUM(N59),0)>0),"PEDIR MENOS",IF(P59/AF59>8,"SOBRESTOCK","OK")))))) -> COMPRAR
A60: 285127-0200 | B60: CAPELLADA | C60: NAPA | D60: NUDE d/t | E60: 1519 | O60: =IF(A60="","SIN SKU — cargar código para calcular",IF(X60="","SIN HISTORIAL DE VENTAS — artículo nuevo o código distinto en Ventas",IF(X60=0,IF(P60>0,"SIN VENTAS Jun-Sep — no comprar ("&TEXT(P60,"#,##0")&" m disponibles)","SIN VENTAS Jun-Sep — no comprar"),IF(AA60>0.1*Y60,"COMPRAR — faltan "&TEXT(AA60,"#,##0")&" m para 4 meses"&IF(P60-E60>0," (ya contando pedidos)",""),IF(AND(-AA60>0.1*Y60,SUM(I60:M60)+IF($AD$3="SI",SUM(N60),0)>0),"PEDIR MENOS — sobran "&TEXT(-AA60,"#,##0")&" m; revisar pedidos sin facturar ("&TEXT(SUM(I60:M60)+IF($AD$3="SI",SUM(N60),0),"#,##0")&" m)",IF(Z60>8,"SOBRESTOCK — "&TEXT(Z60,"0.0")&" meses de cobertura","OK — cubierto ("&TEXT(Z60,"0.0")&" meses)")))))) -> SOBRESTOCK — 30.4 meses de cobertura | P60: =E60+N(F60)+SUM(G60:M60)+IF($AD$3="SI",SUM(N60),0) -> 1519 | X60: =IFERROR(VLOOKUP($A60,Ventas!$A$2:$L$5000,12,FALSE()),"") -> 50 | Y60: =IF(X60="","",ROUND(X60*4,0)) -> 200 | Z60: =IF(OR(X60="",X60=0),"",ROUND(P60/X60,1)) -> 30.4 | AA60: =IF(Y60="","",Y60-P60) -> -1319 | AB60: =IF(A60="","",IF(COUNTIF($A$8:$A$670,A60)>1,"DUPLICADO","")) | AC60: {=IF(AH60<>"COMPRAR","",IF(MAX(INDEX(Ventas!$G$2:$G$5000,MATCH($A60,Ventas!$A$2:$A$5000,0)),INDEX(Ventas!$H$2:$H$5000,MATCH($A60,Ventas!$A$2:$A$5000,0)),INDEX(Ventas!$I$2:$I$5000,MATCH($A60,Ventas!$A$2:$A$5000,0)),INDEX(Ventas!$J$2:$J$5000,MATCH($A60,Ventas!$A$2:$A$5000,0)))>0.5*AF60*4,"1 mes = "&TEXT(MAX(INDEX(Ventas!$G$2:$G$5000,MATCH($A60,Ventas!$A$2:$A$5000,0)),INDEX(Ventas!$H$2:$H$5000,MATCH($A60,Ventas!$A$2:$A$5000,0)),INDEX(Ventas!$I$2:$I$5000,MATCH($A60,Ventas!$A$2:$A$5000,0)),INDEX(Ventas!$J$2:$J$5000,MATCH($A60,Ventas!$A$2:$A$5000,0)))/(AF60*4),"0%")&" de 4 meses",""))} | AD60: =IF(OR(X60="",X60=0),"",IF(E60+N(F60)<X60*$AD$5,"SÍ — "&TEXT(E60+N(F60),"#,##0")&" m vs "&TEXT(X60*$AD$5,"#,##0")&" m","")) | AE60: {=IF(X60="","",IF(AND(E60=0,AVERAGE(INDEX(Ventas!$C$2:$I$5000,MATCH($A60,Ventas!$A$2:$A$5000,0),0))>0,INDEX(Ventas!$J$2:$J$5000,MATCH($A60,Ventas!$A$2:$A$5000,0))<0.5*AVERAGE(INDEX(Ventas!$C$2:$I$5000,MATCH($A60,Ventas!$A$2:$A$5000,0),0))),"SÍ — stock 0 y Sep cayó (prom Feb-Ago "&TEXT(AVERAGE(INDEX(Ventas!$C$2:$I$5000,MATCH($A60,Ventas!$A$2:$A$5000,0),0)),"#,##0")&")",""))} | AF60: {=IF(X60="","",IF(AE60<>"",MAX(X60,AVERAGE(INDEX(Ventas!$C$2:$I$5000,MATCH($A60,Ventas!$A$2:$A$5000,0),0))),X60))} -> 50 | AG60: =IF(AF60="","",ROUND(AF60*4,0)-P60) -> -1319 | AH60: =IF(A60="","",IF(AF60="","SIN HISTORIAL",IF(AF60=0,"SIN VENTAS",IF(AG60>0.1*ROUND(AF60*4,0),"COMPRAR",IF(AND(-AG60>0.1*ROUND(AF60*4,0),SUM(I60:M60)+IF($AD$3="SI",SUM(N60),0)>0),"PEDIR MENOS",IF(P60/AF60>8,"SOBRESTOCK","OK")))))) -> SOBRESTOCK
A61: 285127-0198 | B61: CAPELLADA | C61: NAPA | D61: MANTECA | E61: 200 | O61: =IF(A61="","SIN SKU — cargar código para calcular",IF(X61="","SIN HISTORIAL DE VENTAS — artículo nuevo o código distinto en Ventas",IF(X61=0,IF(P61>0,"SIN VENTAS Jun-Sep — no comprar ("&TEXT(P61,"#,##0")&" m disponibles)","SIN VENTAS Jun-Sep — no comprar"),IF(AA61>0.1*Y61,"COMPRAR — faltan "&TEXT(AA61,"#,##0")&" m para 4 meses"&IF(P61-E61>0," (ya contando pedidos)",""),IF(AND(-AA61>0.1*Y61,SUM(I61:M61)+IF($AD$3="SI",SUM(N61),0)>0),"PEDIR MENOS — sobran "&TEXT(-AA61,"#,##0")&" m; revisar pedidos sin facturar ("&TEXT(SUM(I61:M61)+IF($AD$3="SI",SUM(N61),0),"#,##0")&" m)",IF(Z61>8,"SOBRESTOCK — "&TEXT(Z61,"0.0")&" meses de cobertura","OK — cubierto ("&TEXT(Z61,"0.0")&" meses)")))))) -> COMPRAR — faltan 880 m para 4 meses | P61: =E61+N(F61)+SUM(G61:M61)+IF($AD$3="SI",SUM(N61),0) -> 200 | X61: =IFERROR(VLOOKUP($A61,Ventas!$A$2:$L$5000,12,FALSE()),"") -> 270 | Y61: =IF(X61="","",ROUND(X61*4,0)) -> 1080 | Z61: =IF(OR(X61="",X61=0),"",ROUND(P61/X61,1)) -> 0.7 | AA61: =IF(Y61="","",Y61-P61) -> 880 | AB61: =IF(A61="","",IF(COUNTIF($A$8:$A$670,A61)>1,"DUPLICADO","")) | AC61: {=IF(AH61<>"COMPRAR","",IF(MAX(INDEX(Ventas!$G$2:$G$5000,MATCH($A61,Ventas!$A$2:$A$5000,0)),INDEX(Ventas!$H$2:$H$5000,MATCH($A61,Ventas!$A$2:$A$5000,0)),INDEX(Ventas!$I$2:$I$5000,MATCH($A61,Ventas!$A$2:$A$5000,0)),INDEX(Ventas!$J$2:$J$5000,MATCH($A61,Ventas!$A$2:$A$5000,0)))>0.5*AF61*4,"1 mes = "&TEXT(MAX(INDEX(Ventas!$G$2:$G$5000,MATCH($A61,Ventas!$A$2:$A$5000,0)),INDEX(Ventas!$H$2:$H$5000,MATCH($A61,Ventas!$A$2:$A$5000,0)),INDEX(Ventas!$I$2:$I$5000,MATCH($A61,Ventas!$A$2:$A$5000,0)),INDEX(Ventas!$J$2:$J$5000,MATCH($A61,Ventas!$A$2:$A$5000,0)))/(AF61*4),"0%")&" de 4 meses",""))} -> 1 mes = 56% de 4 meses | AD61: =IF(OR(X61="",X61=0),"",IF(E61+N(F61)<X61*$AD$5,"SÍ — "&TEXT(E61+N(F61),"#,##0")&" m vs "&TEXT(X61*$AD$5,"#,##0")&" m","")) | AE61: {=IF(X61="","",IF(AND(E61=0,AVERAGE(INDEX(Ventas!$C$2:$I$5000,MATCH($A61,Ventas!$A$2:$A$5000,0),0))>0,INDEX(Ventas!$J$2:$J$5000,MATCH($A61,Ventas!$A$2:$A$5000,0))<0.5*AVERAGE(INDEX(Ventas!$C$2:$I$5000,MATCH($A61,Ventas!$A$2:$A$5000,0),0))),"SÍ — stock 0 y Sep cayó (prom Feb-Ago "&TEXT(AVERAGE(INDEX(Ventas!$C$2:$I$5000,MATCH($A61,Ventas!$A$2:$A$5000,0),0)),"#,##0")&")",""))} | AF61: {=IF(X61="","",IF(AE61<>"",MAX(X61,AVERAGE(INDEX(Ventas!$C$2:$I$5000,MATCH($A61,Ventas!$A$2:$A$5000,0),0))),X61))} -> 270 | AG61: =IF(AF61="","",ROUND(AF61*4,0)-P61) -> 880 | AH61: =IF(A61="","",IF(AF61="","SIN HISTORIAL",IF(AF61=0,"SIN VENTAS",IF(AG61>0.1*ROUND(AF61*4,0),"COMPRAR",IF(AND(-AG61>0.1*ROUND(AF61*4,0),SUM(I61:M61)+IF($AD$3="SI",SUM(N61),0)>0),"PEDIR MENOS",IF(P61/AF61>8,"SOBRESTOCK","OK")))))) -> COMPRAR
A62: 285127-0069 | B62: CAPELLADA | C62: NAPA | D62: MIEL | E62: 1328 | O62: =IF(A62="","SIN SKU — cargar código para calcular",IF(X62="","SIN HISTORIAL DE VENTAS — artículo nuevo o código distinto en Ventas",IF(X62=0,IF(P62>0,"SIN VENTAS Jun-Sep — no comprar ("&TEXT(P62,"#,##0")&" m disponibles)","SIN VENTAS Jun-Sep — no comprar"),IF(AA62>0.1*Y62,"COMPRAR — faltan "&TEXT(AA62,"#,##0")&" m para 4 meses"&IF(P62-E62>0," (ya contando pedidos)",""),IF(AND(-AA62>0.1*Y62,SUM(I62:M62)+IF($AD$3="SI",SUM(N62),0)>0),"PEDIR MENOS — sobran "&TEXT(-AA62,"#,##0")&" m; revisar pedidos sin facturar ("&TEXT(SUM(I62:M62)+IF($AD$3="SI",SUM(N62),0),"#,##0")&" m)",IF(Z62>8,"SOBRESTOCK — "&TEXT(Z62,"0.0")&" meses de cobertura","OK — cubierto ("&TEXT(Z62,"0.0")&" meses)")))))) -> OK — cubierto (5.7 meses) | P62: =E62+N(F62)+SUM(G62:M62)+IF($AD$3="SI",SUM(N62),0) -> 1328 | X62: =IFERROR(VLOOKUP($A62,Ventas!$A$2:$L$5000,12,FALSE()),"") -> 231.25 | Y62: =IF(X62="","",ROUND(X62*4,0)) -> 925 | Z62: =IF(OR(X62="",X62=0),"",ROUND(P62/X62,1)) -> 5.7 | AA62: =IF(Y62="","",Y62-P62) -> -403 | AB62: =IF(A62="","",IF(COUNTIF($A$8:$A$670,A62)>1,"DUPLICADO","")) | AC62: {=IF(AH62<>"COMPRAR","",IF(MAX(INDEX(Ventas!$G$2:$G$5000,MATCH($A62,Ventas!$A$2:$A$5000,0)),INDEX(Ventas!$H$2:$H$5000,MATCH($A62,Ventas!$A$2:$A$5000,0)),INDEX(Ventas!$I$2:$I$5000,MATCH($A62,Ventas!$A$2:$A$5000,0)),INDEX(Ventas!$J$2:$J$5000,MATCH($A62,Ventas!$A$2:$A$5000,0)))>0.5*AF62*4,"1 mes = "&TEXT(MAX(INDEX(Ventas!$G$2:$G$5000,MATCH($A62,Ventas!$A$2:$A$5000,0)),INDEX(Ventas!$H$2:$H$5000,MATCH($A62,Ventas!$A$2:$A$5000,0)),INDEX(Ventas!$I$2:$I$5000,MATCH($A62,Ventas!$A$2:$A$5000,0)),INDEX(Ventas!$J$2:$J$5000,MATCH($A62,Ventas!$A$2:$A$5000,0)))/(AF62*4),"0%")&" de 4 meses",""))} | AD62: =IF(OR(X62="",X62=0),"",IF(E62+N(F62)<X62*$AD$5,"SÍ — "&TEXT(E62+N(F62),"#,##0")&" m vs "&TEXT(X62*$AD$5,"#,##0")&" m","")) | AE62: {=IF(X62="","",IF(AND(E62=0,AVERAGE(INDEX(Ventas!$C$2:$I$5000,MATCH($A62,Ventas!$A$2:$A$5000,0),0))>0,INDEX(Ventas!$J$2:$J$5000,MATCH($A62,Ventas!$A$2:$A$5000,0))<0.5*AVERAGE(INDEX(Ventas!$C$2:$I$5000,MATCH($A62,Ventas!$A$2:$A$5000,0),0))),"SÍ — stock 0 y Sep cayó (prom Feb-Ago "&TEXT(AVERAGE(INDEX(Ventas!$C$2:$I$5000,MATCH($A62,Ventas!$A$2:$A$5000,0),0)),"#,##0")&")",""))} | AF62: {=IF(X62="","",IF(AE62<>"",MAX(X62,AVERAGE(INDEX(Ventas!$C$2:$I$5000,MATCH($A62,Ventas!$A$2:$A$5000,0),0))),X62))} -> 231.25 | AG62: =IF(AF62="","",ROUND(AF62*4,0)-P62) -> -403 | AH62: =IF(A62="","",IF(AF62="","SIN HISTORIAL",IF(AF62=0,"SIN VENTAS",IF(AG62>0.1*ROUND(AF62*4,0),"COMPRAR",IF(AND(-AG62>0.1*ROUND(AF62*4,0),SUM(I62:M62)+IF($AD$3="SI",SUM(N62),0)>0),"PEDIR MENOS",IF(P62/AF62>8,"SOBRESTOCK","OK")))))) -> OK
A63: 285127-0001 | B63: CAPELLADA | C63: NAPA | D63: AMARILLO | E63: 681 | O63: =IF(A63="","SIN SKU — cargar código para calcular",IF(X63="","SIN HISTORIAL DE VENTAS — artículo nuevo o código distinto en Ventas",IF(X63=0,IF(P63>0,"SIN VENTAS Jun-Sep — no comprar ("&TEXT(P63,"#,##0")&" m disponibles)","SIN VENTAS Jun-Sep — no comprar"),IF(AA63>0.1*Y63,"COMPRAR — faltan "&TEXT(AA63,"#,##0")&" m para 4 meses"&IF(P63-E63>0," (ya contando pedidos)",""),IF(AND(-AA63>0.1*Y63,SUM(I63:M63)+IF($AD$3="SI",SUM(N63),0)>0),"PEDIR MENOS — sobran "&TEXT(-AA63,"#,##0")&" m; revisar pedidos sin facturar ("&TEXT(SUM(I63:M63)+IF($AD$3="SI",SUM(N63),0),"#,##0")&" m)",IF(Z63>8,"SOBRESTOCK — "&TEXT(Z63,"0.0")&" meses de cobertura","OK — cubierto ("&TEXT(Z63,"0.0")&" meses)")))))) -> SOBRESTOCK — 68.1 meses de cobertura | P63: =E63+N(F63)+SUM(G63:M63)+IF($AD$3="SI",SUM(N63),0) -> 681 | X63: =IFERROR(VLOOKUP($A63,Ventas!$A$2:$L$5000,12,FALSE()),"") -> 10 | Y63: =IF(X63="","",ROUND(X63*4,0)) -> 40 | Z63: =IF(OR(X63="",X63=0),"",ROUND(P63/X63,1)) -> 68.1 | AA63: =IF(Y63="","",Y63-P63) -> -641 | AB63: =IF(A63="","",IF(COUNTIF($A$8:$A$670,A63)>1,"DUPLICADO","")) | AC63: {=IF(AH63<>"COMPRAR","",IF(MAX(INDEX(Ventas!$G$2:$G$5000,MATCH($A63,Ventas!$A$2:$A$5000,0)),INDEX(Ventas!$H$2:$H$5000,MATCH($A63,Ventas!$A$2:$A$5000,0)),INDEX(Ventas!$I$2:$I$5000,MATCH($A63,Ventas!$A$2:$A$5000,0)),INDEX(Ventas!$J$2:$J$5000,MATCH($A63,Ventas!$A$2:$A$5000,0)))>0.5*AF63*4,"1 mes = "&TEXT(MAX(INDEX(Ventas!$G$2:$G$5000,MATCH($A63,Ventas!$A$2:$A$5000,0)),INDEX(Ventas!$H$2:$H$5000,MATCH($A63,Ventas!$A$2:$A$5000,0)),INDEX(Ventas!$I$2:$I$5000,MATCH($A63,Ventas!$A$2:$A$5000,0)),INDEX(Ventas!$J$2:$J$5000,MATCH($A63,Ventas!$A$2:$A$5000,0)))/(AF63*4),"0%")&" de 4 meses",""))} | AD63: =IF(OR(X63="",X63=0),"",IF(E63+N(F63)<X63*$AD$5,"SÍ — "&TEXT(E63+N(F63),"#,##0")&" m vs "&TEXT(X63*$AD$5,"#,##0")&" m","")) | AE63: {=IF(X63="","",IF(AND(E63=0,AVERAGE(INDEX(Ventas!$C$2:$I$5000,MATCH($A63,Ventas!$A$2:$A$5000,0),0))>0,INDEX(Ventas!$J$2:$J$5000,MATCH($A63,Ventas!$A$2:$A$5000,0))<0.5*AVERAGE(INDEX(Ventas!$C$2:$I$5000,MATCH($A63,Ventas!$A$2:$A$5000,0),0))),"SÍ — stock 0 y Sep cayó (prom Feb-Ago "&TEXT(AVERAGE(INDEX(Ventas!$C$2:$I$5000,MATCH($A63,Ventas!$A$2:$A$5000,0),0)),"#,##0")&")",""))} | AF63: {=IF(X63="","",IF(AE63<>"",MAX(X63,AVERAGE(INDEX(Ventas!$C$2:$I$5000,MATCH($A63,Ventas!$A$2:$A$5000,0),0))),X63))} -> 10 | AG63: =IF(AF63="","",ROUND(AF63*4,0)-P63) -> -641 | AH63: =IF(A63="","",IF(AF63="","SIN HISTORIAL",IF(AF63=0,"SIN VENTAS",IF(AG63>0.1*ROUND(AF63*4,0),"COMPRAR",IF(AND(-AG63>0.1*ROUND(AF63*4,0),SUM(I63:M63)+IF($AD$3="SI",SUM(N63),0)>0),"PEDIR MENOS",IF(P63/AF63>8,"SOBRESTOCK","OK")))))) -> SOBRESTOCK
A64: 285127-0129 | B64: CAPELLADA | C64: NAPA | D64: OCRE | E64: 518 | O64: =IF(A64="","SIN SKU — cargar código para calcular",IF(X64="","SIN HISTORIAL DE VENTAS — artículo nuevo o código distinto en Ventas",IF(X64=0,IF(P64>0,"SIN VENTAS Jun-Sep — no comprar ("&TEXT(P64,"#,##0")&" m disponibles)","SIN VENTAS Jun-Sep — no comprar"),IF(AA64>0.1*Y64,"COMPRAR — faltan "&TEXT(AA64,"#,##0")&" m para 4 meses"&IF(P64-E64>0," (ya contando pedidos)",""),IF(AND(-AA64>0.1*Y64,SUM(I64:M64)+IF($AD$3="SI",SUM(N64),0)>0),"PEDIR MENOS — sobran "&TEXT(-AA64,"#,##0")&" m; revisar pedidos sin facturar ("&TEXT(SUM(I64:M64)+IF($AD$3="SI",SUM(N64),0),"#,##0")&" m)",IF(Z64>8,"SOBRESTOCK — "&TEXT(Z64,"0.0")&" meses de cobertura","OK — cubierto ("&TEXT(Z64,"0.0")&" meses)")))))) -> SIN VENTAS Jun-Sep — no comprar (518 m disponibles) | P64: =E64+N(F64)+SUM(G64:M64)+IF($AD$3="SI",SUM(N64),0) -> 518 | X64: =IFERROR(VLOOKUP($A64,Ventas!$A$2:$L$5000,12,FALSE()),"") -> 0 | Y64: =IF(X64="","",ROUND(X64*4,0)) -> 0 | Z64: =IF(OR(X64="",X64=0),"",ROUND(P64/X64,1)) | AA64: =IF(Y64="","",Y64-P64) -> -518 | AB64: =IF(A64="","",IF(COUNTIF($A$8:$A$670,A64)>1,"DUPLICADO","")) | AC64: {=IF(AH64<>"COMPRAR","",IF(MAX(INDEX(Ventas!$G$2:$G$5000,MATCH($A64,Ventas!$A$2:$A$5000,0)),INDEX(Ventas!$H$2:$H$5000,MATCH($A64,Ventas!$A$2:$A$5000,0)),INDEX(Ventas!$I$2:$I$5000,MATCH($A64,Ventas!$A$2:$A$5000,0)),INDEX(Ventas!$J$2:$J$5000,MATCH($A64,Ventas!$A$2:$A$5000,0)))>0.5*AF64*4,"1 mes = "&TEXT(MAX(INDEX(Ventas!$G$2:$G$5000,MATCH($A64,Ventas!$A$2:$A$5000,0)),INDEX(Ventas!$H$2:$H$5000,MATCH($A64,Ventas!$A$2:$A$5000,0)),INDEX(Ventas!$I$2:$I$5000,MATCH($A64,Ventas!$A$2:$A$5000,0)),INDEX(Ventas!$J$2:$J$5000,MATCH($A64,Ventas!$A$2:$A$5000,0)))/(AF64*4),"0%")&" de 4 meses",""))} | AD64: =IF(OR(X64="",X64=0),"",IF(E64+N(F64)<X64*$AD$5,"SÍ — "&TEXT(E64+N(F64),"#,##0")&" m vs "&TEXT(X64*$AD$5,"#,##0")&" m","")) | AE64: {=IF(X64="","",IF(AND(E64=0,AVERAGE(INDEX(Ventas!$C$2:$I$5000,MATCH($A64,Ventas!$A$2:$A$5000,0),0))>0,INDEX(Ventas!$J$2:$J$5000,MATCH($A64,Ventas!$A$2:$A$5000,0))<0.5*AVERAGE(INDEX(Ventas!$C$2:$I$5000,MATCH($A64,Ventas!$A$2:$A$5000,0),0))),"SÍ — stock 0 y Sep cayó (prom Feb-Ago "&TEXT(AVERAGE(INDEX(Ventas!$C$2:$I$5000,MATCH($A64,Ventas!$A$2:$A$5000,0),0)),"#,##0")&")",""))} | AF64: {=IF(X64="","",IF(AE64<>"",MAX(X64,AVERAGE(INDEX(Ventas!$C$2:$I$5000,MATCH($A64,Ventas!$A$2:$A$5000,0),0))),X64))} -> 0 | AG64: =IF(AF64="","",ROUND(AF64*4,0)-P64) -> -518 | AH64: =IF(A64="","",IF(AF64="","SIN HISTORIAL",IF(AF64=0,"SIN VENTAS",IF(AG64>0.1*ROUND(AF64*4,0),"COMPRAR",IF(AND(-AG64>0.1*ROUND(AF64*4,0),SUM(I64:M64)+IF($AD$3="SI",SUM(N64),0)>0),"PEDIR MENOS",IF(P64/AF64>8,"SOBRESTOCK","OK")))))) -> SIN VENTAS
A65: 285127-0009 | B65: CAPELLADA | C65: NAPA | D65: CELESTE | E65: 40 | O65: =IF(A65="","SIN SKU — cargar código para calcular",IF(X65="","SIN HISTORIAL DE VENTAS — artículo nuevo o código distinto en Ventas",IF(X65=0,IF(P65>0,"SIN VENTAS Jun-Sep — no comprar ("&TEXT(P65,"#,##0")&" m disponibles)","SIN VENTAS Jun-Sep — no comprar"),IF(AA65>0.1*Y65,"COMPRAR — faltan "&TEXT(AA65,"#,##0")&" m para 4 meses"&IF(P65-E65>0," (ya contando pedidos)",""),IF(AND(-AA65>0.1*Y65,SUM(I65:M65)+IF($AD$3="SI",SUM(N65),0)>0),"PEDIR MENOS — sobran "&TEXT(-AA65,"#,##0")&" m; revisar pedidos sin facturar ("&TEXT(SUM(I65:M65)+IF($AD$3="SI",SUM(N65),0),"#,##0")&" m)",IF(Z65>8,"SOBRESTOCK — "&TEXT(Z65,"0.0")&" meses de cobertura","OK — cubierto ("&TEXT(Z65,"0.0")&" meses)")))))) -> COMPRAR — faltan 120 m para 4 meses | P65: =E65+N(F65)+SUM(G65:M65)+IF($AD$3="SI",SUM(N65),0) -> 40 | Q65: Ingresaron 594 mts el 17/06/2025 y sigue habiendo mts de la misma partida. | X65: =IFERROR(VLOOKUP($A65,Ventas!$A$2:$L$5000,12,FALSE()),"") -> 40 | Y65: =IF(X65="","",ROUND(X65*4,0)) -> 160 | Z65: =IF(OR(X65="",X65=0),"",ROUND(P65/X65,1)) -> 1 | AA65: =IF(Y65="","",Y65-P65) -> 120 | AB65: =IF(A65="","",IF(COUNTIF($A$8:$A$670,A65)>1,"DUPLICADO","")) | AC65: {=IF(AH65<>"COMPRAR","",IF(MAX(INDEX(Ventas!$G$2:$G$5000,MATCH($A65,Ventas!$A$2:$A$5000,0)),INDEX(Ventas!$H$2:$H$5000,MATCH($A65,Ventas!$A$2:$A$5000,0)),INDEX(Ventas!$I$2:$I$5000,MATCH($A65,Ventas!$A$2:$A$5000,0)),INDEX(Ventas!$J$2:$J$5000,MATCH($A65,Ventas!$A$2:$A$5000,0)))>0.5*AF65*4,"1 mes = "&TEXT(MAX(INDEX(Ventas!$G$2:$G$5000,MATCH($A65,Ventas!$A$2:$A$5000,0)),INDEX(Ventas!$H$2:$H$5000,MATCH($A65,Ventas!$A$2:$A$5000,0)),INDEX(Ventas!$I$2:$I$5000,MATCH($A65,Ventas!$A$2:$A$5000,0)),INDEX(Ventas!$J$2:$J$5000,MATCH($A65,Ventas!$A$2:$A$5000,0)))/(AF65*4),"0%")&" de 4 meses",""))} | AD65: =IF(OR(X65="",X65=0),"",IF(E65+N(F65)<X65*$AD$5,"SÍ — "&TEXT(E65+N(F65),"#,##0")&" m vs "&TEXT(X65*$AD$5,"#,##0")&" m","")) | AE65: {=IF(X65="","",IF(AND(E65=0,AVERAGE(INDEX(Ventas!$C$2:$I$5000,MATCH($A65,Ventas!$A$2:$A$5000,0),0))>0,INDEX(Ventas!$J$2:$J$5000,MATCH($A65,Ventas!$A$2:$A$5000,0))<0.5*AVERAGE(INDEX(Ventas!$C$2:$I$5000,MATCH($A65,Ventas!$A$2:$A$5000,0),0))),"SÍ — stock 0 y Sep cayó (prom Feb-Ago "&TEXT(AVERAGE(INDEX(Ventas!$C$2:$I$5000,MATCH($A65,Ventas!$A$2:$A$5000,0),0)),"#,##0")&")",""))} | AF65: {=IF(X65="","",IF(AE65<>"",MAX(X65,AVERAGE(INDEX(Ventas!$C$2:$I$5000,MATCH($A65,Ventas!$A$2:$A$5000,0),0))),X65))} -> 40 | AG65: =IF(AF65="","",ROUND(AF65*4,0)-P65) -> 120 | AH65: =IF(A65="","",IF(AF65="","SIN HISTORIAL",IF(AF65=0,"SIN VENTAS",IF(AG65>0.1*ROUND(AF65*4,0),"COMPRAR",IF(AND(-AG65>0.1*ROUND(AF65*4,0),SUM(I65:M65)+IF($AD$3="SI",SUM(N65),0)>0),"PEDIR MENOS",IF(P65/AF65>8,"SOBRESTOCK","OK")))))) -> COMPRAR
A66: 285127-0022 | B66: CAPELLADA | C66: NAPA | D66: ROSA | E66: 368 | O66: =IF(A66="","SIN SKU — cargar código para calcular",IF(X66="","SIN HISTORIAL DE VENTAS — artículo nuevo o código distinto en Ventas",IF(X66=0,IF(P66>0,"SIN VENTAS Jun-Sep — no comprar ("&TEXT(P66,"#,##0")&" m disponibles)","SIN VENTAS Jun-Sep — no comprar"),IF(AA66>0.1*Y66,"COMPRAR — faltan "&TEXT(AA66,"#,##0")&" m para 4 meses"&IF(P66-E66>0," (ya contando pedidos)",""),IF(AND(-AA66>0.1*Y66,SUM(I66:M66)+IF($AD$3="SI",SUM(N66),0)>0),"PEDIR MENOS — sobran "&TEXT(-AA66,"#,##0")&" m; revisar pedidos sin facturar ("&TEXT(SUM(I66:M66)+IF($AD$3="SI",SUM(N66),0),"#,##0")&" m)",IF(Z66>8,"SOBRESTOCK — "&TEXT(Z66,"0.0")&" meses de cobertura","OK — cubierto ("&TEXT(Z66,"0.0")&" meses)")))))) -> SOBRESTOCK — 12.3 meses de cobertura | P66: =E66+N(F66)+SUM(G66:M66)+IF($AD$3="SI",SUM(N66),0) -> 368 | X66: =IFERROR(VLOOKUP($A66,Ventas!$A$2:$L$5000,12,FALSE()),"") -> 30 | Y66: =IF(X66="","",ROUND(X66*4,0)) -> 120 | Z66: =IF(OR(X66="",X66=0),"",ROUND(P66/X66,1)) -> 12.3 | AA66: =IF(Y66="","",Y66-P66) -> -248 | AB66: =IF(A66="","",IF(COUNTIF($A$8:$A$670,A66)>1,"DUPLICADO","")) | AC66: {=IF(AH66<>"COMPRAR","",IF(MAX(INDEX(Ventas!$G$2:$G$5000,MATCH($A66,Ventas!$A$2:$A$5000,0)),INDEX(Ventas!$H$2:$H$5000,MATCH($A66,Ventas!$A$2:$A$5000,0)),INDEX(Ventas!$I$2:$I$5000,MATCH($A66,Ventas!$A$2:$A$5000,0)),INDEX(Ventas!$J$2:$J$5000,MATCH($A66,Ventas!$A$2:$A$5000,0)))>0.5*AF66*4,"1 mes = "&TEXT(MAX(INDEX(Ventas!$G$2:$G$5000,MATCH($A66,Ventas!$A$2:$A$5000,0)),INDEX(Ventas!$H$2:$H$5000,MATCH($A66,Ventas!$A$2:$A$5000,0)),INDEX(Ventas!$I$2:$I$5000,MATCH($A66,Ventas!$A$2:$A$5000,0)),INDEX(Ventas!$J$2:$J$5000,MATCH($A66,Ventas!$A$2:$A$5000,0)))/(AF66*4),"0%")&" de 4 meses",""))} | AD66: =IF(OR(X66="",X66=0),"",IF(E66+N(F66)<X66*$AD$5,"SÍ — "&TEXT(E66+N(F66),"#,##0")&" m vs "&TEXT(X66*$AD$5,"#,##0")&" m","")) | AE66: {=IF(X66="","",IF(AND(E66=0,AVERAGE(INDEX(Ventas!$C$2:$I$5000,MATCH($A66,Ventas!$A$2:$A$5000,0),0))>0,INDEX(Ventas!$J$2:$J$5000,MATCH($A66,Ventas!$A$2:$A$5000,0))<0.5*AVERAGE(INDEX(Ventas!$C$2:$I$5000,MATCH($A66,Ventas!$A$2:$A$5000,0),0))),"SÍ — stock 0 y Sep cayó (prom Feb-Ago "&TEXT(AVERAGE(INDEX(Ventas!$C$2:$I$5000,MATCH($A66,Ventas!$A$2:$A$5000,0),0)),"#,##0")&")",""))} | AF66: {=IF(X66="","",IF(AE66<>"",MAX(X66,AVERAGE(INDEX(Ventas!$C$2:$I$5000,MATCH($A66,Ventas!$A$2:$A$5000,0),0))),X66))} -> 30 | AG66: =IF(AF66="","",ROUND(AF66*4,0)-P66) -> -248 | AH66: =IF(A66="","",IF(AF66="","SIN HISTORIAL",IF(AF66=0,"SIN VENTAS",IF(AG66>0.1*ROUND(AF66*4,0),"COMPRAR",IF(AND(-AG66>0.1*ROUND(AF66*4,0),SUM(I66:M66)+IF($AD$3="SI",SUM(N66),0)>0),"PEDIR MENOS",IF(P66/AF66>8,"SOBRESTOCK","OK")))))) -> SOBRESTOCK
A67: 285127-0003 | B67: CAPELLADA | C67: NAPA | D67: BEIGE | E67: 0 | L67: 800 | O67: =IF(A67="","SIN SKU — cargar código para calcular",IF(X67="","SIN HISTORIAL DE VENTAS — artículo nuevo o código distinto en Ventas",IF(X67=0,IF(P67>0,"SIN VENTAS Jun-Sep — no comprar ("&TEXT(P67,"#,##0")&" m disponibles)","SIN VENTAS Jun-Sep — no comprar"),IF(AA67>0.1*Y67,"COMPRAR — faltan "&TEXT(AA67,"#,##0")&" m para 4 meses"&IF(P67-E67>0," (ya contando pedidos)",""),IF(AND(-AA67>0.1*Y67,SUM(I67:M67)+IF($AD$3="SI",SUM(N67),0)>0),"PEDIR MENOS — sobran "&TEXT(-AA67,"#,##0")&" m; revisar pedidos sin facturar ("&TEXT(SUM(I67:M67)+IF($AD$3="SI",SUM(N67),0),"#,##0")&" m)",IF(Z67>8,"SOBRESTOCK — "&TEXT(Z67,"0.0")&" meses de cobertura","OK — cubierto ("&TEXT(Z67,"0.0")&" meses)")))))) -> COMPRAR — faltan 271 m para 4 meses (ya contando pedidos) | P67: =E67+N(F67)+SUM(G67:M67)+IF($AD$3="SI",SUM(N67),0) -> 800 | X67: =IFERROR(VLOOKUP($A67,Ventas!$A$2:$L$5000,12,FALSE()),"") -> 267.75 | Y67: =IF(X67="","",ROUND(X67*4,0)) -> 1071 | Z67: =IF(OR(X67="",X67=0),"",ROUND(P67/X67,1)) -> 3 | AA67: =IF(Y67="","",Y67-P67) -> 271 | AB67: =IF(A67="","",IF(COUNTIF($A$8:$A$670,A67)>1,"DUPLICADO","")) | AC67: {=IF(AH67<>"COMPRAR","",IF(MAX(INDEX(Ventas!$G$2:$G$5000,MATCH($A67,Ventas!$A$2:$A$5000,0)),INDEX(Ventas!$H$2:$H$5000,MATCH($A67,Ventas!$A$2:$A$5000,0)),INDEX(Ventas!$I$2:$I$5000,MATCH($A67,Ventas!$A$2:$A$5000,0)),INDEX(Ventas!$J$2:$J$5000,MATCH($A67,Ventas!$A$2:$A$5000,0)))>0.5*AF67*4,"1 mes = "&TEXT(MAX(INDEX(Ventas!$G$2:$G$5000,MATCH($A67,Ventas!$A$2:$A$5000,0)),INDEX(Ventas!$H$2:$H$5000,MATCH($A67,Ventas!$A$2:$A$5000,0)),INDEX(Ventas!$I$2:$I$5000,MATCH($A67,Ventas!$A$2:$A$5000,0)),INDEX(Ventas!$J$2:$J$5000,MATCH($A67,Ventas!$A$2:$A$5000,0)))/(AF67*4),"0%")&" de 4 meses",""))} | AD67: =IF(OR(X67="",X67=0),"",IF(E67+N(F67)<X67*$AD$5,"SÍ — "&TEXT(E67+N(F67),"#,##0")&" m vs "&TEXT(X67*$AD$5,"#,##0")&" m","")) -> SÍ — 0 m vs 142 m | AE67: {=IF(X67="","",IF(AND(E67=0,AVERAGE(INDEX(Ventas!$C$2:$I$5000,MATCH($A67,Ventas!$A$2:$A$5000,0),0))>0,INDEX(Ventas!$J$2:$J$5000,MATCH($A67,Ventas!$A$2:$A$5000,0))<0.5*AVERAGE(INDEX(Ventas!$C$2:$I$5000,MATCH($A67,Ventas!$A$2:$A$5000,0),0))),"SÍ — stock 0 y Sep cayó (prom Feb-Ago "&TEXT(AVERAGE(INDEX(Ventas!$C$2:$I$5000,MATCH($A67,Ventas!$A$2:$A$5000,0),0)),"#,##0")&")",""))} | AF67: {=IF(X67="","",IF(AE67<>"",MAX(X67,AVERAGE(INDEX(Ventas!$C$2:$I$5000,MATCH($A67,Ventas!$A$2:$A$5000,0),0))),X67))} -> 267.75 | AG67: =IF(AF67="","",ROUND(AF67*4,0)-P67) -> 271 | AH67: =IF(A67="","",IF(AF67="","SIN HISTORIAL",IF(AF67=0,"SIN VENTAS",IF(AG67>0.1*ROUND(AF67*4,0),"COMPRAR",IF(AND(-AG67>0.1*ROUND(AF67*4,0),SUM(I67:M67)+IF($AD$3="SI",SUM(N67),0)>0),"PEDIR MENOS",IF(P67/AF67>8,"SOBRESTOCK","OK")))))) -> COMPRAR
A68: 285127-0045 | B68: CAPELLADA | C68: NAPA | D68: GRIS | E68: 1037 | O68: =IF(A68="","SIN SKU — cargar código para calcular",IF(X68="","SIN HISTORIAL DE VENTAS — artículo nuevo o código distinto en Ventas",IF(X68=0,IF(P68>0,"SIN VENTAS Jun-Sep — no comprar ("&TEXT(P68,"#,##0")&" m disponibles)","SIN VENTAS Jun-Sep — no comprar"),IF(AA68>0.1*Y68,"COMPRAR — faltan "&TEXT(AA68,"#,##0")&" m para 4 meses"&IF(P68-E68>0," (ya contando pedidos)",""),IF(AND(-AA68>0.1*Y68,SUM(I68:M68)+IF($AD$3="SI",SUM(N68),0)>0),"PEDIR MENOS — sobran "&TEXT(-AA68,"#,##0")&" m; revisar pedidos sin facturar ("&TEXT(SUM(I68:M68)+IF($AD$3="SI",SUM(N68),0),"#,##0")&" m)",IF(Z68>8,"SOBRESTOCK — "&TEXT(Z68,"0.0")&" meses de cobertura","OK — cubierto ("&TEXT(Z68,"0.0")&" meses)")))))) -> SOBRESTOCK — 103.7 meses de cobertura | P68: =E68+N(F68)+SUM(G68:M68)+IF($AD$3="SI",SUM(N68),0) -> 1037 | X68: =IFERROR(VLOOKUP($A68,Ventas!$A$2:$L$5000,12,FALSE()),"") -> 10 | Y68: =IF(X68="","",ROUND(X68*4,0)) -> 40 | Z68: =IF(OR(X68="",X68=0),"",ROUND(P68/X68,1)) -> 103.7 | AA68: =IF(Y68="","",Y68-P68) -> -997 | AB68: =IF(A68="","",IF(COUNTIF($A$8:$A$670,A68)>1,"DUPLICADO","")) | AC68: {=IF(AH68<>"COMPRAR","",IF(MAX(INDEX(Ventas!$G$2:$G$5000,MATCH($A68,Ventas!$A$2:$A$5000,0)),INDEX(Ventas!$H$2:$H$5000,MATCH($A68,Ventas!$A$2:$A$5000,0)),INDEX(Ventas!$I$2:$I$5000,MATCH($A68,Ventas!$A$2:$A$5000,0)),INDEX(Ventas!$J$2:$J$5000,MATCH($A68,Ventas!$A$2:$A$5000,0)))>0.5*AF68*4,"1 mes = "&TEXT(MAX(INDEX(Ventas!$G$2:$G$5000,MATCH($A68,Ventas!$A$2:$A$5000,0)),INDEX(Ventas!$H$2:$H$5000,MATCH($A68,Ventas!$A$2:$A$5000,0)),INDEX(Ventas!$I$2:$I$5000,MATCH($A68,Ventas!$A$2:$A$5000,0)),INDEX(Ventas!$J$2:$J$5000,MATCH($A68,Ventas!$A$2:$A$5000,0)))/(AF68*4),"0%")&" de 4 meses",""))} | AD68: =IF(OR(X68="",X68=0),"",IF(E68+N(F68)<X68*$AD$5,"SÍ — "&TEXT(E68+N(F68),"#,##0")&" m vs "&TEXT(X68*$AD$5,"#,##0")&" m","")) | AE68: {=IF(X68="","",IF(AND(E68=0,AVERAGE(INDEX(Ventas!$C$2:$I$5000,MATCH($A68,Ventas!$A$2:$A$5000,0),0))>0,INDEX(Ventas!$J$2:$J$5000,MATCH($A68,Ventas!$A$2:$A$5000,0))<0.5*AVERAGE(INDEX(Ventas!$C$2:$I$5000,MATCH($A68,Ventas!$A$2:$A$5000,0),0))),"SÍ — stock 0 y Sep cayó (prom Feb-Ago "&TEXT(AVERAGE(INDEX(Ventas!$C$2:$I$5000,MATCH($A68,Ventas!$A$2:$A$5000,0),0)),"#,##0")&")",""))} | AF68: {=IF(X68="","",IF(AE68<>"",MAX(X68,AVERAGE(INDEX(Ventas!$C$2:$I$5000,MATCH($A68,Ventas!$A$2:$A$5000,0),0))),X68))} -> 10 | AG68: =IF(AF68="","",ROUND(AF68*4,0)-P68) -> -997 | AH68: =IF(A68="","",IF(AF68="","SIN HISTORIAL",IF(AF68=0,"SIN VENTAS",IF(AG68>0.1*ROUND(AF68*4,0),"COMPRAR",IF(AND(-AG68>0.1*ROUND(AF68*4,0),SUM(I68:M68)+IF($AD$3="SI",SUM(N68),0)>0),"PEDIR MENOS",IF(P68/AF68>8,"SOBRESTOCK","OK")))))) -> SOBRESTOCK
A69: 285127-0018 | B69: CAPELLADA | C69: NAPA | D69: VERDE MUSGO | E69: 1200 | O69: =IF(A69="","SIN SKU — cargar código para calcular",IF(X69="","SIN HISTORIAL DE VENTAS — artículo nuevo o código distinto en Ventas",IF(X69=0,IF(P69>0,"SIN VENTAS Jun-Sep — no comprar ("&TEXT(P69,"#,##0")&" m disponibles)","SIN VENTAS Jun-Sep — no comprar"),IF(AA69>0.1*Y69,"COMPRAR — faltan "&TEXT(AA69,"#,##0")&" m para 4 meses"&IF(P69-E69>0," (ya contando pedidos)",""),IF(AND(-AA69>0.1*Y69,SUM(I69:M69)+IF($AD$3="SI",SUM(N69),0)>0),"PEDIR MENOS — sobran "&TEXT(-AA69,"#,##0")&" m; revisar pedidos sin facturar ("&TEXT(SUM(I69:M69)+IF($AD$3="SI",SUM(N69),0),"#,##0")&" m)",IF(Z69>8,"SOBRESTOCK — "&TEXT(Z69,"0.0")&" meses de cobertura","OK — cubierto ("&TEXT(Z69,"0.0")&" meses)")))))) -> SOBRESTOCK — 15.0 meses de cobertura | P69: =E69+N(F69)+SUM(G69:M69)+IF($AD$3="SI",SUM(N69),0) -> 1200 | X69: =IFERROR(VLOOKUP($A69,Ventas!$A$2:$L$5000,12,FALSE()),"") -> 80 | Y69: =IF(X69="","",ROUND(X69*4,0)) -> 320 | Z69: =IF(OR(X69="",X69=0),"",ROUND(P69/X69,1)) -> 15 | AA69: =IF(Y69="","",Y69-P69) -> -880 | AB69: =IF(A69="","",IF(COUNTIF($A$8:$A$670,A69)>1,"DUPLICADO","")) | AC69: {=IF(AH69<>"COMPRAR","",IF(MAX(INDEX(Ventas!$G$2:$G$5000,MATCH($A69,Ventas!$A$2:$A$5000,0)),INDEX(Ventas!$H$2:$H$5000,MATCH($A69,Ventas!$A$2:$A$5000,0)),INDEX(Ventas!$I$2:$I$5000,MATCH($A69,Ventas!$A$2:$A$5000,0)),INDEX(Ventas!$J$2:$J$5000,MATCH($A69,Ventas!$A$2:$A$5000,0)))>0.5*AF69*4,"1 mes = "&TEXT(MAX(INDEX(Ventas!$G$2:$G$5000,MATCH($A69,Ventas!$A$2:$A$5000,0)),INDEX(Ventas!$H$2:$H$5000,MATCH($A69,Ventas!$A$2:$A$5000,0)),INDEX(Ventas!$I$2:$I$5000,MATCH($A69,Ventas!$A$2:$A$5000,0)),INDEX(Ventas!$J$2:$J$5000,MATCH($A69,Ventas!$A$2:$A$5000,0)))/(AF69*4),"0%")&" de 4 meses",""))} | AD69: =IF(OR(X69="",X69=0),"",IF(E69+N(F69)<X69*$AD$5,"SÍ — "&TEXT(E69+N(F69),"#,##0")&" m vs "&TEXT(X69*$AD$5,"#,##0")&" m","")) | AE69: {=IF(X69="","",IF(AND(E69=0,AVERAGE(INDEX(Ventas!$C$2:$I$5000,MATCH($A69,Ventas!$A$2:$A$5000,0),0))>0,INDEX(Ventas!$J$2:$J$5000,MATCH($A69,Ventas!$A$2:$A$5000,0))<0.5*AVERAGE(INDEX(Ventas!$C$2:$I$5000,MATCH($A69,Ventas!$A$2:$A$5000,0),0))),"SÍ — stock 0 y Sep cayó (prom Feb-Ago "&TEXT(AVERAGE(INDEX(Ventas!$C$2:$I$5000,MATCH($A69,Ventas!$A$2:$A$5000,0),0)),"#,##0")&")",""))} | AF69: {=IF(X69="","",IF(AE69<>"",MAX(X69,AVERAGE(INDEX(Ventas!$C$2:$I$5000,MATCH($A69,Ventas!$A$2:$A$5000,0),0))),X69))} -> 80 | AG69: =IF(AF69="","",ROUND(AF69*4,0)-P69) -> -880 | AH69: =IF(A69="","",IF(AF69="","SIN HISTORIAL",IF(AF69=0,"SIN VENTAS",IF(AG69>0.1*ROUND(AF69*4,0),"COMPRAR",IF(AND(-AG69>0.1*ROUND(AF69*4,0),SUM(I69:M69)+IF($AD$3="SI",SUM(N69),0)>0),"PEDIR MENOS",IF(P69/AF69>8,"SOBRESTOCK","OK")))))) -> SOBRESTOCK
A70: 285127-0010 | B70: CAPELLADA | C70: NAPA | D70: CHOCOLATE | E70: 1275 | K70: 2000 | L70: 1000 | O70: =IF(A70="","SIN SKU — cargar código para calcular",IF(X70="","SIN HISTORIAL DE VENTAS — artículo nuevo o código distinto en Ventas",IF(X70=0,IF(P70>0,"SIN VENTAS Jun-Sep — no comprar ("&TEXT(P70,"#,##0")&" m disponibles)","SIN VENTAS Jun-Sep — no comprar"),IF(AA70>0.1*Y70,"COMPRAR — faltan "&TEXT(AA70,"#,##0")&" m para 4 meses"&IF(P70-E70>0," (ya contando pedidos)",""),IF(AND(-AA70>0.1*Y70,SUM(I70:M70)+IF($AD$3="SI",SUM(N70),0)>0),"PEDIR MENOS — sobran "&TEXT(-AA70,"#,##0")&" m; revisar pedidos sin facturar ("&TEXT(SUM(I70:M70)+IF($AD$3="SI",SUM(N70),0),"#,##0")&" m)",IF(Z70>8,"SOBRESTOCK — "&TEXT(Z70,"0.0")&" meses de cobertura","OK — cubierto ("&TEXT(Z70,"0.0")&" meses)")))))) -> COMPRAR — faltan 3,275 m para 4 meses (ya contando pedidos) | P70: =E70+N(F70)+SUM(G70:M70)+IF($AD$3="SI",SUM(N70),0) -> 4275 | X70: =IFERROR(VLOOKUP($A70,Ventas!$A$2:$L$5000,12,FALSE()),"") -> 1887.5 | Y70: =IF(X70="","",ROUND(X70*4,0)) -> 7550 | Z70: =IF(OR(X70="",X70=0),"",ROUND(P70/X70,1)) -> 2.3 | AA70: =IF(Y70="","",Y70-P70) -> 3275 | AB70: =IF(A70="","",IF(COUNTIF($A$8:$A$670,A70)>1,"DUPLICADO","")) | AC70: {=IF(AH70<>"COMPRAR","",IF(MAX(INDEX(Ventas!$G$2:$G$5000,MATCH($A70,Ventas!$A$2:$A$5000,0)),INDEX(Ventas!$H$2:$H$5000,MATCH($A70,Ventas!$A$2:$A$5000,0)),INDEX(Ventas!$I$2:$I$5000,MATCH($A70,Ventas!$A$2:$A$5000,0)),INDEX(Ventas!$J$2:$J$5000,MATCH($A70,Ventas!$A$2:$A$5000,0)))>0.5*AF70*4,"1 mes = "&TEXT(MAX(INDEX(Ventas!$G$2:$G$5000,MATCH($A70,Ventas!$A$2:$A$5000,0)),INDEX(Ventas!$H$2:$H$5000,MATCH($A70,Ventas!$A$2:$A$5000,0)),INDEX(Ventas!$I$2:$I$5000,MATCH($A70,Ventas!$A$2:$A$5000,0)),INDEX(Ventas!$J$2:$J$5000,MATCH($A70,Ventas!$A$2:$A$5000,0)))/(AF70*4),"0%")&" de 4 meses",""))} | AD70: =IF(OR(X70="",X70=0),"",IF(E70+N(F70)<X70*$AD$5,"SÍ — "&TEXT(E70+N(F70),"#,##0")&" m vs "&TEXT(X70*$AD$5,"#,##0")&" m","")) | AE70: {=IF(X70="","",IF(AND(E70=0,AVERAGE(INDEX(Ventas!$C$2:$I$5000,MATCH($A70,Ventas!$A$2:$A$5000,0),0))>0,INDEX(Ventas!$J$2:$J$5000,MATCH($A70,Ventas!$A$2:$A$5000,0))<0.5*AVERAGE(INDEX(Ventas!$C$2:$I$5000,MATCH($A70,Ventas!$A$2:$A$5000,0),0))),"SÍ — stock 0 y Sep cayó (prom Feb-Ago "&TEXT(AVERAGE(INDEX(Ventas!$C$2:$I$5000,MATCH($A70,Ventas!$A$2:$A$5000,0),0)),"#,##0")&")",""))} | AF70: {=IF(X70="","",IF(AE70<>"",MAX(X70,AVERAGE(INDEX(Ventas!$C$2:$I$5000,MATCH($A70,Ventas!$A$2:$A$5000,0),0))),X70))} -> 1887.5 | AG70: =IF(AF70="","",ROUND(AF70*4,0)-P70) -> 3275 | AH70: =IF(A70="","",IF(AF70="","SIN HISTORIAL",IF(AF70=0,"SIN VENTAS",IF(AG70>0.1*ROUND(AF70*4,0),"COMPRAR",IF(AND(-AG70>0.1*ROUND(AF70*4,0),SUM(I70:M70)+IF($AD$3="SI",SUM(N70),0)>0),"PEDIR MENOS",IF(P70/AF70>8,"SOBRESTOCK","OK")))))) -> COMPRAR
A71: 285127-0044 | B71: CAPELLADA | C71: NAPA | D71: MOCCA | E71: 3241 | O71: =IF(A71="","SIN SKU — cargar código para calcular",IF(X71="","SIN HISTORIAL DE VENTAS — artículo nuevo o código distinto en Ventas",IF(X71=0,IF(P71>0,"SIN VENTAS Jun-Sep — no comprar ("&TEXT(P71,"#,##0")&" m disponibles)","SIN VENTAS Jun-Sep — no comprar"),IF(AA71>0.1*Y71,"COMPRAR — faltan "&TEXT(AA71,"#,##0")&" m para 4 meses"&IF(P71-E71>0," (ya contando pedidos)",""),IF(AND(-AA71>0.1*Y71,SUM(I71:M71)+IF($AD$3="SI",SUM(N71),0)>0),"PEDIR MENOS — sobran "&TEXT(-AA71,"#,##0")&" m; revisar pedidos sin facturar ("&TEXT(SUM(I71:M71)+IF($AD$3="SI",SUM(N71),0),"#,##0")&" m)",IF(Z71>8,"SOBRESTOCK — "&TEXT(Z71,"0.0")&" meses de cobertura","OK — cubierto ("&TEXT(Z71,"0.0")&" meses)")))))) -> SOBRESTOCK — 20.2 meses de cobertura | P71: =E71+N(F71)+SUM(G71:M71)+IF($AD$3="SI",SUM(N71),0) -> 3241 | X71: =IFERROR(VLOOKUP($A71,Ventas!$A$2:$L$5000,12,FALSE()),"") -> 160.75 | Y71: =IF(X71="","",ROUND(X71*4,0)) -> 643 | Z71: =IF(OR(X71="",X71=0),"",ROUND(P71/X71,1)) -> 20.2 | AA71: =IF(Y71="","",Y71-P71) -> -2598 | AB71: =IF(A71="","",IF(COUNTIF($A$8:$A$670,A71)>1,"DUPLICADO","")) | AC71: {=IF(AH71<>"COMPRAR","",IF(MAX(INDEX(Ventas!$G$2:$G$5000,MATCH($A71,Ventas!$A$2:$A$5000,0)),INDEX(Ventas!$H$2:$H$5000,MATCH($A71,Ventas!$A$2:$A$5000,0)),INDEX(Ventas!$I$2:$I$5000,MATCH($A71,Ventas!$A$2:$A$5000,0)),INDEX(Ventas!$J$2:$J$5000,MATCH($A71,Ventas!$A$2:$A$5000,0)))>0.5*AF71*4,"1 mes = "&TEXT(MAX(INDEX(Ventas!$G$2:$G$5000,MATCH($A71,Ventas!$A$2:$A$5000,0)),INDEX(Ventas!$H$2:$H$5000,MATCH($A71,Ventas!$A$2:$A$5000,0)),INDEX(Ventas!$I$2:$I$5000,MATCH($A71,Ventas!$A$2:$A$5000,0)),INDEX(Ventas!$J$2:$J$5000,MATCH($A71,Ventas!$A$2:$A$5000,0)))/(AF71*4),"0%")&" de 4 meses",""))} | AD71: =IF(OR(X71="",X71=0),"",IF(E71+N(F71)<X71*$AD$5,"SÍ — "&TEXT(E71+N(F71),"#,##0")&" m vs "&TEXT(X71*$AD$5,"#,##0")&" m","")) | AE71: {=IF(X71="","",IF(AND(E71=0,AVERAGE(INDEX(Ventas!$C$2:$I$5000,MATCH($A71,Ventas!$A$2:$A$5000,0),0))>0,INDEX(Ventas!$J$2:$J$5000,MATCH($A71,Ventas!$A$2:$A$5000,0))<0.5*AVERAGE(INDEX(Ventas!$C$2:$I$5000,MATCH($A71,Ventas!$A$2:$A$5000,0),0))),"SÍ — stock 0 y Sep cayó (prom Feb-Ago "&TEXT(AVERAGE(INDEX(Ventas!$C$2:$I$5000,MATCH($A71,Ventas!$A$2:$A$5000,0),0)),"#,##0")&")",""))} | AF71: {=IF(X71="","",IF(AE71<>"",MAX(X71,AVERAGE(INDEX(Ventas!$C$2:$I$5000,MATCH($A71,Ventas!$A$2:$A$5000,0),0))),X71))} -> 160.75 | AG71: =IF(AF71="","",ROUND(AF71*4,0)-P71) -> -2598 | AH71: =IF(A71="","",IF(AF71="","SIN HISTORIAL",IF(AF71=0,"SIN VENTAS",IF(AG71>0.1*ROUND(AF71*4,0),"COMPRAR",IF(AND(-AG71>0.1*ROUND(AF71*4,0),SUM(I71:M71)+IF($AD$3="SI",SUM(N71),0)>0),"PEDIR MENOS",IF(P71/AF71>8,"SOBRESTOCK","OK")))))) -> SOBRESTOCK
A72: 285127-0004 | B72: CAPELLADA | C72: NAPA | D72: BORDO | E72: 0 | L72: 1500 | O72: =IF(A72="","SIN SKU — cargar código para calcular",IF(X72="","SIN HISTORIAL DE VENTAS — artículo nuevo o código distinto en Ventas",IF(X72=0,IF(P72>0,"SIN VENTAS Jun-Sep — no comprar ("&TEXT(P72,"#,##0")&" m disponibles)","SIN VENTAS Jun-Sep — no comprar"),IF(AA72>0.1*Y72,"COMPRAR — faltan "&TEXT(AA72,"#,##0")&" m para 4 meses"&IF(P72-E72>0," (ya contando pedidos)",""),IF(AND(-AA72>0.1*Y72,SUM(I72:M72)+IF($AD$3="SI",SUM(N72),0)>0),"PEDIR MENOS — sobran "&TEXT(-AA72,"#,##0")&" m; revisar pedidos sin facturar ("&TEXT(SUM(I72:M72)+IF($AD$3="SI",SUM(N72),0),"#,##0")&" m)",IF(Z72>8,"SOBRESTOCK — "&TEXT(Z72,"0.0")&" meses de cobertura","OK — cubierto ("&TEXT(Z72,"0.0")&" meses)")))))) -> PEDIR MENOS — sobran 570 m; revisar pedidos sin facturar (1,500 m) | P72: =E72+N(F72)+SUM(G72:M72)+IF($AD$3="SI",SUM(N72),0) -> 1500 | Q72: Noviembre y diciembre del 2025 no había stock, enero y febrero del 2026 entraron 3288 mts. No hay stock desde el julio 2026. | X72: =IFERROR(VLOOKUP($A72,Ventas!$A$2:$L$5000,12,FALSE()),"") -> 232.5 | Y72: =IF(X72="","",ROUND(X72*4,0)) -> 930 | Z72: =IF(OR(X72="",X72=0),"",ROUND(P72/X72,1)) -> 6.5 | AA72: =IF(Y72="","",Y72-P72) -> -570 | AB72: =IF(A72="","",IF(COUNTIF($A$8:$A$670,A72)>1,"DUPLICADO","")) | AC72: {=IF(AH72<>"COMPRAR","",IF(MAX(INDEX(Ventas!$G$2:$G$5000,MATCH($A72,Ventas!$A$2:$A$5000,0)),INDEX(Ventas!$H$2:$H$5000,MATCH($A72,Ventas!$A$2:$A$5000,0)),INDEX(Ventas!$I$2:$I$5000,MATCH($A72,Ventas!$A$2:$A$5000,0)),INDEX(Ventas!$J$2:$J$5000,MATCH($A72,Ventas!$A$2:$A$5000,0)))>0.5*AF72*4,"1 mes = "&TEXT(MAX(INDEX(Ventas!$G$2:$G$5000,MATCH($A72,Ventas!$A$2:$A$5000,0)),INDEX(Ventas!$H$2:$H$5000,MATCH($A72,Ventas!$A$2:$A$5000,0)),INDEX(Ventas!$I$2:$I$5000,MATCH($A72,Ventas!$A$2:$A$5000,0)),INDEX(Ventas!$J$2:$J$5000,MATCH($A72,Ventas!$A$2:$A$5000,0)))/(AF72*4),"0%")&" de 4 meses",""))} | AD72: =IF(OR(X72="",X72=0),"",IF(E72+N(F72)<X72*$AD$5,"SÍ — "&TEXT(E72+N(F72),"#,##0")&" m vs "&TEXT(X72*$AD$5,"#,##0")&" m","")) -> SÍ — 0 m vs 123 m | AE72: {=IF(X72="","",IF(AND(E72=0,AVERAGE(INDEX(Ventas!$C$2:$I$5000,MATCH($A72,Ventas!$A$2:$A$5000,0),0))>0,INDEX(Ventas!$J$2:$J$5000,MATCH($A72,Ventas!$A$2:$A$5000,0))<0.5*AVERAGE(INDEX(Ventas!$C$2:$I$5000,MATCH($A72,Ventas!$A$2:$A$5000,0),0))),"SÍ — stock 0 y Sep cayó (prom Feb-Ago "&TEXT(AVERAGE(INDEX(Ventas!$C$2:$I$5000,MATCH($A72,Ventas!$A$2:$A$5000,0),0)),"#,##0")&")",""))} -> SÍ — stock 0 y Sep cayó (prom Feb-Ago 435) | AF72: {=IF(X72="","",IF(AE72<>"",MAX(X72,AVERAGE(INDEX(Ventas!$C$2:$I$5000,MATCH($A72,Ventas!$A$2:$A$5000,0),0))),X72))} -> 434.57143 | AG72: =IF(AF72="","",ROUND(AF72*4,0)-P72) -> 238 | AH72: =IF(A72="","",IF(AF72="","SIN HISTORIAL",IF(AF72=0,"SIN VENTAS",IF(AG72>0.1*ROUND(AF72*4,0),"COMPRAR",IF(AND(-AG72>0.1*ROUND(AF72*4,0),SUM(I72:M72)+IF($AD$3="SI",SUM(N72),0)>0),"PEDIR MENOS",IF(P72/AF72>8,"SOBRESTOCK","OK")))))) -> COMPRAR
A73: 285127-0250 | B73: CAPELLADA | C73: NAPA | D73: TOMATE | E73: 440 | O73: =IF(A73="","SIN SKU — cargar código para calcular",IF(X73="","SIN HISTORIAL DE VENTAS — artículo nuevo o código distinto en Ventas",IF(X73=0,IF(P73>0,"SIN VENTAS Jun-Sep — no comprar ("&TEXT(P73,"#,##0")&" m disponibles)","SIN VENTAS Jun-Sep — no comprar"),IF(AA73>0.1*Y73,"COMPRAR — faltan "&TEXT(AA73,"#,##0")&" m para 4 meses"&IF(P73-E73>0," (ya contando pedidos)",""),IF(AND(-AA73>0.1*Y73,SUM(I73:M73)+IF($AD$3="SI",SUM(N73),0)>0),"PEDIR MENOS — sobran "&TEXT(-AA73,"#,##0")&" m; revisar pedidos sin facturar ("&TEXT(SUM(I73:M73)+IF($AD$3="SI",SUM(N73),0),"#,##0")&" m)",IF(Z73>8,"SOBRESTOCK — "&TEXT(Z73,"0.0")&" meses de cobertura","OK — cubierto ("&TEXT(Z73,"0.0")&" meses)")))))) -> SOBRESTOCK — 12.1 meses de cobertura | P73: =E73+N(F73)+SUM(G73:M73)+IF($AD$3="SI",SUM(N73),0) -> 440 | X73: =IFERROR(VLOOKUP($A73,Ventas!$A$2:$L$5000,12,FALSE()),"") -> 36.5 | Y73: =IF(X73="","",ROUND(X73*4,0)) -> 146 | Z73: =IF(OR(X73="",X73=0),"",ROUND(P73/X73,1)) -> 12.1 | AA73: =IF(Y73="","",Y73-P73) -> -294 | AB73: =IF(A73="","",IF(COUNTIF($A$8:$A$670,A73)>1,"DUPLICADO","")) | AC73: {=IF(AH73<>"COMPRAR","",IF(MAX(INDEX(Ventas!$G$2:$G$5000,MATCH($A73,Ventas!$A$2:$A$5000,0)),INDEX(Ventas!$H$2:$H$5000,MATCH($A73,Ventas!$A$2:$A$5000,0)),INDEX(Ventas!$I$2:$I$5000,MATCH($A73,Ventas!$A$2:$A$5000,0)),INDEX(Ventas!$J$2:$J$5000,MATCH($A73,Ventas!$A$2:$A$5000,0)))>0.5*AF73*4,"1 mes = "&TEXT(MAX(INDEX(Ventas!$G$2:$G$5000,MATCH($A73,Ventas!$A$2:$A$5000,0)),INDEX(Ventas!$H$2:$H$5000,MATCH($A73,Ventas!$A$2:$A$5000,0)),INDEX(Ventas!$I$2:$I$5000,MATCH($A73,Ventas!$A$2:$A$5000,0)),INDEX(Ventas!$J$2:$J$5000,MATCH($A73,Ventas!$A$2:$A$5000,0)))/(AF73*4),"0%")&" de 4 meses",""))} | AD73: =IF(OR(X73="",X73=0),"",IF(E73+N(F73)<X73*$AD$5,"SÍ — "&TEXT(E73+N(F73),"#,##0")&" m vs "&TEXT(X73*$AD$5,"#,##0")&" m","")) | AE73: {=IF(X73="","",IF(AND(E73=0,AVERAGE(INDEX(Ventas!$C$2:$I$5000,MATCH($A73,Ventas!$A$2:$A$5000,0),0))>0,INDEX(Ventas!$J$2:$J$5000,MATCH($A73,Ventas!$A$2:$A$5000,0))<0.5*AVERAGE(INDEX(Ventas!$C$2:$I$5000,MATCH($A73,Ventas!$A$2:$A$5000,0),0))),"SÍ — stock 0 y Sep cayó (prom Feb-Ago "&TEXT(AVERAGE(INDEX(Ventas!$C$2:$I$5000,MATCH($A73,Ventas!$A$2:$A$5000,0),0)),"#,##0")&")",""))} | AF73: {=IF(X73="","",IF(AE73<>"",MAX(X73,AVERAGE(INDEX(Ventas!$C$2:$I$5000,MATCH($A73,Ventas!$A$2:$A$5000,0),0))),X73))} -> 36.5 | AG73: =IF(AF73="","",ROUND(AF73*4,0)-P73) -> -294 | AH73: =IF(A73="","",IF(AF73="","SIN HISTORIAL",IF(AF73=0,"SIN VENTAS",IF(AG73>0.1*ROUND(AF73*4,0),"COMPRAR",IF(AND(-AG73>0.1*ROUND(AF73*4,0),SUM(I73:M73)+IF($AD$3="SI",SUM(N73),0)>0),"PEDIR MENOS",IF(P73/AF73>8,"SOBRESTOCK","OK")))))) -> SOBRESTOCK
A74: 285127-0259 | B74: CAPELLADA | C74: NAPA | D74: PRINT MIEL | E74: 632 | O74: =IF(A74="","SIN SKU — cargar código para calcular",IF(X74="","SIN HISTORIAL DE VENTAS — artículo nuevo o código distinto en Ventas",IF(X74=0,IF(P74>0,"SIN VENTAS Jun-Sep — no comprar ("&TEXT(P74,"#,##0")&" m disponibles)","SIN VENTAS Jun-Sep — no comprar"),IF(AA74>0.1*Y74,"COMPRAR — faltan "&TEXT(AA74,"#,##0")&" m para 4 meses"&IF(P74-E74>0," (ya contando pedidos)",""),IF(AND(-AA74>0.1*Y74,SUM(I74:M74)+IF($AD$3="SI",SUM(N74),0)>0),"PEDIR MENOS — sobran "&TEXT(-AA74,"#,##0")&" m; revisar pedidos sin facturar ("&TEXT(SUM(I74:M74)+IF($AD$3="SI",SUM(N74),0),"#,##0")&" m)",IF(Z74>8,"SOBRESTOCK — "&TEXT(Z74,"0.0")&" meses de cobertura","OK — cubierto ("&TEXT(Z74,"0.0")&" meses)")))))) -> SOBRESTOCK — 8.4 meses de cobertura | P74: =E74+N(F74)+SUM(G74:M74)+IF($AD$3="SI",SUM(N74),0) -> 632 | X74: =IFERROR(VLOOKUP($A74,Ventas!$A$2:$L$5000,12,FALSE()),"") -> 75 | Y74: =IF(X74="","",ROUND(X74*4,0)) -> 300 | Z74: =IF(OR(X74="",X74=0),"",ROUND(P74/X74,1)) -> 8.4 | AA74: =IF(Y74="","",Y74-P74) -> -332 | AB74: =IF(A74="","",IF(COUNTIF($A$8:$A$670,A74)>1,"DUPLICADO","")) | AC74: {=IF(AH74<>"COMPRAR","",IF(MAX(INDEX(Ventas!$G$2:$G$5000,MATCH($A74,Ventas!$A$2:$A$5000,0)),INDEX(Ventas!$H$2:$H$5000,MATCH($A74,Ventas!$A$2:$A$5000,0)),INDEX(Ventas!$I$2:$I$5000,MATCH($A74,Ventas!$A$2:$A$5000,0)),INDEX(Ventas!$J$2:$J$5000,MATCH($A74,Ventas!$A$2:$A$5000,0)))>0.5*AF74*4,"1 mes = "&TEXT(MAX(INDEX(Ventas!$G$2:$G$5000,MATCH($A74,Ventas!$A$2:$A$5000,0)),INDEX(Ventas!$H$2:$H$5000,MATCH($A74,Ventas!$A$2:$A$5000,0)),INDEX(Ventas!$I$2:$I$5000,MATCH($A74,Ventas!$A$2:$A$5000,0)),INDEX(Ventas!$J$2:$J$5000,MATCH($A74,Ventas!$A$2:$A$5000,0)))/(AF74*4),"0%")&" de 4 meses",""))} | AD74: =IF(OR(X74="",X74=0),"",IF(E74+N(F74)<X74*$AD$5,"SÍ — "&TEXT(E74+N(F74),"#,##0")&" m vs "&TEXT(X74*$AD$5,"#,##0")&" m","")) | AE74: {=IF(X74="","",IF(AND(E74=0,AVERAGE(INDEX(Ventas!$C$2:$I$5000,MATCH($A74,Ventas!$A$2:$A$5000,0),0))>0,INDEX(Ventas!$J$2:$J$5000,MATCH($A74,Ventas!$A$2:$A$5000,0))<0.5*AVERAGE(INDEX(Ventas!$C$2:$I$5000,MATCH($A74,Ventas!$A$2:$A$5000,0),0))),"SÍ — stock 0 y Sep cayó (prom Feb-Ago "&TEXT(AVERAGE(INDEX(Ventas!$C$2:$I$5000,MATCH($A74,Ventas!$A$2:$A$5000,0),0)),"#,##0")&")",""))} | AF74: {=IF(X74="","",IF(AE74<>"",MAX(X74,AVERAGE(INDEX(Ventas!$C$2:$I$5000,MATCH($A74,Ventas!$A$2:$A$5000,0),0))),X74))} -> 75 | AG74: =IF(AF74="","",ROUND(AF74*4,0)-P74) -> -332 | AH74: =IF(A74="","",IF(AF74="","SIN HISTORIAL",IF(AF74=0,"SIN VENTAS",IF(AG74>0.1*ROUND(AF74*4,0),"COMPRAR",IF(AND(-AG74>0.1*ROUND(AF74*4,0),SUM(I74:M74)+IF($AD$3="SI",SUM(N74),0)>0),"PEDIR MENOS",IF(P74/AF74>8,"SOBRESTOCK","OK")))))) -> SOBRESTOCK
A75: 285127-0258 | B75: CAPELLADA | C75: NAPA | D75: PRINT BLANCO | E75: 638 | O75: =IF(A75="","SIN SKU — cargar código para calcular",IF(X75="","SIN HISTORIAL DE VENTAS — artículo nuevo o código distinto en Ventas",IF(X75=0,IF(P75>0,"SIN VENTAS Jun-Sep — no comprar ("&TEXT(P75,"#,##0")&" m disponibles)","SIN VENTAS Jun-Sep — no comprar"),IF(AA75>0.1*Y75,"COMPRAR — faltan "&TEXT(AA75,"#,##0")&" m para 4 meses"&IF(P75-E75>0," (ya contando pedidos)",""),IF(AND(-AA75>0.1*Y75,SUM(I75:M75)+IF($AD$3="SI",SUM(N75),0)>0),"PEDIR MENOS — sobran "&TEXT(-AA75,"#,##0")&" m; revisar pedidos sin facturar ("&TEXT(SUM(I75:M75)+IF($AD$3="SI",SUM(N75),0),"#,##0")&" m)",IF(Z75>8,"SOBRESTOCK — "&TEXT(Z75,"0.0")&" meses de cobertura","OK — cubierto ("&TEXT(Z75,"0.0")&" meses)")))))) -> SOBRESTOCK — 51.0 meses de cobertura | P75: =E75+N(F75)+SUM(G75:M75)+IF($AD$3="SI",SUM(N75),0) -> 638 | X75: =IFERROR(VLOOKUP($A75,Ventas!$A$2:$L$5000,12,FALSE()),"") -> 12.5 | Y75: =IF(X75="","",ROUND(X75*4,0)) -> 50 | Z75: =IF(OR(X75="",X75=0),"",ROUND(P75/X75,1)) -> 51 | AA75: =IF(Y75="","",Y75-P75) -> -588 | AB75: =IF(A75="","",IF(COUNTIF($A$8:$A$670,A75)>1,"DUPLICADO","")) | AC75: {=IF(AH75<>"COMPRAR","",IF(MAX(INDEX(Ventas!$G$2:$G$5000,MATCH($A75,Ventas!$A$2:$A$5000,0)),INDEX(Ventas!$H$2:$H$5000,MATCH($A75,Ventas!$A$2:$A$5000,0)),INDEX(Ventas!$I$2:$I$5000,MATCH($A75,Ventas!$A$2:$A$5000,0)),INDEX(Ventas!$J$2:$J$5000,MATCH($A75,Ventas!$A$2:$A$5000,0)))>0.5*AF75*4,"1 mes = "&TEXT(MAX(INDEX(Ventas!$G$2:$G$5000,MATCH($A75,Ventas!$A$2:$A$5000,0)),INDEX(Ventas!$H$2:$H$5000,MATCH($A75,Ventas!$A$2:$A$5000,0)),INDEX(Ventas!$I$2:$I$5000,MATCH($A75,Ventas!$A$2:$A$5000,0)),INDEX(Ventas!$J$2:$J$5000,MATCH($A75,Ventas!$A$2:$A$5000,0)))/(AF75*4),"0%")&" de 4 meses",""))} | AD75: =IF(OR(X75="",X75=0),"",IF(E75+N(F75)<X75*$AD$5,"SÍ — "&TEXT(E75+N(F75),"#,##0")&" m vs "&TEXT(X75*$AD$5,"#,##0")&" m","")) | AE75: {=IF(X75="","",IF(AND(E75=0,AVERAGE(INDEX(Ventas!$C$2:$I$5000,MATCH($A75,Ventas!$A$2:$A$5000,0),0))>0,INDEX(Ventas!$J$2:$J$5000,MATCH($A75,Ventas!$A$2:$A$5000,0))<0.5*AVERAGE(INDEX(Ventas!$C$2:$I$5000,MATCH($A75,Ventas!$A$2:$A$5000,0),0))),"SÍ — stock 0 y Sep cayó (prom Feb-Ago "&TEXT(AVERAGE(INDEX(Ventas!$C$2:$I$5000,MATCH($A75,Ventas!$A$2:$A$5000,0),0)),"#,##0")&")",""))} | AF75: {=IF(X75="","",IF(AE75<>"",MAX(X75,AVERAGE(INDEX(Ventas!$C$2:$I$5000,MATCH($A75,Ventas!$A$2:$A$5000,0),0))),X75))} -> 12.5 | AG75: =IF(AF75="","",ROUND(AF75*4,0)-P75) -> -588 | AH75: =IF(A75="","",IF(AF75="","SIN HISTORIAL",IF(AF75=0,"SIN VENTAS",IF(AG75>0.1*ROUND(AF75*4,0),"COMPRAR",IF(AND(-AG75>0.1*ROUND(AF75*4,0),SUM(I75:M75)+IF($AD$3="SI",SUM(N75),0)>0),"PEDIR MENOS",IF(P75/AF75>8,"SOBRESTOCK","OK")))))) -> SOBRESTOCK
B76: CAPELLADA | C76: NAPA ELASTIZADA | D76: NEGRO | L76: 2000 | O76: =IF(A76="","SIN SKU — cargar código para calcular",IF(X76="","SIN HISTORIAL DE VENTAS — artículo nuevo o código distinto en Ventas",IF(X76=0,IF(P76>0,"SIN VENTAS Jun-Sep — no comprar ("&TEXT(P76,"#,##0")&" m disponibles)","SIN VENTAS Jun-Sep — no comprar"),IF(AA76>0.1*Y76,"COMPRAR — faltan "&TEXT(AA76,"#,##0")&" m para 4 meses"&IF(P76-E76>0," (ya contando pedidos)",""),IF(AND(-AA76>0.1*Y76,SUM(I76:M76)+IF($AD$3="SI",SUM(N76),0)>0),"PEDIR MENOS — sobran "&TEXT(-AA76,"#,##0")&" m; revisar pedidos sin facturar ("&TEXT(SUM(I76:M76)+IF($AD$3="SI",SUM(N76),0),"#,##0")&" m)",IF(Z76>8,"SOBRESTOCK — "&TEXT(Z76,"0.0")&" meses de cobertura","OK — cubierto ("&TEXT(Z76,"0.0")&" meses)")))))) -> SIN SKU — cargar código para calcular | P76: =E76+N(F76)+SUM(G76:M76)+IF($AD$3="SI",SUM(N76),0) -> 2000 | X76: =IFERROR(VLOOKUP($A76,Ventas!$A$2:$L$5000,12,FALSE()),"") | Y76: =IF(X76="","",ROUND(X76*4,0)) | Z76: =IF(OR(X76="",X76=0),"",ROUND(P76/X76,1)) | AA76: =IF(Y76="","",Y76-P76) | AB76: =IF(A76="","",IF(COUNTIF($A$8:$A$670,A76)>1,"DUPLICADO","")) | AC76: {=IF(AH76<>"COMPRAR","",IF(MAX(INDEX(Ventas!$G$2:$G$5000,MATCH($A76,Ventas!$A$2:$A$5000,0)),INDEX(Ventas!$H$2:$H$5000,MATCH($A76,Ventas!$A$2:$A$5000,0)),INDEX(Ventas!$I$2:$I$5000,MATCH($A76,Ventas!$A$2:$A$5000,0)),INDEX(Ventas!$J$2:$J$5000,MATCH($A76,Ventas!$A$2:$A$5000,0)))>0.5*AF76*4,"1 mes = "&TEXT(MAX(INDEX(Ventas!$G$2:$G$5000,MATCH($A76,Ventas!$A$2:$A$5000,0)),INDEX(Ventas!$H$2:$H$5000,MATCH($A76,Ventas!$A$2:$A$5000,0)),INDEX(Ventas!$I$2:$I$5000,MATCH($A76,Ventas!$A$2:$A$5000,0)),INDEX(Ventas!$J$2:$J$5000,MATCH($A76,Ventas!$A$2:$A$5000,0)))/(AF76*4),"0%")&" de 4 meses",""))} | AD76: =IF(OR(X76="",X76=0),"",IF(E76+N(F76)<X76*$AD$5,"SÍ — "&TEXT(E76+N(F76),"#,##0")&" m vs "&TEXT(X76*$AD$5,"#,##0")&" m","")) | AE76: {=IF(X76="","",IF(AND(E76=0,AVERAGE(INDEX(Ventas!$C$2:$I$5000,MATCH($A76,Ventas!$A$2:$A$5000,0),0))>0,INDEX(Ventas!$J$2:$J$5000,MATCH($A76,Ventas!$A$2:$A$5000,0))<0.5*AVERAGE(INDEX(Ventas!$C$2:$I$5000,MATCH($A76,Ventas!$A$2:$A$5000,0),0))),"SÍ — stock 0 y Sep cayó (prom Feb-Ago "&TEXT(AVERAGE(INDEX(Ventas!$C$2:$I$5000,MATCH($A76,Ventas!$A$2:$A$5000,0),0)),"#,##0")&")",""))} | AF76: {=IF(X76="","",IF(AE76<>"",MAX(X76,AVERAGE(INDEX(Ventas!$C$2:$I$5000,MATCH($A76,Ventas!$A$2:$A$5000,0),0))),X76))} | AG76: =IF(AF76="","",ROUND(AF76*4,0)-P76) | AH76: =IF(A76="","",IF(AF76="","SIN HISTORIAL",IF(AF76=0,"SIN VENTAS",IF(AG76>0.1*ROUND(AF76*4,0),"COMPRAR",IF(AND(-AG76>0.1*ROUND(AF76*4,0),SUM(I76:M76)+IF($AD$3="SI",SUM(N76),0)>0),"PEDIR MENOS",IF(P76/AF76>8,"SOBRESTOCK","OK"))))))
B77: CAPELLADA | C77: NAPA ELASTIZADA | D77: CARAMELO | O77: =IF(A77="","SIN SKU — cargar código para calcular",IF(X77="","SIN HISTORIAL DE VENTAS — artículo nuevo o código distinto en Ventas",IF(X77=0,IF(P77>0,"SIN VENTAS Jun-Sep — no comprar ("&TEXT(P77,"#,##0")&" m disponibles)","SIN VENTAS Jun-Sep — no comprar"),IF(AA77>0.1*Y77,"COMPRAR — faltan "&TEXT(AA77,"#,##0")&" m para 4 meses"&IF(P77-E77>0," (ya contando pedidos)",""),IF(AND(-AA77>0.1*Y77,SUM(I77:M77)+IF($AD$3="SI",SUM(N77),0)>0),"PEDIR MENOS — sobran "&TEXT(-AA77,"#,##0")&" m; revisar pedidos sin facturar ("&TEXT(SUM(I77:M77)+IF($AD$3="SI",SUM(N77),0),"#,##0")&" m)",IF(Z77>8,"SOBRESTOCK — "&TEXT(Z77,"0.0")&" meses de cobertura","OK — cubierto ("&TEXT(Z77,"0.0")&" meses)")))))) -> SIN SKU — cargar código para calcular | P77: =E77+N(F77)+SUM(G77:M77)+IF($AD$3="SI",SUM(N77),0) -> 0 | X77: =IFERROR(VLOOKUP($A77,Ventas!$A$2:$L$5000,12,FALSE()),"") | Y77: =IF(X77="","",ROUND(X77*4,0)) | Z77: =IF(OR(X77="",X77=0),"",ROUND(P77/X77,1)) | AA77: =IF(Y77="","",Y77-P77) | AB77: =IF(A77="","",IF(COUNTIF($A$8:$A$670,A77)>1,"DUPLICADO","")) | AC77: {=IF(AH77<>"COMPRAR","",IF(MAX(INDEX(Ventas!$G$2:$G$5000,MATCH($A77,Ventas!$A$2:$A$5000,0)),INDEX(Ventas!$H$2:$H$5000,MATCH($A77,Ventas!$A$2:$A$5000,0)),INDEX(Ventas!$I$2:$I$5000,MATCH($A77,Ventas!$A$2:$A$5000,0)),INDEX(Ventas!$J$2:$J$5000,MATCH($A77,Ventas!$A$2:$A$5000,0)))>0.5*AF77*4,"1 mes = "&TEXT(MAX(INDEX(Ventas!$G$2:$G$5000,MATCH($A77,Ventas!$A$2:$A$5000,0)),INDEX(Ventas!$H$2:$H$5000,MATCH($A77,Ventas!$A$2:$A$5000,0)),INDEX(Ventas!$I$2:$I$5000,MATCH($A77,Ventas!$A$2:$A$5000,0)),INDEX(Ventas!$J$2:$J$5000,MATCH($A77,Ventas!$A$2:$A$5000,0)))/(AF77*4),"0%")&" de 4 meses",""))} | AD77: =IF(OR(X77="",X77=0),"",IF(E77+N(F77)<X77*$AD$5,"SÍ — "&TEXT(E77+N(F77),"#,##0")&" m vs "&TEXT(X77*$AD$5,"#,##0")&" m","")) | AE77: {=IF(X77="","",IF(AND(E77=0,AVERAGE(INDEX(Ventas!$C$2:$I$5000,MATCH($A77,Ventas!$A$2:$A$5000,0),0))>0,INDEX(Ventas!$J$2:$J$5000,MATCH($A77,Ventas!$A$2:$A$5000,0))<0.5*AVERAGE(INDEX(Ventas!$C$2:$I$5000,MATCH($A77,Ventas!$A$2:$A$5000,0),0))),"SÍ — stock 0 y Sep cayó (prom Feb-Ago "&TEXT(AVERAGE(INDEX(Ventas!$C$2:$I$5000,MATCH($A77,Ventas!$A$2:$A$5000,0),0)),"#,##0")&")",""))} | AF77: {=IF(X77="","",IF(AE77<>"",MAX(X77,AVERAGE(INDEX(Ventas!$C$2:$I$5000,MATCH($A77,Ventas!$A$2:$A$5000,0),0))),X77))} | AG77: =IF(AF77="","",ROUND(AF77*4,0)-P77) | AH77: =IF(A77="","",IF(AF77="","SIN HISTORIAL",IF(AF77=0,"SIN VENTAS",IF(AG77>0.1*ROUND(AF77*4,0),"COMPRAR",IF(AND(-AG77>0.1*ROUND(AF77*4,0),SUM(I77:M77)+IF($AD$3="SI",SUM(N77),0)>0),"PEDIR MENOS",IF(P77/AF77>8,"SOBRESTOCK","OK"))))))
B78: CAPELLADA | C78: NAPA ELASTIZADA | D78: MIEL | O78: =IF(A78="","SIN SKU — cargar código para calcular",IF(X78="","SIN HISTORIAL DE VENTAS — artículo nuevo o código distinto en Ventas",IF(X78=0,IF(P78>0,"SIN VENTAS Jun-Sep — no comprar ("&TEXT(P78,"#,##0")&" m disponibles)","SIN VENTAS Jun-Sep — no comprar"),IF(AA78>0.1*Y78,"COMPRAR — faltan "&TEXT(AA78,"#,##0")&" m para 4 meses"&IF(P78-E78>0," (ya contando pedidos)",""),IF(AND(-AA78>0.1*Y78,SUM(I78:M78)+IF($AD$3="SI",SUM(N78),0)>0),"PEDIR MENOS — sobran "&TEXT(-AA78,"#,##0")&" m; revisar pedidos sin facturar ("&TEXT(SUM(I78:M78)+IF($AD$3="SI",SUM(N78),0),"#,##0")&" m)",IF(Z78>8,"SOBRESTOCK — "&TEXT(Z78,"0.0")&" meses de cobertura","OK — cubierto ("&TEXT(Z78,"0.0")&" meses)")))))) -> SIN SKU — cargar código para calcular | P78: =E78+N(F78)+SUM(G78:M78)+IF($AD$3="SI",SUM(N78),0) -> 0 | X78: =IFERROR(VLOOKUP($A78,Ventas!$A$2:$L$5000,12,FALSE()),"") | Y78: =IF(X78="","",ROUND(X78*4,0)) | Z78: =IF(OR(X78="",X78=0),"",ROUND(P78/X78,1)) | AA78: =IF(Y78="","",Y78-P78) | AB78: =IF(A78="","",IF(COUNTIF($A$8:$A$670,A78)>1,"DUPLICADO","")) | AC78: {=IF(AH78<>"COMPRAR","",IF(MAX(INDEX(Ventas!$G$2:$G$5000,MATCH($A78,Ventas!$A$2:$A$5000,0)),INDEX(Ventas!$H$2:$H$5000,MATCH($A78,Ventas!$A$2:$A$5000,0)),INDEX(Ventas!$I$2:$I$5000,MATCH($A78,Ventas!$A$2:$A$5000,0)),INDEX(Ventas!$J$2:$J$5000,MATCH($A78,Ventas!$A$2:$A$5000,0)))>0.5*AF78*4,"1 mes = "&TEXT(MAX(INDEX(Ventas!$G$2:$G$5000,MATCH($A78,Ventas!$A$2:$A$5000,0)),INDEX(Ventas!$H$2:$H$5000,MATCH($A78,Ventas!$A$2:$A$5000,0)),INDEX(Ventas!$I$2:$I$5000,MATCH($A78,Ventas!$A$2:$A$5000,0)),INDEX(Ventas!$J$2:$J$5000,MATCH($A78,Ventas!$A$2:$A$5000,0)))/(AF78*4),"0%")&" de 4 meses",""))} | AD78: =IF(OR(X78="",X78=0),"",IF(E78+N(F78)<X78*$AD$5,"SÍ — "&TEXT(E78+N(F78),"#,##0")&" m vs "&TEXT(X78*$AD$5,"#,##0")&" m","")) | AE78: {=IF(X78="","",IF(AND(E78=0,AVERAGE(INDEX(Ventas!$C$2:$I$5000,MATCH($A78,Ventas!$A$2:$A$5000,0),0))>0,INDEX(Ventas!$J$2:$J$5000,MATCH($A78,Ventas!$A$2:$A$5000,0))<0.5*AVERAGE(INDEX(Ventas!$C$2:$I$5000,MATCH($A78,Ventas!$A$2:$A$5000,0),0))),"SÍ — stock 0 y Sep cayó (prom Feb-Ago "&TEXT(AVERAGE(INDEX(Ventas!$C$2:$I$5000,MATCH($A78,Ventas!$A$2:$A$5000,0),0)),"#,##0")&")",""))} | AF78: {=IF(X78="","",IF(AE78<>"",MAX(X78,AVERAGE(INDEX(Ventas!$C$2:$I$5000,MATCH($A78,Ventas!$A$2:$A$5000,0),0))),X78))} | AG78: =IF(AF78="","",ROUND(AF78*4,0)-P78) | AH78: =IF(A78="","",IF(AF78="","SIN HISTORIAL",IF(AF78=0,"SIN VENTAS",IF(AG78>0.1*ROUND(AF78*4,0),"COMPRAR",IF(AND(-AG78>0.1*ROUND(AF78*4,0),SUM(I78:M78)+IF($AD$3="SI",SUM(N78),0)>0),"PEDIR MENOS",IF(P78/AF78>8,"SOBRESTOCK","OK"))))))
B79: CAPELLADA | C79: NAPA ELASTIZADA | D79: CHOCOLATE | O79: =IF(A79="","SIN SKU — cargar código para calcular",IF(X79="","SIN HISTORIAL DE VENTAS — artículo nuevo o código distinto en Ventas",IF(X79=0,IF(P79>0,"SIN VENTAS Jun-Sep — no comprar ("&TEXT(P79,"#,##0")&" m disponibles)","SIN VENTAS Jun-Sep — no comprar"),IF(AA79>0.1*Y79,"COMPRAR — faltan "&TEXT(AA79,"#,##0")&" m para 4 meses"&IF(P79-E79>0," (ya contando pedidos)",""),IF(AND(-AA79>0.1*Y79,SUM(I79:M79)+IF($AD$3="SI",SUM(N79),0)>0),"PEDIR MENOS — sobran "&TEXT(-AA79,"#,##0")&" m; revisar pedidos sin facturar ("&TEXT(SUM(I79:M79)+IF($AD$3="SI",SUM(N79),0),"#,##0")&" m)",IF(Z79>8,"SOBRESTOCK — "&TEXT(Z79,"0.0")&" meses de cobertura","OK — cubierto ("&TEXT(Z79,"0.0")&" meses)")))))) -> SIN SKU — cargar código para calcular | P79: =E79+N(F79)+SUM(G79:M79)+IF($AD$3="SI",SUM(N79),0) -> 0 | X79: =IFERROR(VLOOKUP($A79,Ventas!$A$2:$L$5000,12,FALSE()),"") | Y79: =IF(X79="","",ROUND(X79*4,0)) | Z79: =IF(OR(X79="",X79=0),"",ROUND(P79/X79,1)) | AA79: =IF(Y79="","",Y79-P79) | AB79: =IF(A79="","",IF(COUNTIF($A$8:$A$670,A79)>1,"DUPLICADO","")) | AC79: {=IF(AH79<>"COMPRAR","",IF(MAX(INDEX(Ventas!$G$2:$G$5000,MATCH($A79,Ventas!$A$2:$A$5000,0)),INDEX(Ventas!$H$2:$H$5000,MATCH($A79,Ventas!$A$2:$A$5000,0)),INDEX(Ventas!$I$2:$I$5000,MATCH($A79,Ventas!$A$2:$A$5000,0)),INDEX(Ventas!$J$2:$J$5000,MATCH($A79,Ventas!$A$2:$A$5000,0)))>0.5*AF79*4,"1 mes = "&TEXT(MAX(INDEX(Ventas!$G$2:$G$5000,MATCH($A79,Ventas!$A$2:$A$5000,0)),INDEX(Ventas!$H$2:$H$5000,MATCH($A79,Ventas!$A$2:$A$5000,0)),INDEX(Ventas!$I$2:$I$5000,MATCH($A79,Ventas!$A$2:$A$5000,0)),INDEX(Ventas!$J$2:$J$5000,MATCH($A79,Ventas!$A$2:$A$5000,0)))/(AF79*4),"0%")&" de 4 meses",""))} | AD79: =IF(OR(X79="",X79=0),"",IF(E79+N(F79)<X79*$AD$5,"SÍ — "&TEXT(E79+N(F79),"#,##0")&" m vs "&TEXT(X79*$AD$5,"#,##0")&" m","")) | AE79: {=IF(X79="","",IF(AND(E79=0,AVERAGE(INDEX(Ventas!$C$2:$I$5000,MATCH($A79,Ventas!$A$2:$A$5000,0),0))>0,INDEX(Ventas!$J$2:$J$5000,MATCH($A79,Ventas!$A$2:$A$5000,0))<0.5*AVERAGE(INDEX(Ventas!$C$2:$I$5000,MATCH($A79,Ventas!$A$2:$A$5000,0),0))),"SÍ — stock 0 y Sep cayó (prom Feb-Ago "&TEXT(AVERAGE(INDEX(Ventas!$C$2:$I$5000,MATCH($A79,Ventas!$A$2:$A$5000,0),0)),"#,##0")&")",""))} | AF79: {=IF(X79="","",IF(AE79<>"",MAX(X79,AVERAGE(INDEX(Ventas!$C$2:$I$5000,MATCH($A79,Ventas!$A$2:$A$5000,0),0))),X79))} | AG79: =IF(AF79="","",ROUND(AF79*4,0)-P79) | AH79: =IF(A79="","",IF(AF79="","SIN HISTORIAL",IF(AF79=0,"SIN VENTAS",IF(AG79>0.1*ROUND(AF79*4,0),"COMPRAR",IF(AND(-AG79>0.1*ROUND(AF79*4,0),SUM(I79:M79)+IF($AD$3="SI",SUM(N79),0)>0),"PEDIR MENOS",IF(P79/AF79>8,"SOBRESTOCK","OK"))))))
